{"errno":0,"data":[{"new_title_basic_seg_list":["勇士","王朝","崩坏","导火索","？","格林","辱骂","杜兰特","，","看","美","球迷","如何","评价","他们","？"],"quality_grade":2,"is_high_quality_res":0,"nid":"16736811619630306176","prior_antispam_tag":{},"type_setting_basic_feature":{"valid_image_media_type_number":1,"is_good_clarity":false,"valid_bjh_type_number":0,"text_para_density":false,"valid_image_media_number":0,"heading_rich":false,"valid_customer_subtitle_number":0,"is_through_the_subtitle":false,"valid_bjh_number":0,"valid_customer_subtitle_type_number":0,"text_image_inter_good":0,"is_clarity":true,"rich_media_types":false},"novelty_sim_docs":[],"nlpc_title_ner":["看","评价"],"news_clickbait_score":0.000675097,"news_category_prob":0.790362,"click_estimate_level":0,"novelty_rtg_time":1542208951,"rule_quality_reason":1000,"image_sign":"[{\"image_id\":\"FFE1AE2F_513748F6\",\"sign\":\"2DB0209CB48F0EEC3AA07586030080A0\"},{\"image_id\":\"F6322A56_3B95D8C1\",\"sign\":\"4B10498A4D9007E95268259903001093\"},{\"image_id\":\"F10E224F_3BE3371D\",\"sign\":\"8B200089449A17ED86E1808C03003003\"},{\"image_id\":\"0753E240_948DD60D\",\"sign\":\"6EE2208C7C53BCD05EA496830300B087\"}]\n","filter_reason":"bs_filter:brief bs filter","url_type":1,"news_title_attraction_level":1,"res_title_sign":"589597 1080522733","time_dis":[],"author_authority_score_v1_from":{},"title_pure":"勇士王朝崩坏导火索？格林辱骂杜兰特，看美球迷如何评价他们？","news_category_v2":"体育","news_category_v1":"体育","plsa3000":{"2537":317,"2965":654,"1776":749,"1423":505,"554":535,"2486":597,"2385":334,"1053":321,"2472":366,"1603":436},"high_quality_repo":{"rewrite_times":2,"is_platform_high_quality":0,"is_push":0,"timeliness":172800,"is_topic_data":0,"push_source":0,"quality_score":{"final_score":2,"after_score":2,"prev_score":2},"is_hqv2_data":1,"is_listen_data":0,"is_tup2_data":0,"is_group_data":0,"is_explore_data":0},"low_matching_score":0.3140483075899692,"display_url":"","feature_mapping":{"http://t12.baidu.com/it/u=3111758387,809779261&fm=173&app=25&f=JPEG?w=218&h=146&s=29B0209CB68F0EEC3AA07586030080A0":{"original_src":"http://5b0988e595225.cdn.sohucs.com/images/20181114/aaf6325e64814428b9503de93a8e54d1.jpeg","feature_970_topn":[{"val":0.87401378154755,"cid":196},{"val":0.058382924646139,"cid":194},{"val":0.022879371419549,"cid":201},{"val":0.013506608083844,"cid":216},{"val":0.002613123273477,"cid":218}]},"http://t11.baidu.com/it/u=1379924773,2240087527&fm=173&app=25&f=JPEG?w=218&h=146&s=2EA3208C6C53BEDC5CA416830300E08F":{"original_src":"http://5b0988e595225.cdn.sohucs.com/images/20181114/b4cd5d3e631d4995aee168a31c61b3eb.jpeg","feature_970_topn":[{"val":0.68148899078369,"cid":196},{"val":0.2935982644558,"cid":201},{"val":0.0082486197352409,"cid":212},{"val":0.0048978864215314,"cid":194},{"val":0.0043523418717086,"cid":216}]},"http://t11.baidu.com/it/u=980303476,3546484602&fm=173&app=25&f=JPEG?w=218&h=146&s=4B02498A4D9007E95268259903008093":{"original_src":"http://5b0988e595225.cdn.sohucs.com/images/20181114/9535b4613bef41d5baa22c1e73dfc8bc.jpeg","feature_970_topn":[{"val":0.72940051555634,"cid":201},{"val":0.062286946922541,"cid":188},{"val":0.055911667644978,"cid":212},{"val":0.034509669989347,"cid":196},{"val":0.024747719988227,"cid":194}]},"http://t12.baidu.com/it/u=184648805,3595241792&fm=173&app=25&f=JPEG?w=218&h=146&s=832004A8449A17ED86E1808C03003003":{"original_src":"http://5b0988e595225.cdn.sohucs.com/images/20181114/49ce736cf9454e29b7766e03b4b4ad3b.jpeg","feature_970_topn":[{"val":0.50611311197281,"cid":201},{"val":0.3828592300415,"cid":196},{"val":0.080235049128532,"cid":212},{"val":0.0097663076594472,"cid":213},{"val":0.0036623657215387,"cid":217}]}},"m_public_time":"1542208951","media_subCategory_id":0,"readable_level":2,"conserve_type":2,"mthid":"","recommend":0,"meta_keywords":"","novelty_feed_all_sim":0.0,"cont_xpath_type":"0","res_content_sign":"589597 1080522733","term":{"格林":184,"全明星":21,"汤普森":22,"勇士队":24,"球迷":77,"杜兰特":107,"科尔":24,"王朝":45,"崩坏":42,"勇士":67},"ad_recognition_reason":{"hot_flag":true,"ad_level":0,"pincou_flag":false,"matched_rule":"","white_rule":"","matched_dict_type":"","hot_msg":["杜兰特"],"white_dict_type":""},"url_level":0,"news_score":0.798,"novelty_imgs_real_time":{},"plsa30":{"22":184,"1":4255,"13":159,"2":1429,"26":347,"4":138,"28":159,"29":138,"7":542,"10":161},"kg_resource_tag_index":{},"new_title_phrase_seg_list":["勇士","王朝","崩坏","导火索","？","格林","辱骂","杜兰特","，","看","美","球迷","如何","评价","他们","？"],"innersource_id":"","news_style_ext_info":{},"sex_score":0.03609800245934769,"author_health_score":-1,"quality_score":{"final_score":2,"after_score":2,"prev_score":2},"news_style_gamma":[],"category_sign":1599734263,"tj_lda_square":109.9499886311954,"porn_score":0.00272727,"plsa300":{"232":501,"58":699,"49":496,"116":533,"190":371,"208":524,"160":341,"130":380,"141":1325,"142":2068},"m_content_type":"1","tag_intr_term":{"终结":0.0,"格林和":1.168839453601117,"令人难以置信":1.0,"全明星":1.780936184878545,"汤普森":1.86376194489842,"宣告":0.0,"合同":0.6971267052238779,"勇士":3.753411910716307,"小白文":1.0,"历来":0.0,"小婊砸":1.0,"场上":0.0,"场下":0.0,"大前锋":1.0,"快船":0.7328007097253889,"评价":0.0,"全民":1.0,"铁腕":1.0,"湖人":1.0,"瓦解":0.0,"寡言":0.0,"顶薪合同":0.6971267052238779,"点子":1.0,"置信":0.0,"惊天动地":0.0,"弱旅":1.0,"口角":0.7526766210460356,"内讧":0.7708636522872764,"这件事":1.490159894241352,"崩坏":0.9850409866045096,"发酵":0.0,"想法":0.7663637188655157,"鲁莽":0.0,"露水":1.0,"拆散":0.0,"季后赛":0.4706229389263361,"参赛":0.0,"选中":0.0,"有资格":1.0,"格林":9.97354091464966,"沉默寡言":0.0,"西部":0.0,"勇士队":2.0,"球迷":4.450548434295635,"沉默":0.0,"开口":0.0,"首发":0.5238829397936083,"杜兰特":4.370694827111532,"科尔":1.988461370197403,"自由市场":1.0,"调侃":0.0,"球队":1.213381086647557,"市场":0.378432122085504,"禁赛":0.0,"团队":0.8768590557956669,"影响":0.0,"乐观":0.0,"根源":0.8407291006291461,"王朝":1.624853561892329,"发动":0.0,"鱼腩":1.0},"tag_title_term":{"评价":0.0,"辱骂":0.0,"格林":1.753259130610447,"球迷":0.6539455541183883,"杜兰特":1.5,"王朝":0.7116316607844647,"崩坏":0.8291851885105179,"勇士":0.5933449491364371},"news_sub_category_mul_v2":{"NBA":0.929194},"news_sub_category_mul_v1":{"篮球":0.862633,"NBA":0.913836},"is_mjh":0,"img_ids":[13364900506028490813,4210371373121605498,793060582315723072],"news_attentions_rewrite":{"格林-->>德雷蒙德·格林":"","汤普森-->>克莱·汤普森":"","篮球":"","杜兰特":"","nba":"","史蒂夫-->>勇士队教练":""},"newsmans":[],"disgust_score":0.01669733837527163,"news_style_super_beta":[],"displaytype_exinfo":"","quality_feature_level":2,"source_url":"http://NULL","idset":[80003],"score_topic_short":0.032572683485804,"novelty_rtg_sim":0.0,"is_modify":0,"cluster_info":{"key":9281180913557514411,"cid":9281180913557514411},"score_quality":0.1,"smfw":{"quality_model_1003406":{"quality_score":{"final_score":2,"after_score":2,"prev_score":2}},"content_model_1008810":{"news_attentions_id":{"格林-->>德雷蒙德·格林":"1850q3","篮球":"1fgs_6","杜兰特":"10_stj","nba":"1td1cv"},"news_attention":{"格林-->>德雷蒙德·格林":619,"篮球":226,"杜兰特":608,"nba":289},"news_hierarchy":[{"path":[["nba=>篮球=>球类运动=>体育项目=>体育",256]],"topic":"篮球"}],"news_short_hierarchy":[{"path":[["nba=>篮球",256]],"topic":"篮球"}],"news_attentions_rewrite":{"格林-->>德雷蒙德·格林":"","篮球":"","杜兰特":"","nba":""}},"1005989_1":{"vertical_level_bak":0,"author_authority_score_v1":0},"1009041_2":{"quality_emergent_flags":{"51010":"common_weight","50010":"common_weight","40100":"non_fr_brush_common_weight","60100":"fr_brush_common_weight","70010":"common_weight","71010":"common_weight"}},"content_model_1006454":{"news_attention":{"格林-->>德雷蒙德·格林":595,"汤普森-->>克莱·汤普森":217,"篮球":209,"杜兰特":584,"nba":267,"史蒂夫-->>勇士队教练":215}},"1006739_0":{"news_style_super":[],"news_style_super_beta":[]},"1008133_1":{"timeliness":172800},"1006739_1":{"news_style_super":[],"news_style_super_beta":[]},"content_model_1000403":{"base_weight":55},"quality_model_1008133":{"timeliness":172800},"1004558_2":{"author_authority_score_v1":0},"1006454_1":{"news_attention":{"格林-->>德雷蒙德·格林":595,"汤普森-->>克莱·汤普森":217,"篮球":209,"杜兰特":584,"nba":267,"史蒂夫-->>勇士队教练":215}},"content_model_1006770":{"news_attentions_id":{"格林-->>德雷蒙德·格林":"1850q3","篮球":"1fgs_6","杜兰特":"10_stj","nba":"1td1cv"},"news_attention":{"格林-->>德雷蒙德·格林":638,"篮球":224,"杜兰特":627,"nba":252},"news_hierarchy":[{"path":[["nba=>篮球=>球类运动=>体育项目=>体育",225]],"topic":"篮球"}],"news_short_hierarchy":[{"path":[["nba=>篮球",225]],"topic":"篮球"}],"news_attentions_rewrite":{"格林-->>德雷蒙德·格林":"","篮球":"","杜兰特":"","nba":""}},"1008810_2":{"news_attentions_id":{"格林-->>德雷蒙德·格林":"1850q3","篮球":"1fgs_6","杜兰特":"10_stj","nba":"1td1cv"},"news_attention":{"格林-->>德雷蒙德·格林":619,"篮球":226,"杜兰特":608,"nba":289},"news_hierarchy":[{"path":[["nba=>篮球=>球类运动=>体育项目=>体育",256]],"topic":"篮球"}],"news_short_hierarchy":[{"path":[["nba=>篮球",256]],"topic":"篮球"}],"news_attentions_rewrite":{"格林-->>德雷蒙德·格林":"","篮球":"","杜兰特":"","nba":""}},"1003406_1":{"quality_score":{"final_score":2,"after_score":2,"prev_score":2}},"1006770_2":{"news_attentions_id":{"格林-->>德雷蒙德·格林":"1850q3","篮球":"1fgs_6","杜兰特":"10_stj","nba":"1td1cv"},"news_attention":{"格林-->>德雷蒙德·格林":638,"篮球":224,"杜兰特":627,"nba":252},"news_hierarchy":[{"path":[["nba=>篮球=>球类运动=>体育项目=>体育",225]],"topic":"篮球"}],"news_short_hierarchy":[{"path":[["nba=>篮球",225]],"topic":"篮球"}],"news_attentions_rewrite":{"格林-->>德雷蒙德·格林":"","篮球":"","杜兰特":"","nba":""}},"quality_model_1004558":{"author_authority_score_v1":0},"1006770_1":{"news_attentions_id":{"格林-->>德雷蒙德·格林":"1850q3","篮球":"1fgs_6","杜兰特":"10_stj","nba":"1td1cv"},"news_attention":{"格林-->>德雷蒙德·格林":638,"篮球":224,"杜兰特":627,"nba":252},"news_hierarchy":[{"path":[["nba=>篮球=>球类运动=>体育项目=>体育",225]],"topic":"篮球"}],"news_short_hierarchy":[{"path":[["nba=>篮球",225]],"topic":"篮球"}],"news_attentions_rewrite":{"格林-->>德雷蒙德·格林":"","篮球":"","杜兰特":"","nba":""}}},"novelty_paras_real_time":{},"m_related_sign":"6185173119204958644","recommend_to_bs":1,"sndc_send_time":1542208977,"stype":2,"url_sign":16736811619630306176,"old_news_level":0,"m_site":"搜狐体育","weight":5,"entity_importance":11.89345688666651,"hit_conf_cont_xpath":"0","site_name":"搜狐体育","tags_author":[],"m_isvideo":"0","m_title":"勇士王朝崩坏导火索？格林辱骂杜兰特，看美球迷如何评价他们？","m_url":"http://sports.sohu.com/20181114/n555369066.shtml","operator_time":{"al2_nlpc_output_time":1542208978.262732,"content_vertical_input_time":1542208980.517425,"content_combian_input_time":1542208982.344814,"sndc_send_time":1542208977,"content_mining_input_time":1542208978.281287,"content_combian_output_time":1542208982.485564,"content_task_input_time":1542208979.642638,"data_analyzer_input_time":1542208980.855754,"content_cmnlpc_output_time":1542208982.546825,"content_class_input_time":1542208979.572809,"content_quality_output_time":1542208982.291596,"content_task_output_time":1542208980.485306,"content_cmnlpc_input_time":1542208982.539792,"content_mining_output_time":1542208978.512143,"part1_importer_output_time":1542208978.144857,"al2_nlpc_input_time":1542208978.250788,"content_quality_input_time":1542208980.963542,"content_rcmc_agent_input_time":1542208982.564531,"content_vertical_output_time":1542208980.771243,"part1_importer_input_time":1542208978.142955,"data_analyzer_output_time":1542208980.944757,"content_class_output_time":1542208979.599327},"sn_procesor_quality_reason":0,"low_quality_all_matched":{"set_flag":[{"rule_id":"rule_setflag5","reason":"","priority":1,"order":1}]},"news_title_attraction_score":2.53937,"news_sub_category_v1_prob":0.913836,"unique_class":{"second_class_weight":0.867,"second_class_name":"体育活动","first_class_weight":1.0,"first_class_name":"活动与事件"},"merge_locname":{"province":"","town":"","city":"","district":"","circle":""},"content_quality":{"disgust_level":0,"gj_quality":-1,"title_attentions":{"杜兰特":584},"news_attraction":0,"news_sub_category_prob":0.766756,"copy_time":1542208951,"news_category_prob":0.790362,"copy_level":0,"high_timeliness":0},"first_content":"","m_json_text":"{\"content\":[{\"data\":\"格林和杜兰特的口角逐渐发酵，最终在科尔的铁腕下，勇士队内禁赛格林参赛一场宣告终结；可美球迷如何评价勇士内讧？\",\"type\":\"text\"},{\"data\":{\"big\":{\"height\":504,\"url\":\"http://t11.baidu.com/it/u=2640112372,1817035442&fm=173&app=25&f=JPEG?w=640&h=504&s=29B0209CB68F0EEC3AA07586030080A0\",\"width\":640},\"caption\":\"\",\"cont_small\":{\"height\":252,\"src\":\"http://t11.baidu.com/it/u=4219124845,1084696370&fm=173&app=25&f=JPEG?w=320&h=252&s=29B0209CB68F0EEC3AA07586030080A0\",\"width\":320},\"original\":{\"feature_json_format\":\"{\\\"aesthetic\\\":-1.6205762624741,\\\"antiporn_normal\\\":0.999476,\\\"antiporn_porn\\\":0.000319,\\\"antiporn_sexy\\\":0.000205,\\\"array\\\":[{\\\"locheight\\\":20,\\\"locleft\\\":14,\\\"loctop\\\":7,\\\"locwidth\\\":616,\\\"ocrresult\\\":\\\" [ story with @ spearsespn and me : late game exchange between kevin durant dray\\\"},{\\\"locheight\\\":21,\\\"locleft\\\":15,\\\"loctop\\\":25,\\\"locwidth\\\":616,\\\"ocrresult\\\":\\\" mond green carried into locker room monday night w \\\\/ oudly confronting green for decisio\\\"},{\\\"locheight\\\":16,\\\"locleft\\\":15,\\\"loctop\\\":48,\\\"locwidth\\\":568,\\\"ocrresult\\\":\\\" n - making on final play of regulation . scene described as one of most intense of this g - state era .\\\"},{\\\"locheight\\\":21,\\\"locleft\\\":14,\\\"loctop\\\":79,\\\"locwidth\\\":618,\\\"ocrresult\\\":\\\"Woj:\\\\u4e0eEsPN\\\\u7684 Marc spears\\\\u8054\\\\u5408\\\\u62a5\\\\u9053:\\\\u5468\\\\u665a,\\\\u793e\\\\u5170\\\\u7279\\\\u548c\\\\u683c\\\\u6797\\\\u5728\\\\u6bd4\\\\u8d5b\\\\u672b\\\\u5c3e\\\\u53d1\\\\u751f\\\\u4e86\\\\u4e89\\\\u6267,\\\\u540e\\\\u8fd9\\\\u5a07\\\\u4e89\\\\u5435\\\\u5ef6\\\\u7eed\\\\u5230\\\\u4e86\\\"},{\\\"locheight\\\":19,\\\"locleft\\\":15,\\\"loctop\\\":101,\\\"locwidth\\\":616,\\\"ocrresult\\\":\\\"\\\\u66f4\\\\u8863\\\\u5ba4\\\\u3002\\\\u961f\\\\u53cb\\\\u4eec\\\\u5927\\\\u58f0\\\\u5730\\\\u9488\\\\u5bf9\\\\u683c\\\\u6797\\\\u5e38\\\\u89c4\\\\u65f6\\\\u95f4\\\\u7684\\\\u8d14\\\\u540e\\\\u4e00\\\\u653b\\\\u51b3\\\\u7b56\\\\u63d0\\\\u8d77\\\\u8d28\\\\u8d51\\\\u3002\\\\u636e\\\\u63cf\\\\u8ff0,\\\\u5f53\\\\u65f6\\\\u7684\\\\u573a\\\\u666f\\\\u662f(\\\\u675c\\\\u5170\\\\u7279\\\\u52a0\\\\u96b0\\\\u540e\\\\u7684)\\\\u52c7\\\"},{\\\"locheight\\\":15,\\\"locleft\\\":15,\\\"loctop\\\":120,\\\"locwidth\\\":88,\\\"ocrresult\\\":\\\"\\\\u58eb\\\\u65f6\\\\u4ee3\\\\u6700\\\\u7d27\\\\u5f20\\\\u4e4b\\\"},{\\\"locheight\\\":29,\\\"locleft\\\":450,\\\"loctop\\\":423,\\\"locwidth\\\":43,\\\"ocrresult\\\":\\\"23\\\"}],\\\"clarity\\\":0.24382677674294,\\\"contsign\\\":\\\"3733825992,2428286652\\\",\\\"disgust\\\":9.8357204478816e-6,\\\"feature_970_topn\\\":[{\\\"cid\\\":196,\\\"val\\\":0.87401378154755},{\\\"cid\\\":194,\\\"val\\\":0.058382924646139},{\\\"cid\\\":201,\\\"val\\\":0.022879371419549},{\\\"cid\\\":216,\\\"val\\\":0.013506608083844},{\\\"cid\\\":218,\\\"val\\\":0.002613123273477}],\\\"feature_sexy_lady\\\":0.0011969044571742,\\\"main_area\\\":{\\\"height\\\":353,\\\"left\\\":5,\\\"top\\\":153,\\\"width\\\":600},\\\"porn_prob\\\":0.000319,\\\"same_feature_with_hash\\\":\\\"{\\\\\\\"same_feature_hash_id\\\\\\\":46631,\\\\\\\"same_feature_hash_ids\\\\\\\":[46631,47078,178727,179174,46992,179088,124455,124902,124816]}\\\"}\",\"height\":504,\"image_format\":\"JPEG\",\"low_quality_type\":0,\"url\":\"http://5b0988e595225.cdn.sohucs.com/images/20181114/aaf6325e64814428b9503de93a8e54d1.jpeg\",\"width\":640},\"original_third\":{\"feature_json_format\":\"{\\\"aesthetic\\\":-1.6205762624741,\\\"antiporn_normal\\\":0.999476,\\\"antiporn_porn\\\":0.000319,\\\"antiporn_sexy\\\":0.000205,\\\"array\\\":[{\\\"locheight\\\":20,\\\"locleft\\\":14,\\\"loctop\\\":7,\\\"locwidth\\\":616,\\\"ocrresult\\\":\\\" [ story with @ spearsespn and me : late game exchange between kevin durant dray\\\"},{\\\"locheight\\\":21,\\\"locleft\\\":15,\\\"loctop\\\":25,\\\"locwidth\\\":616,\\\"ocrresult\\\":\\\" mond green carried into locker room monday night w \\\\/ oudly confronting green for decisio\\\"},{\\\"locheight\\\":16,\\\"locleft\\\":15,\\\"loctop\\\":48,\\\"locwidth\\\":568,\\\"ocrresult\\\":\\\" n - making on final play of regulation . scene described as one of most intense of this g - state era .\\\"},{\\\"locheight\\\":21,\\\"locleft\\\":14,\\\"loctop\\\":79,\\\"locwidth\\\":618,\\\"ocrresult\\\":\\\"Woj:\\\\u4e0eEsPN\\\\u7684 Marc spears\\\\u8054\\\\u5408\\\\u62a5\\\\u9053:\\\\u5468\\\\u665a,\\\\u793e\\\\u5170\\\\u7279\\\\u548c\\\\u683c\\\\u6797\\\\u5728\\\\u6bd4\\\\u8d5b\\\\u672b\\\\u5c3e\\\\u53d1\\\\u751f\\\\u4e86\\\\u4e89\\\\u6267,\\\\u540e\\\\u8fd9\\\\u5a07\\\\u4e89\\\\u5435\\\\u5ef6\\\\u7eed\\\\u5230\\\\u4e86\\\"},{\\\"locheight\\\":19,\\\"locleft\\\":15,\\\"loctop\\\":101,\\\"locwidth\\\":616,\\\"ocrresult\\\":\\\"\\\\u66f4\\\\u8863\\\\u5ba4\\\\u3002\\\\u961f\\\\u53cb\\\\u4eec\\\\u5927\\\\u58f0\\\\u5730\\\\u9488\\\\u5bf9\\\\u683c\\\\u6797\\\\u5e38\\\\u89c4\\\\u65f6\\\\u95f4\\\\u7684\\\\u8d14\\\\u540e\\\\u4e00\\\\u653b\\\\u51b3\\\\u7b56\\\\u63d0\\\\u8d77\\\\u8d28\\\\u8d51\\\\u3002\\\\u636e\\\\u63cf\\\\u8ff0,\\\\u5f53\\\\u65f6\\\\u7684\\\\u573a\\\\u666f\\\\u662f(\\\\u675c\\\\u5170\\\\u7279\\\\u52a0\\\\u96b0\\\\u540e\\\\u7684)\\\\u52c7\\\"},{\\\"locheight\\\":15,\\\"locleft\\\":15,\\\"loctop\\\":120,\\\"locwidth\\\":88,\\\"ocrresult\\\":\\\"\\\\u58eb\\\\u65f6\\\\u4ee3\\\\u6700\\\\u7d27\\\\u5f20\\\\u4e4b\\\"},{\\\"locheight\\\":29,\\\"locleft\\\":450,\\\"loctop\\\":423,\\\"locwidth\\\":43,\\\"ocrresult\\\":\\\"23\\\"}],\\\"clarity\\\":0.24382677674294,\\\"contsign\\\":\\\"3733825992,2428286652\\\",\\\"disgust\\\":9.8357204478816e-6,\\\"feature_970_topn\\\":[{\\\"cid\\\":196,\\\"val\\\":0.87401378154755},{\\\"cid\\\":194,\\\"val\\\":0.058382924646139},{\\\"cid\\\":201,\\\"val\\\":0.022879371419549},{\\\"cid\\\":216,\\\"val\\\":0.013506608083844},{\\\"cid\\\":218,\\\"val\\\":0.002613123273477}],\\\"feature_sexy_lady\\\":0.0011969044571742,\\\"main_area\\\":{\\\"height\\\":353,\\\"left\\\":5,\\\"top\\\":153,\\\"width\\\":600},\\\"porn_prob\\\":0.000319,\\\"same_feature_with_hash\\\":\\\"{\\\\\\\"same_feature_hash_id\\\\\\\":46631,\\\\\\\"same_feature_hash_ids\\\\\\\":[46631,47078,178727,179174,46992,179088,124455,124902,124816]}\\\"}\",\"height\":504,\"image_format\":\"JPEG\",\"low_quality_type\":0,\"url\":\"http://5b0988e595225.cdn.sohucs.com/images/20181114/aaf6325e64814428b9503de93a8e54d1.jpeg\",\"width\":640},\"small\":{\"height\":360,\"url\":\"http://t12.baidu.com/it/u=159896915,2087523580&fm=173&app=25&f=JPEG?w=480&h=360&s=29B0209CB68F0EEC3AA07586030080A0\",\"width\":480}},\"type\":\"image\"},{\"data\":\"“你（杜兰特）马上就要进入自由市场了，你个小婊砸！”这句话成为了勇士内讧的根源之一！历来“场上鲁莽，场下人精”的格林竟说出这种小白文，令人难以置信！\",\"type\":\"text\"},{\"data\":\"连一向在更衣室沉默寡言的汤普森都站出来，开口强调了团队的重要性，可见这件事在勇士队内影响有多大！\",\"type\":\"text\"},{\"data\":\"美球迷怎么评价这件事？\",\"type\":\"text\"},{\"data\":{\"big\":{\"height\":499,\"url\":\"http://t10.baidu.com/it/u=2176865364,2091152033&fm=173&app=25&f=JPEG?w=640&h=499&s=4B02498A4D9007E95268259903008093\",\"width\":640},\"caption\":\"\",\"cont_small\":{\"height\":250,\"src\":\"http://t12.baidu.com/it/u=229528574,2025499134&fm=173&app=25&f=JPEG?w=320&h=250&s=4B02498A4D9007E95268259903008093\",\"width\":320},\"original\":{\"feature_json_format\":\"{\\\"aesthetic\\\":0.5536093711853,\\\"antiporn_normal\\\":0.996077,\\\"antiporn_porn\\\":0.001065,\\\"antiporn_sexy\\\":0.002858,\\\"array\\\":[{\\\"locheight\\\":17,\\\"locleft\\\":12,\\\"loctop\\\":3,\\\"locwidth\\\":620,\\\"ocrresult\\\":\\\" Imagine after all they ve gone through . the clippers may actually play a small part in the warriors dynast\\\"},{\\\"locheight\\\":19,\\\"locleft\\\":8,\\\"loctop\\\":46,\\\"locwidth\\\":520,\\\"ocrresult\\\":\\\"\\\\u5feb\\\\u8239\\\\u7403\\\\u8ff7:\\\\u6211\\\\u8239\\\\u8fd9\\\\u4e9b\\\\u5e74\\\\u7ecf\\\\u5386\\\\u4e86\\\\u65e0\\\\u6570\\\\u96be,\\\\u5982\\\\u4eca\\\\u8fd8\\\\u771f\\\\u6709\\\\u53ef\\\\u80fd\\\\u4e3a\\\\u52c7\\\\u58eb\\\\u738b\\\\u671d\\\\u89e3\\\\u4f53\\\\u505a\\\\u51fa\\\\u4e00\\\\u70b9\\\\u5fae\\\\u5c0f\\\\u7684\\\\u8d21?\\\"},{\\\"locheight\\\":17,\\\"locleft\\\":8,\\\"loctop\\\":64,\\\"locwidth\\\":139,\\\"ocrresult\\\":\\\"\\\\u68a6,\\\\u505a\\\\u5f97\\\\u4e0d\\\\u5927,\\\\u8fd8\\\\u53eb\\\\u68a6\\\\u5417\\\"}],\\\"clarity\\\":1.0226001739502,\\\"contsign\\\":\\\"3635503010,1600128633\\\",\\\"disgust\\\":5.0552651373437e-5,\\\"feature_970_topn\\\":[{\\\"cid\\\":201,\\\"val\\\":0.72940051555634},{\\\"cid\\\":188,\\\"val\\\":0.062286946922541},{\\\"cid\\\":212,\\\"val\\\":0.055911667644978},{\\\"cid\\\":196,\\\"val\\\":0.034509669989347},{\\\"cid\\\":194,\\\"val\\\":0.024747719988227}],\\\"feature_sexy_lady\\\":0.014979796484113,\\\"main_area\\\":{\\\"height\\\":426,\\\"left\\\":3,\\\"top\\\":79,\\\"width\\\":627},\\\"porn_prob\\\":0.001065,\\\"same_feature_with_hash\\\":\\\"{\\\\\\\"same_feature_hash_id\\\\\\\":178727,\\\\\\\"same_feature_hash_ids\\\\\\\":[178727,179174,163879,164326,178860,164012,242727,243174,242860]}\\\"}\",\"height\":499,\"image_format\":\"JPEG\",\"low_quality_type\":0,\"url\":\"http://5b0988e595225.cdn.sohucs.com/images/20181114/9535b4613bef41d5baa22c1e73dfc8bc.jpeg\",\"width\":640},\"original_third\":{\"feature_json_format\":\"{\\\"aesthetic\\\":0.5536093711853,\\\"antiporn_normal\\\":0.996077,\\\"antiporn_porn\\\":0.001065,\\\"antiporn_sexy\\\":0.002858,\\\"array\\\":[{\\\"locheight\\\":17,\\\"locleft\\\":12,\\\"loctop\\\":3,\\\"locwidth\\\":620,\\\"ocrresult\\\":\\\" Imagine after all they ve gone through . the clippers may actually play a small part in the warriors dynast\\\"},{\\\"locheight\\\":19,\\\"locleft\\\":8,\\\"loctop\\\":46,\\\"locwidth\\\":520,\\\"ocrresult\\\":\\\"\\\\u5feb\\\\u8239\\\\u7403\\\\u8ff7:\\\\u6211\\\\u8239\\\\u8fd9\\\\u4e9b\\\\u5e74\\\\u7ecf\\\\u5386\\\\u4e86\\\\u65e0\\\\u6570\\\\u96be,\\\\u5982\\\\u4eca\\\\u8fd8\\\\u771f\\\\u6709\\\\u53ef\\\\u80fd\\\\u4e3a\\\\u52c7\\\\u58eb\\\\u738b\\\\u671d\\\\u89e3\\\\u4f53\\\\u505a\\\\u51fa\\\\u4e00\\\\u70b9\\\\u5fae\\\\u5c0f\\\\u7684\\\\u8d21?\\\"},{\\\"locheight\\\":17,\\\"locleft\\\":8,\\\"loctop\\\":64,\\\"locwidth\\\":139,\\\"ocrresult\\\":\\\"\\\\u68a6,\\\\u505a\\\\u5f97\\\\u4e0d\\\\u5927,\\\\u8fd8\\\\u53eb\\\\u68a6\\\\u5417\\\"}],\\\"clarity\\\":1.0226001739502,\\\"contsign\\\":\\\"3635503010,1600128633\\\",\\\"disgust\\\":5.0552651373437e-5,\\\"feature_970_topn\\\":[{\\\"cid\\\":201,\\\"val\\\":0.72940051555634},{\\\"cid\\\":188,\\\"val\\\":0.062286946922541},{\\\"cid\\\":212,\\\"val\\\":0.055911667644978},{\\\"cid\\\":196,\\\"val\\\":0.034509669989347},{\\\"cid\\\":194,\\\"val\\\":0.024747719988227}],\\\"feature_sexy_lady\\\":0.014979796484113,\\\"main_area\\\":{\\\"height\\\":426,\\\"left\\\":3,\\\"top\\\":79,\\\"width\\\":627},\\\"porn_prob\\\":0.001065,\\\"same_feature_with_hash\\\":\\\"{\\\\\\\"same_feature_hash_id\\\\\\\":178727,\\\\\\\"same_feature_hash_ids\\\\\\\":[178727,179174,163879,164326,178860,164012,242727,243174,242860]}\\\"}\",\"height\":499,\"image_format\":\"JPEG\",\"low_quality_type\":0,\"url\":\"http://5b0988e595225.cdn.sohucs.com/images/20181114/9535b4613bef41d5baa22c1e73dfc8bc.jpeg\",\"width\":640},\"small\":{\"height\":360,\"url\":\"http://t12.baidu.com/it/u=4156188746,2125046199&fm=173&app=25&f=JPEG?w=480&h=360&s=4B02498A4D9007E95268259903008093\",\"width\":480}},\"type\":\"image\"},{\"data\":\"美球迷调侃道：没想到西部弱旅快船，不显山不露水，竟然干出了如此惊天动地的大事——他们竟然成为一支王朝球队崩坏的导火索！\",\"type\":\"text\"},{\"data\":\"“梦做的不大，还叫梦吗？”难以想象，他们只是一支有可能连季后赛都进不了的鱼腩球队。\",\"type\":\"text\"},{\"data\":{\"big\":{\"height\":468,\"url\":\"http://t11.baidu.com/it/u=2840714101,4274321966&fm=173&app=25&f=JPEG?w=640&h=468&s=832004A8449A17ED86E1808C03003003\",\"width\":640},\"caption\":\"\",\"cont_small\":{\"height\":234,\"src\":\"http://t12.baidu.com/it/u=3193909571,1984092170&fm=173&app=25&f=JPEG?w=320&h=234&s=832004A8449A17ED86E1808C03003003\",\"width\":320},\"original\":{\"feature_json_format\":\"{\\\"aesthetic\\\":1.4453283548355,\\\"antiporn_normal\\\":0.998336,\\\"antiporn_porn\\\":0.000218,\\\"antiporn_sexy\\\":0.001446,\\\"array\\\":[{\\\"locheight\\\":23,\\\"locleft\\\":3,\\\"loctop\\\":0,\\\"locwidth\\\":631,\\\"ocrresult\\\":\\\" Man this would be such an evil campaign by the internet vote dray as a starter to ruin the warriors dyn\\\"},{\\\"locheight\\\":17,\\\"locleft\\\":3,\\\"loctop\\\":23,\\\"locwidth\\\":148,\\\"ocrresult\\\":\\\" asty . i love it . let ' s do it .\\\"},{\\\"locheight\\\":17,\\\"locleft\\\":2,\\\"loctop\\\":42,\\\"locwidth\\\":633,\\\"ocrresult\\\":\\\"\\\\u6e56\\\\u4eba\\\\u7403\\\\u8ff7:\\\\u6211\\\\u9760,\\\\u8fd9\\\\u542c\\\\u7740\\\\u50cf\\\\u662f\\\\u7f51\\\\u4e0a\\\\u53d1\\\\u8d77\\\\u7684\\\\u90aa\\\\u6076\\\\u8fd0\\\\u52a8\\\\u671f,\\\\u628a\\\\u683c\\\\u6797\\\\u6295\\\\u6210\\\\u5168\\\\u660e\\\\u661f\\\\u9996\\\\u53d1\\\\u4ece\\\\u800c\\\\u6467\\\\u6bc1\\\\u52c7\\\\u58eb\\\\u738b\\\\u671d\\\\u3002\\\\u6211\\\\u559c\\\\u6b22,\\\\u4e00\\\\u8d77\\\\u6765\\\"},{\\\"locheight\\\":29,\\\"locleft\\\":284,\\\"loctop\\\":258,\\\"locwidth\\\":46,\\\"ocrresult\\\":\\\"35\\\"}],\\\"clarity\\\":3.4930624961853,\\\"contsign\\\":\\\"2423624123,3076698353\\\",\\\"disgust\\\":5.0567596190376e-5,\\\"feature_970_topn\\\":[{\\\"cid\\\":201,\\\"val\\\":0.50611311197281},{\\\"cid\\\":196,\\\"val\\\":0.3828592300415},{\\\"cid\\\":212,\\\"val\\\":0.080235049128532},{\\\"cid\\\":213,\\\"val\\\":0.0097663076594472},{\\\"cid\\\":217,\\\"val\\\":0.0036623657215387}],\\\"feature_sexy_lady\\\":0.020666144788265,\\\"main_area\\\":{\\\"height\\\":403,\\\"left\\\":2,\\\"top\\\":71,\\\"width\\\":625},\\\"porn_prob\\\":0.000218,\\\"same_feature_with_hash\\\":\\\"{\\\\\\\"same_feature_hash_id\\\\\\\":178727,\\\\\\\"same_feature_hash_ids\\\\\\\":[178727,178860,46631,46764,178863,46767,164903,165036,165039]}\\\"}\",\"height\":468,\"image_format\":\"JPEG\",\"low_quality_type\":32,\"url\":\"http://5b0988e595225.cdn.sohucs.com/images/20181114/49ce736cf9454e29b7766e03b4b4ad3b.jpeg\",\"width\":640},\"original_third\":{\"feature_json_format\":\"{\\\"aesthetic\\\":1.4453283548355,\\\"antiporn_normal\\\":0.998336,\\\"antiporn_porn\\\":0.000218,\\\"antiporn_sexy\\\":0.001446,\\\"array\\\":[{\\\"locheight\\\":23,\\\"locleft\\\":3,\\\"loctop\\\":0,\\\"locwidth\\\":631,\\\"ocrresult\\\":\\\" Man this would be such an evil campaign by the internet vote dray as a starter to ruin the warriors dyn\\\"},{\\\"locheight\\\":17,\\\"locleft\\\":3,\\\"loctop\\\":23,\\\"locwidth\\\":148,\\\"ocrresult\\\":\\\" asty . i love it . let ' s do it .\\\"},{\\\"locheight\\\":17,\\\"locleft\\\":2,\\\"loctop\\\":42,\\\"locwidth\\\":633,\\\"ocrresult\\\":\\\"\\\\u6e56\\\\u4eba\\\\u7403\\\\u8ff7:\\\\u6211\\\\u9760,\\\\u8fd9\\\\u542c\\\\u7740\\\\u50cf\\\\u662f\\\\u7f51\\\\u4e0a\\\\u53d1\\\\u8d77\\\\u7684\\\\u90aa\\\\u6076\\\\u8fd0\\\\u52a8\\\\u671f,\\\\u628a\\\\u683c\\\\u6797\\\\u6295\\\\u6210\\\\u5168\\\\u660e\\\\u661f\\\\u9996\\\\u53d1\\\\u4ece\\\\u800c\\\\u6467\\\\u6bc1\\\\u52c7\\\\u58eb\\\\u738b\\\\u671d\\\\u3002\\\\u6211\\\\u559c\\\\u6b22,\\\\u4e00\\\\u8d77\\\\u6765\\\"},{\\\"locheight\\\":29,\\\"locleft\\\":284,\\\"loctop\\\":258,\\\"locwidth\\\":46,\\\"ocrresult\\\":\\\"35\\\"}],\\\"clarity\\\":3.4930624961853,\\\"contsign\\\":\\\"2423624123,3076698353\\\",\\\"disgust\\\":5.0567596190376e-5,\\\"feature_970_topn\\\":[{\\\"cid\\\":201,\\\"val\\\":0.50611311197281},{\\\"cid\\\":196,\\\"val\\\":0.3828592300415},{\\\"cid\\\":212,\\\"val\\\":0.080235049128532},{\\\"cid\\\":213,\\\"val\\\":0.0097663076594472},{\\\"cid\\\":217,\\\"val\\\":0.0036623657215387}],\\\"feature_sexy_lady\\\":0.020666144788265,\\\"main_area\\\":{\\\"height\\\":403,\\\"left\\\":2,\\\"top\\\":71,\\\"width\\\":625},\\\"porn_prob\\\":0.000218,\\\"same_feature_with_hash\\\":\\\"{\\\\\\\"same_feature_hash_id\\\\\\\":178727,\\\\\\\"same_feature_hash_ids\\\\\\\":[178727,178860,46631,46764,178863,46767,164903,165036,165039]}\\\"}\",\"height\":468,\"image_format\":\"JPEG\",\"low_quality_type\":32,\"url\":\"http://5b0988e595225.cdn.sohucs.com/images/20181114/49ce736cf9454e29b7766e03b4b4ad3b.jpeg\",\"width\":640},\"small\":{\"height\":360,\"url\":\"http://t12.baidu.com/it/u=4247807270,1460951038&fm=173&app=25&f=JPEG?w=480&h=360&s=832004A8449A17ED86E1808C03003003\",\"width\":480}},\"type\":\"image\"},{\"data\":\"不少球迷想出了多种拆散勇士王朝的点子，其中一个深得我心！\",\"type\":\"text\"},{\"data\":\"一位湖人球迷表示“在全明星票选中，全民发动，让格林成为全明星首发大前锋！那么格林将有资格得到一份顶薪合同”，那么，杜兰特和格林必须离开一个人，从内到外瓦解勇士！\",\"type\":\"text\"},{\"data\":{\"big\":{\"height\":426,\"url\":\"http://t12.baidu.com/it/u=2470776695,275776136&fm=173&app=25&f=JPEG?w=640&h=426&s=2EA3208C6C53BEDC5CA416830300E08F\",\"width\":640},\"caption\":\"\",\"cont_small\":{\"height\":213,\"src\":\"http://t12.baidu.com/it/u=3329840975,510291623&fm=173&app=25&f=JPEG?w=320&h=213&s=2EA3208C6C53BEDC5CA416830300E08F\",\"width\":320},\"original\":{\"feature_json_format\":\"{\\\"aesthetic\\\":2.9100289344788,\\\"antiporn_normal\\\":0.99873,\\\"antiporn_porn\\\":2.4e-5,\\\"antiporn_sexy\\\":0.001246,\\\"array\\\":[{\\\"locheight\\\":21,\\\"locleft\\\":541,\\\"loctop\\\":186,\\\"locwidth\\\":17,\\\"ocrresult\\\":\\\"9\\\"}],\\\"clarity\\\":2.5328080654144,\\\"contsign\\\":\\\"133935982,2267365010\\\",\\\"disgust\\\":2.7369169401936e-6,\\\"feature_970_topn\\\":[{\\\"cid\\\":196,\\\"val\\\":0.68148899078369},{\\\"cid\\\":201,\\\"val\\\":0.2935982644558},{\\\"cid\\\":212,\\\"val\\\":0.0082486197352409},{\\\"cid\\\":194,\\\"val\\\":0.0048978864215314},{\\\"cid\\\":216,\\\"val\\\":0.0043523418717086}],\\\"feature_sexy_lady\\\":0.00042520245187916,\\\"main_area\\\":{\\\"height\\\":419,\\\"left\\\":1,\\\"top\\\":16,\\\"width\\\":631},\\\"porn_prob\\\":2.4e-5,\\\"same_feature_with_hash\\\":\\\"{\\\\\\\"same_feature_hash_id\\\\\\\":46816,\\\\\\\"same_feature_hash_ids\\\\\\\":[46816,46833,178912,178929,47041,179137,165088,165105,165313]}\\\"}\",\"height\":426,\"image_format\":\"JPEG\",\"low_quality_type\":0,\"url\":\"http://5b0988e595225.cdn.sohucs.com/images/20181114/b4cd5d3e631d4995aee168a31c61b3eb.jpeg\",\"width\":640},\"original_third\":{\"feature_json_format\":\"{\\\"aesthetic\\\":2.9100289344788,\\\"antiporn_normal\\\":0.99873,\\\"antiporn_porn\\\":2.4e-5,\\\"antiporn_sexy\\\":0.001246,\\\"array\\\":[{\\\"locheight\\\":21,\\\"locleft\\\":541,\\\"loctop\\\":186,\\\"locwidth\\\":17,\\\"ocrresult\\\":\\\"9\\\"}],\\\"clarity\\\":2.5328080654144,\\\"contsign\\\":\\\"133935982,2267365010\\\",\\\"disgust\\\":2.7369169401936e-6,\\\"feature_970_topn\\\":[{\\\"cid\\\":196,\\\"val\\\":0.68148899078369},{\\\"cid\\\":201,\\\"val\\\":0.2935982644558},{\\\"cid\\\":212,\\\"val\\\":0.0082486197352409},{\\\"cid\\\":194,\\\"val\\\":0.0048978864215314},{\\\"cid\\\":216,\\\"val\\\":0.0043523418717086}],\\\"feature_sexy_lady\\\":0.00042520245187916,\\\"main_area\\\":{\\\"height\\\":419,\\\"left\\\":1,\\\"top\\\":16,\\\"width\\\":631},\\\"porn_prob\\\":2.4e-5,\\\"same_feature_with_hash\\\":\\\"{\\\\\\\"same_feature_hash_id\\\\\\\":46816,\\\\\\\"same_feature_hash_ids\\\\\\\":[46816,46833,178912,178929,47041,179137,165088,165105,165313]}\\\"}\",\"height\":426,\"image_format\":\"JPEG\",\"low_quality_type\":0,\"url\":\"http://5b0988e595225.cdn.sohucs.com/images/20181114/b4cd5d3e631d4995aee168a31c61b3eb.jpeg\",\"width\":640},\"small\":{\"height\":360,\"url\":\"http://t12.baidu.com/it/u=3561670007,1943450254&fm=173&app=25&f=JPEG?w=480&h=360&s=2EA3208C6C53BEDC5CA416830300E08F\",\"width\":480}},\"type\":\"image\"},{\"data\":\"但仍然有不少美球迷表示：拆散他们就能瓦解勇士，这个想法太乐观！\",\"type\":\"text\"}],\"duplicate_sign\":\"589597 1080522733\",\"idset\":[80003],\"replace_sign\":\"589597 1080522733\"}","title":"勇士王朝崩坏导火索？格林辱骂杜兰特，看美球迷如何评价他们？","title_nlpc_lexer":[{"text":"勇士王朝崩坏导火索？格林辱骂杜兰特，看美球迷如何评价他们？","items":[{"formal":"","loc_details":[],"item":"勇士","pos":"n","basic_words":["勇士"],"byte_length":4,"ne":"","byte_offset":0,"uri":""},{"formal":"","loc_details":[],"item":"王朝","pos":"n","basic_words":["王朝"],"byte_length":4,"ne":"","byte_offset":4,"uri":""},{"formal":"","loc_details":[],"item":"崩坏","pos":"v","basic_words":["崩坏"],"byte_length":4,"ne":"","byte_offset":8,"uri":""},{"formal":"","loc_details":[],"item":"导火索","pos":"n","basic_words":["导火索"],"byte_length":6,"ne":"","byte_offset":12,"uri":""},{"formal":"","loc_details":[],"item":"？","pos":"w","basic_words":["？"],"byte_length":2,"ne":"","byte_offset":18,"uri":""},{"formal":"","loc_details":[],"item":"格林","pos":"","basic_words":["格林"],"byte_length":4,"ne":"1007","byte_offset":20,"uri":""},{"formal":"","loc_details":[],"item":"辱骂","pos":"v","basic_words":["辱骂"],"byte_length":4,"ne":"","byte_offset":24,"uri":""},{"formal":"","loc_details":[],"item":"杜兰特","pos":"","basic_words":["杜兰特"],"byte_length":6,"ne":"1007","byte_offset":28,"uri":""},{"formal":"","loc_details":[],"item":"，","pos":"w","basic_words":["，"],"byte_length":2,"ne":"","byte_offset":34,"uri":""},{"formal":"","loc_details":[],"item":"看","pos":"v","basic_words":["看"],"byte_length":2,"ne":"","byte_offset":36,"uri":""},{"formal":"","loc_details":[],"item":"美","pos":"ns","basic_words":["美"],"byte_length":2,"ne":"","byte_offset":38,"uri":""},{"formal":"","loc_details":[],"item":"球迷","pos":"","basic_words":["球迷"],"byte_length":4,"ne":"1099","byte_offset":40,"uri":""},{"formal":"","loc_details":[],"item":"如何","pos":"r","basic_words":["如何"],"byte_length":4,"ne":"","byte_offset":44,"uri":""},{"formal":"","loc_details":[],"item":"评价","pos":"v","basic_words":["评价"],"byte_length":4,"ne":"","byte_offset":48,"uri":""},{"formal":"","loc_details":[],"item":"他们","pos":"r","basic_words":["他们"],"byte_length":4,"ne":"","byte_offset":52,"uri":""},{"formal":"","loc_details":[],"item":"？","pos":"w","basic_words":["？"],"byte_length":2,"ne":"","byte_offset":56,"uri":""}],"retcode":0}],"m_content":"格林和杜兰特的口角逐渐发酵，最终在科尔的铁腕下，勇士队内禁赛格林参赛一场宣告终结；可美球迷如何评价勇士内讧？“你（杜兰特）马上就要进入自由市场了，你个小婊砸！”这句话成为了勇士内讧的根源之一！历来“场上鲁莽，场下人精”的格林竟说出这种小白文，令人难以置信！连一向在更衣室沉默寡言的汤普森都站出来，开口强调了团队的重要性，可见这件事在勇士队内影响有多大！美球迷怎么评价这件事？美球迷调侃道：没想到西部弱旅快船，不显山不露水，竟然干出了如此惊天动地的大事——他们竟然成为一支王朝球队崩坏的导火索！“梦做的不大，还叫梦吗？”难以想象，他们只是一支有可能连季后赛都进不了的鱼腩球队。不少球迷想出了多种拆散勇士王朝的点子，其中一个深得我心！一位湖人球迷表示“在全明星票选中，全民发动，让格林成为全明星首发大前锋！那么格林将有资格得到一份顶薪合同”，那么，杜兰特和格林必须离开一个人，从内到外瓦解勇士！但仍然有不少美球迷表示：拆散他们就能瓦解勇士，这个想法太乐观！","strategy_exinfo":"","content":"格林和杜兰特的口角逐渐发酵，最终在科尔的铁腕下，勇士队内禁赛格林参赛一场宣告终结；可美球迷如何评价勇士内讧？“你（杜兰特）马上就要进入自由市场了，你个小婊砸！”这句话成为了勇士内讧的根源之一！历来“场上鲁莽，场下人精”的格林竟说出这种小白文，令人难以置信！连一向在更衣室沉默寡言的汤普森都站出来，开口强调了团队的重要性，可见这件事在勇士队内影响有多大！美球迷怎么评价这件事？美球迷调侃道：没想到西部弱旅快船，不显山不露水，竟然干出了如此惊天动地的大事——他们竟然成为一支王朝球队崩坏的导火索！“梦做的不大，还叫梦吗？”难以想象，他们只是一支有可能连季后赛都进不了的鱼腩球队。不少球迷想出了多种拆散勇士王朝的点子，其中一个深得我心！一位湖人球迷表示“在全明星票选中，全民发动，让格林成为全明星首发大前锋！那么格林将有资格得到一份顶薪合同”，那么，杜兰特和格林必须离开一个人，从内到外瓦解勇士！但仍然有不少美球迷表示：拆散他们就能瓦解勇士，这个想法太乐观！","m_text":"格林和杜兰特的口角逐渐发酵，最终在科尔的铁腕下，勇士队内禁赛格林参赛一场宣告终结；可美球迷如何评价勇士内讧。","news_short_title":0,"display_type":1,"flip_page_num":0,"rela_sign":"1954652596 1440097838","content_type":1,"sex_level":0,"tj_category":3,"tj_news_attention":[["格林-->>德雷蒙德·格林",595],["杜兰特",584],["nba",267],["汤普森-->>克莱·汤普森",217],["史蒂夫-->>勇士队教练",215]],"score_topic_short_weibo":0.03714251674619307,"new_long_summary":"{\"new_long_summary\":[{\"type\":\"text\", \"data\":\"格林和杜兰特的口角逐渐发酵，最终在科尔的铁腕下，勇士队内禁赛格林参赛一场宣告终结；可美球迷如何评价勇士内讧？“你（杜兰特）马上就要进入自由市场了，你个小婊砸！”这句话成为了勇士内讧的根源之一！历来“场上鲁莽，场下人精”的格林竟说出这种小白文，令人难以置信！连一向在更衣室沉默寡言的汤普森都站出来，开口强调了团队的重要性，可见这件事在勇士队内影响有多大！\", \"para_index\":1, \"view_index\":1, \"view_hint\":\"\", \"view_keywords\":\"\", \"logic_label\":\"0\"}, {\"type\":\"image\", \"data\":{\"original\":{\"url\":\"http:\\/\\/5b0988e595225.cdn.sohucs.com\\/images\\/20181114\\/aaf6325e64814428b9503de93a8e54d1.jpeg\", \"width\":640, \"height\":504}, \"original_third\":{\"url\":\"http:\\/\\/5b0988e595225.cdn.sohucs.com\\/images\\/20181114\\/aaf6325e64814428b9503de93a8e54d1.jpeg\", \"width\":640, \"height\":504}, \"big\":{\"url\":\"http:\\/\\/t11.baidu.com\\/it\\/u=2640112372,1817035442&fm=173&app=25&f=JPEG?w=640&h=504&s=29B0209CB68F0EEC3AA07586030080A0\", \"width\":640, \"height\":504}, \"small\":{\"url\":\"http:\\/\\/t12.baidu.com\\/it\\/u=159896915,2087523580&fm=173&app=25&f=JPEG?w=480&h=360&s=29B0209CB68F0EEC3AA07586030080A0\", \"width\":480, \"height\":360}}, \"para_index\":2, \"view_index\":1, \"view_hint\":\"\", \"view_keywords\":\"\", \"logic_label\":\"0\"}, {\"type\":\"text\", \"data\":\"美球迷调侃道：没想到西部弱旅快船，不显山不露水，竟然干出了如此惊天动地的大事——他们竟然成为一支王朝球队崩坏的导火索！一位湖人球迷表示，在全明星票选中，全民发动，让格林成为全明星首发大前锋！那么格林将有资格得到一份顶薪合同，那么，杜兰特和格林必须离开一个人，从内到外瓦解勇士！但仍然有不少美球迷表示：拆散他们就能瓦解勇士，这个想法太乐观！\", \"para_index\":3, \"view_index\":2, \"view_hint\":\"\", \"view_keywords\":\"\", \"logic_label\":\"0\"}, {\"type\":\"image\", \"data\":{\"original\":{\"url\":\"http:\\/\\/5b0988e595225.cdn.sohucs.com\\/images\\/20181114\\/9535b4613bef41d5baa22c1e73dfc8bc.jpeg\", \"width\":640, \"height\":499}, \"original_third\":{\"url\":\"http:\\/\\/5b0988e595225.cdn.sohucs.com\\/images\\/20181114\\/9535b4613bef41d5baa22c1e73dfc8bc.jpeg\", \"width\":640, \"height\":499}, \"big\":{\"url\":\"http:\\/\\/t10.baidu.com\\/it\\/u=2176865364,2091152033&fm=173&app=25&f=JPEG?w=640&h=499&s=4B02498A4D9007E95268259903008093\", \"width\":640, \"height\":499}, \"small\":{\"url\":\"http:\\/\\/t12.baidu.com\\/it\\/u=4156188746,2125046199&fm=173&app=25&f=JPEG?w=480&h=360&s=4B02498A4D9007E95268259903008093\", \"width\":480, \"height\":360}}, \"para_index\":4, \"view_index\":2, \"view_hint\":\"\", \"view_keywords\":\"\", \"logic_label\":\"0\"}, {\"type\":\"image\", \"data\":{\"original\":{\"url\":\"http:\\/\\/5b0988e595225.cdn.sohucs.com\\/images\\/20181114\\/49ce736cf9454e29b7766e03b4b4ad3b.jpeg\", \"width\":640, \"height\":468}, \"original_third\":{\"url\":\"http:\\/\\/5b0988e595225.cdn.sohucs.com\\/images\\/20181114\\/49ce736cf9454e29b7766e03b4b4ad3b.jpeg\", \"width\":640, \"height\":468}, \"big\":{\"url\":\"http:\\/\\/t11.baidu.com\\/it\\/u=2840714101,4274321966&fm=173&app=25&f=JPEG?w=640&h=468&s=832004A8449A17ED86E1808C03003003\", \"width\":640, \"height\":468}, \"small\":{\"url\":\"http:\\/\\/t12.baidu.com\\/it\\/u=4247807270,1460951038&fm=173&app=25&f=JPEG?w=480&h=360&s=832004A8449A17ED86E1808C03003003\", \"width\":480, \"height\":360}}, \"para_index\":5, \"view_index\":2, \"view_hint\":\"\", \"view_keywords\":\"\", \"logic_label\":\"0\"}]}","queue_summary":{"QT_10005_data":{"queue_type":"10005","queue_attention":{"搜狐体育-sports.sohu.com":100}},"QT_10007_data":{"queue_type":"10007","queue_attention":{"体育_NBA球队动态":493}}},"innersource_type":0,"news_style_super_alpha":[],"new_summary":"勇士王朝崩坏导火索？格林辱骂杜兰特，看美球迷如何评价他们？","m_tag":"[\"杜兰特\",\"格林\",\"篮球\"]","star_private_flag":0,"media_category_id":0,"multi_cate":[{"cate":3,"ratio":95},{"cate":4,"ratio":1}],"news_sub_category_prob":0.766756,"tj_tags":[["杜兰特",190],["格林",184],["球迷",173],["勇士",171],["王朝",163],["崩坏",156],["评价",138],["辱骂",114],["这件事",39],["全明星",35],["拆散",33],["内讧",32],["瓦解",30],["科尔",27],["汤普森",25],["顶薪合同",25],["球队",24],["勇士队",20],["鱼腩",20],["自由市场",20]],"copy_time":1542208951,"title_simhash64":5822682635009111592,"tj_cate_prob":0.988634689941164,"tj_timeliness":1,"score_topic_long_content":0.03637832047367706,"scrape_hot_attention_level":0,"feedid":"","new_ds":"[{\"ds1\":589597,\"ds2\":1080522733}]\n","news_style_super":[],"old_news_recog_info":{"sim":0.0,"nid":"","type":"","url":""},"low_matching_level":0,"data_type":0,"pages_type":"0","comment":"","time":1542208977,"is_confident_source":0,"red_news_type":0,"need_cms_check":0,"news_tag":{"格林":100,"篮球":38,"杜兰特":100},"virtual_level":0,"news_style":[],"scene_type":0,"passport_id":"","title_content_non_sim_score":0.0,"mypos":"","importance_model_level":"1","replace_sign":"589597 1080522733","value_general_tags":[],"is_push":"0","quality_emergent_flags":{"50010":"common_weight","40100":"non_fr_brush_default","60100":"fr_brush_default","70010":"common_weight"},"readable_score":0.3189892172813416,"same_sign":"1954652596 1440097838","piclist_feat":"{\"pic_con_feat\": [-0.33448882897694904, -0.9962279399236044, -0.9999997814496359, -0.32861671845118207, -0.888244648774465, 0.9994938969612122, 0.9999961853027344, -0.8809561928113302, 0.9929515520731608, -0.9948535164197286, 0.6219975153605143, -0.06429458657900493, 0.999369204044342, 0.48763173818588257, -0.8110954364140829, -0.9975224733352661, -0.9999232888221741, -0.939952532450358, -0.6109296381473541, -0.999984602133433, -0.9688869714736938, 0.9999907811482748, -0.9999995032946268, 0.417418638865153, 0.999499241511027, -0.8834412296613058, -0.1405447522799174, -0.9999997417132059, 0.9999785820643107, 0.9854108293851217, 0.09522578120231628, 0.5043352345625559, 0.9999997814496359, -0.9309239784876505, -0.688925159474214, -0.5040997614463171, -0.9995265603065491, 0.33341338237126666, -0.998893678188324, 0.905943234761556, 0.3260815540949504, -0.9999999205271403, -0.21507710218429565, -0.9984458287556967, -0.31803780794143677, -0.9998881419499716, 0.07035451630751292, -0.999837060769399, 0.9094009399414062, 0.9916808406511942, -0.999151329199473, 0.9942081769307455, 0.3411323626836141, -0.9999988873799642, -0.9996364315350851, 0.1379697322845459, -0.7127868781487147, -0.2989601294199626, 1.0, 0.4938293198744456, 0.9984389146169027, -0.9987595280011495, 0.999995211760203, -0.9998893936475118, -0.925147553284963, -0.9992057681083679, 0.9984084963798523, 0.9986725648244222, 0.6514170070489248, -0.9823238253593445, 0.9999978144963583, 0.3275238076845805, 0.9997796217600504, -0.999646008014679, -0.7249682943026224, -0.3339182734489441, -0.9992825984954834, 0.9196919600168864, 0.05010536809762319, -0.989466925462087, 0.5482130646705627, -0.05238799254099528, -0.9964447021484375, -0.910463293393453, -0.9998250007629395, -0.9761807521184286, 0.9999882976214091, 0.045173294842243195, -0.9907196561495463, -0.9999948541323344, -0.3390084703763326, -0.8125026027361552, 0.9998922944068909, 0.9846229553222656, -0.33495477835337323, -0.33905025323232013, -0.9966395497322083, 0.8905658523241679, -0.9999985694885254, -0.9957149227460226, -0.9997840921084086, 0.8236258427302042, 0.9999998211860657, 0.9999932249387106, 0.9999500711758932, 0.2315251032511393, 1.0, 0.92124871412913, 0.03385332226753235, -0.9953104058901469, -1.0, -0.9998644391695658, 0.9999006390571594, -0.31239132086435956, 0.9999997417132059, -0.9998518824577332, 0.5586468577384949, 0.9994435707728068, 0.9985859990119934, 0.999999980131785, 0.9343347152074178, 0.9823905229568481, 0.9537762602170309, 0.9999773899714152, 0.999025841554006, 0.792099396387736, 0.9999989668528239, -0.6829644503692786, -0.31855746110280353, -0.32122917970021564, -0.9960776170094808, -0.9997193217277527, -0.9945716659228007, 0.9999895890553793, -0.310255765914917, 0.9998262723286947, -0.5297478586435318, 0.9996251861254374, -0.3193034927050273, 0.9448732137680054, 0.8767334222793579, 0.025652545193831127, -0.2897839993238449, -0.8438536723454794, -0.9912512898445129, 0.9999996423721313, -0.9999811848004659, -0.9999518990516663, 0.23849775393803915, -0.8872186342875162, 0.9999987483024597, -0.9439827998479208, -0.9997748136520386, -0.9999416669209799, 0.9998919566472372, -0.7190584441026052, 0.29304389158884686, -0.9590096275011698, -0.2603648900985718, -0.21511916319529215, 0.16638493537902832, -0.9999931255976359, 0.9965649644533793, -0.9999999602635702, -0.999998410542806, 0.270382821559906, 0.9754457473754883, -0.9999995430310568, 0.9961231549580892, 0.04375013709068298, -0.9957016905148824, -0.9785944024721781, 0.3322920600573222, -0.9999878605206808, -0.9999904235204061, 0.13237769405047098, 0.9734646876653036, -0.9959945877393087, 0.8081881205240885, 0.999997595945994, 0.42312514781951904, 0.9999901056289673, -0.999991257985433, 0.8030414879322052, -0.21545420090357462, 0.050146314005057015, 0.30246490240097046, 0.9996250669161478, -0.999635378519694, 0.4884815017382304, -0.5982349812984467, 0.4123028715451558, 0.9589710831642151, -0.9999793569246928, -0.9994761149088541, -0.9999538858731588, -0.9999932448069254, 0.8801790277163187, 0.9358824292818705, 0.4802661935488383, 0.9882676601409912, 0.9999959270159403, -0.09133330484231313, 0.9849520921707153, 0.9703323443730673, -0.7490278681119283, -0.9999994039535522, -0.9731230934460958, 0.9999645551045736, -0.9976027409235636, 0.5899764423569044, 0.7375567803780237, 0.3333219885826111, 0.999774714310964, -0.7766929467519125, 0.9958393375078837, -0.9350075920422872, -0.4512656529744466, -0.9995309313138326, -0.3077133695284526, 0.9999009370803833, -0.2168749968210856, 0.5833706930279732, -0.9792874256769816, 0.9999904235204061, 0.9913569092750549, -0.886561652024587, -0.9999997814496359, 0.9113774299621582, -0.962717870871226, 0.8778093854586283, -0.2979036172231038, -0.993646482626597, -0.46192724754412967, -0.9956364830334982, 0.996733287970225, -0.7997258106867472, -0.15318802992502847, 0.9999994238217672, -0.44343356291453045, 0.9982258478800455, 0.9236101110776266, 0.5252619944512844, -0.9996692736943563, -0.9326101740201315, 0.999968151251475, -0.9991815090179443, 0.7360807657241821, -0.9994610945383707, 0.9991774161656698, -0.9915407101313273, 0.9999355872472128, 0.9648192326227824, 0.3024366895357768, -0.9624957839647929, 0.9977914094924927], \"pic_con_score\": 0.58238546053568518}","vertical_types":[0],"cluster_infos_for_rank":{"cluster_attention":{"格林-->>德雷蒙德·格林":579,"篮球":210,"杜兰特":567,"nba":276},"cluster_tags":{"格林":184,"球迷":173,"杜兰特":190,"王朝":163,"崩坏":166,"勇士":171},"cluster_cnt":"2","cluster_nid":"9281180913557514411"},"importance_model_info":{"0":0.0253906,"1":0.492188,"2":0.478516},"news_category_v1_id":2,"ext_tag_term":"","query_attention":{"足球":0.4879,"伊戈达拉":0.4971,"汤普森":0.4599,"篮球":0.4755},"is_original":1,"novelty_level":2,"ext_info":"{\"ABTEST\":{\"mode\":\"1\",\"repo\":\"3\"},\"has_rtf\":0,\"has_spd\":0,\"is_pv\":0,\"original_recog_serv_ret\":{\"key_info\":{\"content\":\"一位湖人球迷表示在全明星票选中全民发动让格林成为全明星首发大前锋那么格林将有资格得到一份顶薪合同那么杜兰特和格林必须离开一个人从内到外瓦解勇士\",\"dedupid\":\"46203455227600010\",\"time\":1542208951,\"title\":\"勇士王朝崩坏导火索？格林辱骂杜兰特，看美球迷如何评价他们？\",\"url\":\"http://sports.sohu.com/20181114/n555369066.shtml\"},\"recog_ret\":\"NOSIM\",\"sim_cnt\":0},\"site_type\":0}","importance_score_v1":0.1043196183942039,"high_timeliness":0,"type_setting_level":2,"timeliness":172800,"original_name":"","push_source":"-1","author_authority_score_v1":0,"m_category":"3","new_sex_level":0,"copy_score":0.0,"kg_resource_tag":[],"cont_xpath":"","loc_news":0,"from_id":"queue_dongxi","author_activity_score":-1,"check_locname":{},"m_display_url":"","informative_level":1,"news_short_hierarchy":[{"path":[["nba=>篮球",231],["汤普森-->>克莱·汤普森=>篮球",231]],"topic":"篮球"}],"img_num":4,"title_simhash":"49560325311236612356117237161550151470","new_image_sign":"[{\"img_id\":528014348330587661,\"sign\":[528014348330587661]}, {\"img_id\":17369858536517089053,\"sign\":[17369858536517089053]}, {\"img_id\":17740288432021035201,\"sign\":[17740288432021035201]}, {\"img_id\":18438209867680794870,\"sign\":[18438209867680794870]}]","title_intr_wordseg":{"仍然":0.0,"一":0.0,"终结":0.0,"强调":0.0,"这种":0.0,"更衣室":0.4035737794427855,"将":0.0,"全明星":0.74634335306277,"汤普森":0.6835472310915861,"有":0.0,"看":0.0,"下":0.0,"宣告":0.0,"不":0.0,"合同":0.6971267251076552,"勇士":1.135541712191992,"我":0.0,"向":0.0,"逐渐":0.0,"那么":0.0,"外":0.0,"吗":0.0,"这句话":0.5728086432875569,"如何":0.0,"小婊砸":1.0,"场上":0.0,"多":0.0,"场下":0.0,"成为":0.0,"一支":0.3753517925046495,"在":0.0,"湖人":0.8655760696387137,"如此":0.0,"个":0.0,"太":0.0,"到":0.0,"竟然":0.0,"场":0.0,"显":0.0,"惊天动地":0.0,"口角":0.6531770633122592,"但":0.0,"之":0.0,"崩坏":1.829185227984234,"位":0.0,"大事":0.5388333392290495,"鲁莽":0.0,"露水":0.5148763021942758,"拆散":0.0,"道":0.0,"选中":0.0,"沉默寡言":0.0,"西部":0.0,"必须":0.0,"球迷":1.251518979761991,"做":0.0,"没想到":0.0,"你":0.0,"重要性":0.404934896603045,"票":0.4246566912368275,"科尔":1.099563549868109,"马上就要":1.0,"山":0.2517290803634691,"得到":0.0,"干":0.0,"球队":0.4700502016344786,"导火索":1.36988512331922,"顶":0.0,"团队":0.2807944420750586,"影响":0.0,"乐观":0.0,"根源":0.8407290835717597,"其中":0.0,"鱼腩":1.0,"的":0.0,"令人难以置信":0.5616450599441556,"内":0.0,"了":0.0,"和":0.0,"美":0.0,"只是":0.0,"小白文":0.5397764579469534,"站出来":0.3728630428265215,"历来":0.0,"得":0.0,"说出":0.0,"有多大":0.2658265897896616,"大前锋":0.9557034007774092,"快船":0.7328006630153967,"评价":0.0,"全民":0.5630833014578616,"梦":0.9906351073547344,"铁腕":0.8294580289660023,"让":0.0,"离开":0.0,"薪":0.0,"不少":0.0,"不大":0.0,"瓦解":0.0,"可见":0.0,"点子":1.0,"人":0.1578602110691049,"精":0.0,"弱旅":1.0,"表示":0.0,"想象":0.0,"心":0.297159582656567,"最终":0.0,"内讧":0.0,"这件事":0.3979466219485409,"种":0.0,"从":0.0,"发酵":0.0,"季后赛":0.4706229154225071,"参赛":0.0,"有资格":1.0,"格林":2.236921093961763,"还":0.0,"勇士队":0.5914103567715278,"进":0.0,"连":0.0,"竟":0.0,"他们":0.0,"辱骂":0.0,"可能":0.0,"这个想法":1.0,"就能":0.2347000067709798,"开口":0.0,"首发":0.5006766744779375,"杜兰特":1.913796576889819,"叫":0.0,"自由市场":1.0,"可":0.0,"调侃":0.0,"深":0.0,"怎么":0.0,"想":0.0,"禁赛":0.0,"难以":0.0,"出":0.0,"进入":0.0,"王朝":1.491093290741575,"都":0.0,"发动":0.0,"份":0.0,"一个人":0.476629975636996},"quality_feature_score":0.3189892172813416,"priori_quality_score":0.8334978810711288,"quality_status":"","para_content":{"idset":[80003],"replace_sign":"589597 1080522733","duplicate_sign":"589597 1080522733","content":[{"data":"格林和杜兰特的口角逐渐发酵，最终在科尔的铁腕下，勇士队内禁赛格林参赛一场宣告终结；可美球迷如何评价勇士内讧？","type":"text"},{"data":{"cont_small":{"src":"http://t11.baidu.com/it/u=4219124845,1084696370&fm=173&app=25&f=JPEG?w=320&h=252&s=29B0209CB68F0EEC3AA07586030080A0","width":320,"height":252},"small":{"width":480,"url":"http://t12.baidu.com/it/u=159896915,2087523580&fm=173&app=25&f=JPEG?w=480&h=360&s=29B0209CB68F0EEC3AA07586030080A0","height":360},"big":{"width":640,"url":"http://t11.baidu.com/it/u=2640112372,1817035442&fm=173&app=25&f=JPEG?w=640&h=504&s=29B0209CB68F0EEC3AA07586030080A0","height":504},"original":{"low_quality_type":0,"feature_json_format":"{\"aesthetic\":-1.6205762624741,\"antiporn_normal\":0.999476,\"antiporn_porn\":0.000319,\"antiporn_sexy\":0.000205,\"array\":[{\"locheight\":20,\"locleft\":14,\"loctop\":7,\"locwidth\":616,\"ocrresult\":\" [ story with @ spearsespn and me : late game exchange between kevin durant dray\"},{\"locheight\":21,\"locleft\":15,\"loctop\":25,\"locwidth\":616,\"ocrresult\":\" mond green carried into locker room monday night w \\/ oudly confronting green for decisio\"},{\"locheight\":16,\"locleft\":15,\"loctop\":48,\"locwidth\":568,\"ocrresult\":\" n - making on final play of regulation . scene described as one of most intense of this g - state era .\"},{\"locheight\":21,\"locleft\":14,\"loctop\":79,\"locwidth\":618,\"ocrresult\":\"Woj:\\u4e0eEsPN\\u7684 Marc spears\\u8054\\u5408\\u62a5\\u9053:\\u5468\\u665a,\\u793e\\u5170\\u7279\\u548c\\u683c\\u6797\\u5728\\u6bd4\\u8d5b\\u672b\\u5c3e\\u53d1\\u751f\\u4e86\\u4e89\\u6267,\\u540e\\u8fd9\\u5a07\\u4e89\\u5435\\u5ef6\\u7eed\\u5230\\u4e86\"},{\"locheight\":19,\"locleft\":15,\"loctop\":101,\"locwidth\":616,\"ocrresult\":\"\\u66f4\\u8863\\u5ba4\\u3002\\u961f\\u53cb\\u4eec\\u5927\\u58f0\\u5730\\u9488\\u5bf9\\u683c\\u6797\\u5e38\\u89c4\\u65f6\\u95f4\\u7684\\u8d14\\u540e\\u4e00\\u653b\\u51b3\\u7b56\\u63d0\\u8d77\\u8d28\\u8d51\\u3002\\u636e\\u63cf\\u8ff0,\\u5f53\\u65f6\\u7684\\u573a\\u666f\\u662f(\\u675c\\u5170\\u7279\\u52a0\\u96b0\\u540e\\u7684)\\u52c7\"},{\"locheight\":15,\"locleft\":15,\"loctop\":120,\"locwidth\":88,\"ocrresult\":\"\\u58eb\\u65f6\\u4ee3\\u6700\\u7d27\\u5f20\\u4e4b\"},{\"locheight\":29,\"locleft\":450,\"loctop\":423,\"locwidth\":43,\"ocrresult\":\"23\"}],\"clarity\":0.24382677674294,\"contsign\":\"3733825992,2428286652\",\"disgust\":9.8357204478816e-6,\"feature_970_topn\":[{\"cid\":196,\"val\":0.87401378154755},{\"cid\":194,\"val\":0.058382924646139},{\"cid\":201,\"val\":0.022879371419549},{\"cid\":216,\"val\":0.013506608083844},{\"cid\":218,\"val\":0.002613123273477}],\"feature_sexy_lady\":0.0011969044571742,\"main_area\":{\"height\":353,\"left\":5,\"top\":153,\"width\":600},\"porn_prob\":0.000319,\"same_feature_with_hash\":\"{\\\"same_feature_hash_id\\\":46631,\\\"same_feature_hash_ids\\\":[46631,47078,178727,179174,46992,179088,124455,124902,124816]}\"}","width":640,"image_format":"JPEG","url":"http://5b0988e595225.cdn.sohucs.com/images/20181114/aaf6325e64814428b9503de93a8e54d1.jpeg","height":504},"original_third":{"low_quality_type":0,"feature_json_format":"{\"aesthetic\":-1.6205762624741,\"antiporn_normal\":0.999476,\"antiporn_porn\":0.000319,\"antiporn_sexy\":0.000205,\"array\":[{\"locheight\":20,\"locleft\":14,\"loctop\":7,\"locwidth\":616,\"ocrresult\":\" [ story with @ spearsespn and me : late game exchange between kevin durant dray\"},{\"locheight\":21,\"locleft\":15,\"loctop\":25,\"locwidth\":616,\"ocrresult\":\" mond green carried into locker room monday night w \\/ oudly confronting green for decisio\"},{\"locheight\":16,\"locleft\":15,\"loctop\":48,\"locwidth\":568,\"ocrresult\":\" n - making on final play of regulation . scene described as one of most intense of this g - state era .\"},{\"locheight\":21,\"locleft\":14,\"loctop\":79,\"locwidth\":618,\"ocrresult\":\"Woj:\\u4e0eEsPN\\u7684 Marc spears\\u8054\\u5408\\u62a5\\u9053:\\u5468\\u665a,\\u793e\\u5170\\u7279\\u548c\\u683c\\u6797\\u5728\\u6bd4\\u8d5b\\u672b\\u5c3e\\u53d1\\u751f\\u4e86\\u4e89\\u6267,\\u540e\\u8fd9\\u5a07\\u4e89\\u5435\\u5ef6\\u7eed\\u5230\\u4e86\"},{\"locheight\":19,\"locleft\":15,\"loctop\":101,\"locwidth\":616,\"ocrresult\":\"\\u66f4\\u8863\\u5ba4\\u3002\\u961f\\u53cb\\u4eec\\u5927\\u58f0\\u5730\\u9488\\u5bf9\\u683c\\u6797\\u5e38\\u89c4\\u65f6\\u95f4\\u7684\\u8d14\\u540e\\u4e00\\u653b\\u51b3\\u7b56\\u63d0\\u8d77\\u8d28\\u8d51\\u3002\\u636e\\u63cf\\u8ff0,\\u5f53\\u65f6\\u7684\\u573a\\u666f\\u662f(\\u675c\\u5170\\u7279\\u52a0\\u96b0\\u540e\\u7684)\\u52c7\"},{\"locheight\":15,\"locleft\":15,\"loctop\":120,\"locwidth\":88,\"ocrresult\":\"\\u58eb\\u65f6\\u4ee3\\u6700\\u7d27\\u5f20\\u4e4b\"},{\"locheight\":29,\"locleft\":450,\"loctop\":423,\"locwidth\":43,\"ocrresult\":\"23\"}],\"clarity\":0.24382677674294,\"contsign\":\"3733825992,2428286652\",\"disgust\":9.8357204478816e-6,\"feature_970_topn\":[{\"cid\":196,\"val\":0.87401378154755},{\"cid\":194,\"val\":0.058382924646139},{\"cid\":201,\"val\":0.022879371419549},{\"cid\":216,\"val\":0.013506608083844},{\"cid\":218,\"val\":0.002613123273477}],\"feature_sexy_lady\":0.0011969044571742,\"main_area\":{\"height\":353,\"left\":5,\"top\":153,\"width\":600},\"porn_prob\":0.000319,\"same_feature_with_hash\":\"{\\\"same_feature_hash_id\\\":46631,\\\"same_feature_hash_ids\\\":[46631,47078,178727,179174,46992,179088,124455,124902,124816]}\"}","width":640,"image_format":"JPEG","url":"http://5b0988e595225.cdn.sohucs.com/images/20181114/aaf6325e64814428b9503de93a8e54d1.jpeg","height":504},"caption":""},"type":"image"},{"data":"“你（杜兰特）马上就要进入自由市场了，你个小婊砸！”这句话成为了勇士内讧的根源之一！历来“场上鲁莽，场下人精”的格林竟说出这种小白文，令人难以置信！","type":"text"},{"data":"连一向在更衣室沉默寡言的汤普森都站出来，开口强调了团队的重要性，可见这件事在勇士队内影响有多大！","type":"text"},{"data":"美球迷怎么评价这件事？","type":"text"},{"data":{"cont_small":{"src":"http://t12.baidu.com/it/u=229528574,2025499134&fm=173&app=25&f=JPEG?w=320&h=250&s=4B02498A4D9007E95268259903008093","width":320,"height":250},"small":{"width":480,"url":"http://t12.baidu.com/it/u=4156188746,2125046199&fm=173&app=25&f=JPEG?w=480&h=360&s=4B02498A4D9007E95268259903008093","height":360},"big":{"width":640,"url":"http://t10.baidu.com/it/u=2176865364,2091152033&fm=173&app=25&f=JPEG?w=640&h=499&s=4B02498A4D9007E95268259903008093","height":499},"original":{"low_quality_type":0,"feature_json_format":"{\"aesthetic\":0.5536093711853,\"antiporn_normal\":0.996077,\"antiporn_porn\":0.001065,\"antiporn_sexy\":0.002858,\"array\":[{\"locheight\":17,\"locleft\":12,\"loctop\":3,\"locwidth\":620,\"ocrresult\":\" Imagine after all they ve gone through . the clippers may actually play a small part in the warriors dynast\"},{\"locheight\":19,\"locleft\":8,\"loctop\":46,\"locwidth\":520,\"ocrresult\":\"\\u5feb\\u8239\\u7403\\u8ff7:\\u6211\\u8239\\u8fd9\\u4e9b\\u5e74\\u7ecf\\u5386\\u4e86\\u65e0\\u6570\\u96be,\\u5982\\u4eca\\u8fd8\\u771f\\u6709\\u53ef\\u80fd\\u4e3a\\u52c7\\u58eb\\u738b\\u671d\\u89e3\\u4f53\\u505a\\u51fa\\u4e00\\u70b9\\u5fae\\u5c0f\\u7684\\u8d21?\"},{\"locheight\":17,\"locleft\":8,\"loctop\":64,\"locwidth\":139,\"ocrresult\":\"\\u68a6,\\u505a\\u5f97\\u4e0d\\u5927,\\u8fd8\\u53eb\\u68a6\\u5417\"}],\"clarity\":1.0226001739502,\"contsign\":\"3635503010,1600128633\",\"disgust\":5.0552651373437e-5,\"feature_970_topn\":[{\"cid\":201,\"val\":0.72940051555634},{\"cid\":188,\"val\":0.062286946922541},{\"cid\":212,\"val\":0.055911667644978},{\"cid\":196,\"val\":0.034509669989347},{\"cid\":194,\"val\":0.024747719988227}],\"feature_sexy_lady\":0.014979796484113,\"main_area\":{\"height\":426,\"left\":3,\"top\":79,\"width\":627},\"porn_prob\":0.001065,\"same_feature_with_hash\":\"{\\\"same_feature_hash_id\\\":178727,\\\"same_feature_hash_ids\\\":[178727,179174,163879,164326,178860,164012,242727,243174,242860]}\"}","width":640,"image_format":"JPEG","url":"http://5b0988e595225.cdn.sohucs.com/images/20181114/9535b4613bef41d5baa22c1e73dfc8bc.jpeg","height":499},"original_third":{"low_quality_type":0,"feature_json_format":"{\"aesthetic\":0.5536093711853,\"antiporn_normal\":0.996077,\"antiporn_porn\":0.001065,\"antiporn_sexy\":0.002858,\"array\":[{\"locheight\":17,\"locleft\":12,\"loctop\":3,\"locwidth\":620,\"ocrresult\":\" Imagine after all they ve gone through . the clippers may actually play a small part in the warriors dynast\"},{\"locheight\":19,\"locleft\":8,\"loctop\":46,\"locwidth\":520,\"ocrresult\":\"\\u5feb\\u8239\\u7403\\u8ff7:\\u6211\\u8239\\u8fd9\\u4e9b\\u5e74\\u7ecf\\u5386\\u4e86\\u65e0\\u6570\\u96be,\\u5982\\u4eca\\u8fd8\\u771f\\u6709\\u53ef\\u80fd\\u4e3a\\u52c7\\u58eb\\u738b\\u671d\\u89e3\\u4f53\\u505a\\u51fa\\u4e00\\u70b9\\u5fae\\u5c0f\\u7684\\u8d21?\"},{\"locheight\":17,\"locleft\":8,\"loctop\":64,\"locwidth\":139,\"ocrresult\":\"\\u68a6,\\u505a\\u5f97\\u4e0d\\u5927,\\u8fd8\\u53eb\\u68a6\\u5417\"}],\"clarity\":1.0226001739502,\"contsign\":\"3635503010,1600128633\",\"disgust\":5.0552651373437e-5,\"feature_970_topn\":[{\"cid\":201,\"val\":0.72940051555634},{\"cid\":188,\"val\":0.062286946922541},{\"cid\":212,\"val\":0.055911667644978},{\"cid\":196,\"val\":0.034509669989347},{\"cid\":194,\"val\":0.024747719988227}],\"feature_sexy_lady\":0.014979796484113,\"main_area\":{\"height\":426,\"left\":3,\"top\":79,\"width\":627},\"porn_prob\":0.001065,\"same_feature_with_hash\":\"{\\\"same_feature_hash_id\\\":178727,\\\"same_feature_hash_ids\\\":[178727,179174,163879,164326,178860,164012,242727,243174,242860]}\"}","width":640,"image_format":"JPEG","url":"http://5b0988e595225.cdn.sohucs.com/images/20181114/9535b4613bef41d5baa22c1e73dfc8bc.jpeg","height":499},"caption":""},"type":"image"},{"data":"美球迷调侃道：没想到西部弱旅快船，不显山不露水，竟然干出了如此惊天动地的大事——他们竟然成为一支王朝球队崩坏的导火索！","type":"text"},{"data":"“梦做的不大，还叫梦吗？”难以想象，他们只是一支有可能连季后赛都进不了的鱼腩球队。","type":"text"},{"data":{"cont_small":{"src":"http://t12.baidu.com/it/u=3193909571,1984092170&fm=173&app=25&f=JPEG?w=320&h=234&s=832004A8449A17ED86E1808C03003003","width":320,"height":234},"small":{"width":480,"url":"http://t12.baidu.com/it/u=4247807270,1460951038&fm=173&app=25&f=JPEG?w=480&h=360&s=832004A8449A17ED86E1808C03003003","height":360},"big":{"width":640,"url":"http://t11.baidu.com/it/u=2840714101,4274321966&fm=173&app=25&f=JPEG?w=640&h=468&s=832004A8449A17ED86E1808C03003003","height":468},"original":{"low_quality_type":32,"feature_json_format":"{\"aesthetic\":1.4453283548355,\"antiporn_normal\":0.998336,\"antiporn_porn\":0.000218,\"antiporn_sexy\":0.001446,\"array\":[{\"locheight\":23,\"locleft\":3,\"loctop\":0,\"locwidth\":631,\"ocrresult\":\" Man this would be such an evil campaign by the internet vote dray as a starter to ruin the warriors dyn\"},{\"locheight\":17,\"locleft\":3,\"loctop\":23,\"locwidth\":148,\"ocrresult\":\" asty . i love it . let ' s do it .\"},{\"locheight\":17,\"locleft\":2,\"loctop\":42,\"locwidth\":633,\"ocrresult\":\"\\u6e56\\u4eba\\u7403\\u8ff7:\\u6211\\u9760,\\u8fd9\\u542c\\u7740\\u50cf\\u662f\\u7f51\\u4e0a\\u53d1\\u8d77\\u7684\\u90aa\\u6076\\u8fd0\\u52a8\\u671f,\\u628a\\u683c\\u6797\\u6295\\u6210\\u5168\\u660e\\u661f\\u9996\\u53d1\\u4ece\\u800c\\u6467\\u6bc1\\u52c7\\u58eb\\u738b\\u671d\\u3002\\u6211\\u559c\\u6b22,\\u4e00\\u8d77\\u6765\"},{\"locheight\":29,\"locleft\":284,\"loctop\":258,\"locwidth\":46,\"ocrresult\":\"35\"}],\"clarity\":3.4930624961853,\"contsign\":\"2423624123,3076698353\",\"disgust\":5.0567596190376e-5,\"feature_970_topn\":[{\"cid\":201,\"val\":0.50611311197281},{\"cid\":196,\"val\":0.3828592300415},{\"cid\":212,\"val\":0.080235049128532},{\"cid\":213,\"val\":0.0097663076594472},{\"cid\":217,\"val\":0.0036623657215387}],\"feature_sexy_lady\":0.020666144788265,\"main_area\":{\"height\":403,\"left\":2,\"top\":71,\"width\":625},\"porn_prob\":0.000218,\"same_feature_with_hash\":\"{\\\"same_feature_hash_id\\\":178727,\\\"same_feature_hash_ids\\\":[178727,178860,46631,46764,178863,46767,164903,165036,165039]}\"}","width":640,"image_format":"JPEG","url":"http://5b0988e595225.cdn.sohucs.com/images/20181114/49ce736cf9454e29b7766e03b4b4ad3b.jpeg","height":468},"original_third":{"low_quality_type":32,"feature_json_format":"{\"aesthetic\":1.4453283548355,\"antiporn_normal\":0.998336,\"antiporn_porn\":0.000218,\"antiporn_sexy\":0.001446,\"array\":[{\"locheight\":23,\"locleft\":3,\"loctop\":0,\"locwidth\":631,\"ocrresult\":\" Man this would be such an evil campaign by the internet vote dray as a starter to ruin the warriors dyn\"},{\"locheight\":17,\"locleft\":3,\"loctop\":23,\"locwidth\":148,\"ocrresult\":\" asty . i love it . let ' s do it .\"},{\"locheight\":17,\"locleft\":2,\"loctop\":42,\"locwidth\":633,\"ocrresult\":\"\\u6e56\\u4eba\\u7403\\u8ff7:\\u6211\\u9760,\\u8fd9\\u542c\\u7740\\u50cf\\u662f\\u7f51\\u4e0a\\u53d1\\u8d77\\u7684\\u90aa\\u6076\\u8fd0\\u52a8\\u671f,\\u628a\\u683c\\u6797\\u6295\\u6210\\u5168\\u660e\\u661f\\u9996\\u53d1\\u4ece\\u800c\\u6467\\u6bc1\\u52c7\\u58eb\\u738b\\u671d\\u3002\\u6211\\u559c\\u6b22,\\u4e00\\u8d77\\u6765\"},{\"locheight\":29,\"locleft\":284,\"loctop\":258,\"locwidth\":46,\"ocrresult\":\"35\"}],\"clarity\":3.4930624961853,\"contsign\":\"2423624123,3076698353\",\"disgust\":5.0567596190376e-5,\"feature_970_topn\":[{\"cid\":201,\"val\":0.50611311197281},{\"cid\":196,\"val\":0.3828592300415},{\"cid\":212,\"val\":0.080235049128532},{\"cid\":213,\"val\":0.0097663076594472},{\"cid\":217,\"val\":0.0036623657215387}],\"feature_sexy_lady\":0.020666144788265,\"main_area\":{\"height\":403,\"left\":2,\"top\":71,\"width\":625},\"porn_prob\":0.000218,\"same_feature_with_hash\":\"{\\\"same_feature_hash_id\\\":178727,\\\"same_feature_hash_ids\\\":[178727,178860,46631,46764,178863,46767,164903,165036,165039]}\"}","width":640,"image_format":"JPEG","url":"http://5b0988e595225.cdn.sohucs.com/images/20181114/49ce736cf9454e29b7766e03b4b4ad3b.jpeg","height":468},"caption":""},"type":"image"},{"data":"不少球迷想出了多种拆散勇士王朝的点子，其中一个深得我心！","type":"text"},{"data":"一位湖人球迷表示“在全明星票选中，全民发动，让格林成为全明星首发大前锋！那么格林将有资格得到一份顶薪合同”，那么，杜兰特和格林必须离开一个人，从内到外瓦解勇士！","type":"text"},{"data":{"cont_small":{"src":"http://t12.baidu.com/it/u=3329840975,510291623&fm=173&app=25&f=JPEG?w=320&h=213&s=2EA3208C6C53BEDC5CA416830300E08F","width":320,"height":213},"small":{"width":480,"url":"http://t12.baidu.com/it/u=3561670007,1943450254&fm=173&app=25&f=JPEG?w=480&h=360&s=2EA3208C6C53BEDC5CA416830300E08F","height":360},"big":{"width":640,"url":"http://t12.baidu.com/it/u=2470776695,275776136&fm=173&app=25&f=JPEG?w=640&h=426&s=2EA3208C6C53BEDC5CA416830300E08F","height":426},"original":{"low_quality_type":0,"feature_json_format":"{\"aesthetic\":2.9100289344788,\"antiporn_normal\":0.99873,\"antiporn_porn\":2.4e-5,\"antiporn_sexy\":0.001246,\"array\":[{\"locheight\":21,\"locleft\":541,\"loctop\":186,\"locwidth\":17,\"ocrresult\":\"9\"}],\"clarity\":2.5328080654144,\"contsign\":\"133935982,2267365010\",\"disgust\":2.7369169401936e-6,\"feature_970_topn\":[{\"cid\":196,\"val\":0.68148899078369},{\"cid\":201,\"val\":0.2935982644558},{\"cid\":212,\"val\":0.0082486197352409},{\"cid\":194,\"val\":0.0048978864215314},{\"cid\":216,\"val\":0.0043523418717086}],\"feature_sexy_lady\":0.00042520245187916,\"main_area\":{\"height\":419,\"left\":1,\"top\":16,\"width\":631},\"porn_prob\":2.4e-5,\"same_feature_with_hash\":\"{\\\"same_feature_hash_id\\\":46816,\\\"same_feature_hash_ids\\\":[46816,46833,178912,178929,47041,179137,165088,165105,165313]}\"}","width":640,"image_format":"JPEG","url":"http://5b0988e595225.cdn.sohucs.com/images/20181114/b4cd5d3e631d4995aee168a31c61b3eb.jpeg","height":426},"original_third":{"low_quality_type":0,"feature_json_format":"{\"aesthetic\":2.9100289344788,\"antiporn_normal\":0.99873,\"antiporn_porn\":2.4e-5,\"antiporn_sexy\":0.001246,\"array\":[{\"locheight\":21,\"locleft\":541,\"loctop\":186,\"locwidth\":17,\"ocrresult\":\"9\"}],\"clarity\":2.5328080654144,\"contsign\":\"133935982,2267365010\",\"disgust\":2.7369169401936e-6,\"feature_970_topn\":[{\"cid\":196,\"val\":0.68148899078369},{\"cid\":201,\"val\":0.2935982644558},{\"cid\":212,\"val\":0.0082486197352409},{\"cid\":194,\"val\":0.0048978864215314},{\"cid\":216,\"val\":0.0043523418717086}],\"feature_sexy_lady\":0.00042520245187916,\"main_area\":{\"height\":419,\"left\":1,\"top\":16,\"width\":631},\"porn_prob\":2.4e-5,\"same_feature_with_hash\":\"{\\\"same_feature_hash_id\\\":46816,\\\"same_feature_hash_ids\\\":[46816,46833,178912,178929,47041,179137,165088,165105,165313]}\"}","width":640,"image_format":"JPEG","url":"http://5b0988e595225.cdn.sohucs.com/images/20181114/b4cd5d3e631d4995aee168a31c61b3eb.jpeg","height":426},"caption":""},"type":"image"},{"data":"但仍然有不少美球迷表示：拆散他们就能瓦解勇士，这个想法太乐观！","type":"text"}]},"news_lda":[[743,0.2986547085201794],[737,0.03796711509715994],[46,0.03527653213751868],[355,0.03258594917787743],[643,0.03139013452914798],[782,0.02959641255605381],[1132,0.02720478325859492],[1107,0.02541106128550075],[202,0.02511210762331838],[334,0.02481315396113602],[1030,0.02272047832585949],[1115,0.02242152466367713],[725,0.02242152466367713],[1127,0.02122571001494768],[1159,0.01913303437967115],[1445,0.01853512705530643],[1174,0.01823617339312407],[1093,0.014050822122571],[838,0.01345291479820628],[184,0.01345291479820628],[1418,0.009865470852017937],[270,0.009566517189835577],[677,0.009267563527653214],[637,0.009267563527653214],[518,0.009267563527653214],[1188,0.009267563527653214],[451,0.009267563527653214],[1283,0.009267563527653214],[20,0.009267563527653214],[738,0.008968609865470852],[1281,0.008968609865470852],[423,0.008968609865470852],[332,0.008968609865470852],[298,0.008968609865470852],[1354,0.008968609865470852],[918,0.008968609865470852],[934,0.008968609865470852],[998,0.00837070254110613],[816,0.00837070254110613],[1011,0.007772795216741405],[206,0.007772795216741405],[717,0.007174887892376682],[752,0.006278026905829596],[829,0.005680119581464873],[1493,0.005082212257100149],[873,0.004484304932735426],[504,0.004484304932735426],[256,0.004484304932735426],[1047,0.004484304932735426],[1138,0.004185351270553065],[726,0.003288490284005979],[460,0.002391629297458894],[1346,0.002092675635276532],[240,0.00179372197309417],[1273,0.001195814648729447],[898,0.0002989536621823618],[1349,0.0002989536621823618],[86,0.0002989536621823618]],"m_from":"2","news_category_id":3,"PIP_HEADER":{"Priority":"0","Product":"midway","Extra-data":{"spider_t":1542208976701,"dc_t":1542208977705},"Url":"http://sports.sohu.com/20181114/n555369066.shtml"},"content_simhash64":8998125269879137836,"score_attraction":1.3231129897381189E-17,"author_quality_score":-1,"gram_check_level":0,"product":"midway","local_authority_info":{"level":0,"from":""},"m_ext":"{\"8\":{\"long_summary\":\"格林和杜兰特的口角逐渐发酵，最终在科尔的铁腕下，勇士队内禁赛格林参赛一场宣告终结；可美球迷如何评价勇士内讧？“你（杜兰特）马上就要进入自由市场了，你个小婊砸！”这句话成为了勇士内讧的根源之一！历来“场上鲁莽，场下人精”的格林竟说出这种小白文，令人难以置信！连一向在更衣室沉默寡言的汤普森都站出来，开口强调了团队的重要性，可见这件事在勇士队内影响有多大！美球迷调侃道：没想到西部弱旅快船，不显山不露水，竟然干出了如此惊天动地的大事——他们竟然成为一支王朝球队崩坏的导火索！不少球迷想出了多种拆散勇士王朝的点子，其中一个深得我心！但仍然有不少美球迷表示：拆散他们就能瓦解勇士，这个想法太乐观！\"},\"displaytype_exinfo\":\"\",\"ext_info\":{\"ABTEST\":{\"mode\":\"1\",\"repo\":\"3\"},\"has_rtf\":0,\"has_spd\":0,\"is_pv\":0,\"original_recog_serv_ret\":{\"key_info\":{\"content\":\"一位湖人球迷表示在全明星票选中全民发动让格林成为全明星首发大前锋那么格林将有资格得到一份顶薪合同那么杜兰特和格林必须离开一个人从内到外瓦解勇士\",\"dedupid\":\"46203455227600010\",\"time\":1542208951,\"title\":\"勇士王朝崩坏导火索？格林辱骂杜兰特，看美球迷如何评价他们？\",\"url\":\"http://sports.sohu.com/20181114/n555369066.shtml\"},\"recog_ret\":\"NOSIM\",\"sim_cnt\":0},\"site_type\":0},\"innersource_id\":\"\",\"sourceid\":80003}","is_scarce_sub_category_v1":1,"news_hierarchy":[{"path":[["nba=>篮球=>球类运动=>体育项目=>体育",231],["汤普森-->>克莱·汤普森=>篮球=>球类运动=>体育项目=>体育",231]],"topic":"篮球"}],"content_simhash":"130653127443655208404556767055265609519","title_defect_bad_str":"","para_num":9,"news_importance":0,"title_nerl_plus":[["勇士","","0","4"],["王朝","","4","4"],["崩坏","","8","4"],["导火索","","12","6"],["？","","18","2"],["格林","1007","20","4"],["辱骂","","24","4"],["杜兰特","1007","28","6"],["，","","34","2"],["看","","36","2"],["美","2200","38","2"],["球迷","","40","4"],["如何","","44","4"],["评价","","48","4"],["他们","","52","4"],["？","","56","2"]],"url":"http://sports.sohu.com/20181114/n555369066.shtml","metaapi_versionkey":1542225292026,"disgust_level":0,"filter":1,"site":"sports.sohu.com","tj_ldas":[[93,108],[35,20],[16,4],[3,3],[20,0]],"new_sex_level_rule":0,"novelty_feed_sim":0.0,"original_url":"","img_urls":"{\"image_score_beta\": [{\"url\": \"http://t11.baidu.com/it/u=980303476,3546484602&fm=173&app=25&f=JPEG?w=218&h=146&s=4B02498A4D9007E95268259903008093\", \"image_score_beta\": -0.67532598972321, \"height\": 146, \"width\": 218}, {\"url\": \"http://t12.baidu.com/it/u=184648805,3595241792&fm=173&app=25&f=JPEG?w=218&h=146&s=832004A8449A17ED86E1808C03003003\", \"image_score_beta\": -0.41119229793549, \"height\": 146, \"width\": 218}, {\"url\": \"http://t11.baidu.com/it/u=1379924773,2240087527&fm=173&app=25&f=JPEG?w=218&h=146&s=2EA3208C6C53BEDC5CA416830300E08F\", \"image_score_beta\": 3.3924374580383, \"height\": 146, \"width\": 218}], \"author_img\": {\"original\": {\"url\": null, \"width\": null, \"height\": null}}, \"imgurls\": [{\"url\": \"http://t12.baidu.com/it/u=3111758387,809779261&fm=173&app=25&f=JPEG?w=218&h=146&s=29B0209CB68F0EEC3AA07586030080A0\", \"width\": 218, \"height\": 146}, {\"url\": \"http://t11.baidu.com/it/u=980303476,3546484602&fm=173&app=25&f=JPEG?w=218&h=146&s=4B02498A4D9007E95268259903008093\", \"width\": 218, \"height\": 146}, {\"url\": \"http://t12.baidu.com/it/u=184648805,3595241792&fm=173&app=25&f=JPEG?w=218&h=146&s=832004A8449A17ED86E1808C03003003\", \"width\": 218, \"height\": 146}, {\"url\": \"http://t11.baidu.com/it/u=1379924773,2240087527&fm=173&app=25&f=JPEG?w=218&h=146&s=2EA3208C6C53BEDC5CA416830300E08F\", \"width\": 218, \"height\": 146}], \"bimgurls\": null, \"gimgurls\": null}","novelty_copy_score":0.0,"author_authority_score":-1,"logid":1617123281596649,"source_id":80003,"url_3g":"","m_display_type":"1","public_time":1542208951,"plsa":{"58":699,"116":533,"208":524,"141":1325,"142":2068},"feedcms_operation_oldnews":0,"real_time":1542208951,"command_no":1,"tag_square":470.7281593446477,"new_sex_score":0.03609800245934769,"title_ner":[["勇士","NOR","n"],["王朝","NOR","n"],["崩坏","NOR","v"],["导火索","NOR","n"],["？","NOR","w"],["格林","BRD","nr"],["辱骂","NOR","nr"],["杜兰特","PER","nr"],["，","NOR","w"],["看","RQST_VDO","v"],["美","NOR","j"],["球迷","NOR","n"],["如何","NOR","r"],["评价","RQST_DOC","v"],["他们","NOR","r"],["？","NOR","w"]],"base_weight":55,"elevate_ratio":{"bs":1.0,"grc":1.0,"ucf":1.0,"matchnet":1.0,"gr":1.0,"icf":1.0,"cb":1.0},"thread_id":"1000000010021135","title_attentions":{"杜兰特":584},"rule_quality_level":3,"is_valid_attention":1,"anti_spam":{"source_id_status":"normal","url_status":"normal","tradition_char":0,"title_weirdochat_status":"normal","content_inferior_status":"normal","mthid_status":"normal","nid_status":"normal","title_inferior_status":"normal"},"content_len":852,"copy_level":0,"mth_data":{},"small_big_lists":"[{\"small_list\":{\"height\":146,\"image_score\":-1.45806980133060,\"image_score_alpha\":1.0,\"image_score_alpha_desc\":\"image_score_alpha_20170407_beta1,cal four scores for test\",\"image_score_beta\":-1.4570193290710,\"image_score_beta_desc\":\"image_score_beta_20170407_beta1,cal four scores for test\",\"image_score_delta\":-1.45806980133060,\"image_score_delta_desc\":\"image_score_delta_20170407_beta1,cal four scores for test\",\"image_score_desc\":\"image_score_20170407_beta1,cal four scores for test\",\"src\":\"http://t12.baidu.com/it/u=3111758387,809779261&fm=173&app=25&f=JPEG?w=218&h=146&s=29B0209CB68F0EEC3AA07586030080A0\",\"width\":218}},{\"small_list\":{\"height\":146,\"image_score\":-0.685437083244320,\"image_score_alpha\":1.0,\"image_score_alpha_desc\":\"image_score_alpha_20170407_beta1,cal four scores for test\",\"image_score_beta\":-0.675325989723210,\"image_score_beta_desc\":\"image_score_beta_20170407_beta1,cal four scores for test\",\"image_score_delta\":-0.685437083244320,\"image_score_delta_desc\":\"image_score_delta_20170407_beta1,cal four scores for test\",\"image_score_desc\":\"image_score_20170407_beta1,cal four scores for test\",\"src\":\"http://t11.baidu.com/it/u=980303476,3546484602&fm=173&app=25&f=JPEG?w=218&h=146&s=4B02498A4D9007E95268259903008093\",\"width\":218}},{\"small_list\":{\"height\":146,\"image_score\":-0.415878176689150,\"image_score_alpha\":1.0,\"image_score_alpha_desc\":\"image_score_alpha_20170407_beta1,cal four scores for test\",\"image_score_beta\":-0.411192297935490,\"image_score_beta_desc\":\"image_score_beta_20170407_beta1,cal four scores for test\",\"image_score_delta\":-0.415878176689150,\"image_score_delta_desc\":\"image_score_delta_20170407_beta1,cal four scores for test\",\"image_score_desc\":\"image_score_20170407_beta1,cal four scores for test\",\"src\":\"http://t12.baidu.com/it/u=184648805,3595241792&fm=173&app=25&f=JPEG?w=218&h=146&s=832004A8449A17ED86E1808C03003003\",\"width\":218}},{\"small_list\":{\"height\":146,\"image_score\":3.38861942291260,\"image_score_alpha\":1.0,\"image_score_alpha_desc\":\"image_score_alpha_20170407_beta1,cal four scores for test\",\"image_score_beta\":3.39243745803830,\"image_score_beta_desc\":\"image_score_beta_20170407_beta1,cal four scores for test\",\"image_score_delta\":3.38861942291260,\"image_score_delta_desc\":\"image_score_delta_20170407_beta1,cal four scores for test\",\"image_score_desc\":\"image_score_20170407_beta1,cal four scores for test\",\"src\":\"http://t11.baidu.com/it/u=1379924773,2240087527&fm=173&app=25&f=JPEG?w=218&h=146&s=2EA3208C6C53BEDC5CA416830300E08F\",\"width\":218}}]","resource_status":"normal","importance_model_score":1.44922,"informative_score":0.2007753849029541,"news_attraction":0,"author_brand_info":{},"general_tag":{"体育_NBA球队动态":493},"news_clickbait_level":0,"news_sub_category":"NBA","img_urls_new":"","page_weight":35.04034263440866,"title_defect_level":0,"news_title_attraction_ext_info":{"loc":0,"basiclen":16,"d":0,"nr":6.0,"phraselen":16,"exclam":0,"m":0,"n":8.0,"comma":2.0,"r":4.0,"v":6.0,"w":6.0,"pj":0,"gbklen":58},"cluster_optimized":158152,"news_attentions_id":{"格林-->>德雷蒙德·格林":"1850q3","汤普森-->>克莱·汤普森":"1hcfc2","篮球":"1fgs_6","杜兰特":"10_stj","nba":"1td1cv","史蒂夫-->>勇士队教练":"1zyl8f"},"ctype":1,"similar_sign":"88343802 1027324291","category_tag":"","quality_package":5351000,"speed_push":0,"title_term":{"评价":34,"辱骂":34,"导火索":21,"格林":22,"如何":30,"球迷":21,"杜兰特":22,"王朝":21,"崩坏":21,"勇士":21},"pic_isdel":0,"cont_sign":"1954652596 1440097838","news_attention":{"格林-->>德雷蒙德·格林":595,"汤普森-->>克莱·汤普森":217,"篮球":209,"杜兰特":584,"nba":267,"史蒂夫-->>勇士队教练":215},"news_category_v1_prob":0.783928,"ptype":0,"pages_url":[],"duplicate_sign":"589597 1080522733","img_urls_num":4,"m_calc_time":"1542208977","audite":{"is_audit":0,"audit_info":""},"path_exinfo":"","cms_editor_news_category":"","score_topic_long_weibo":0.03714251292511028,"cluster_id":0,"nlpc_title_seg":["勇士","王朝","崩坏","导火索","格林","辱骂","杜兰特","看","美","球迷","如何","评价","他们"],"novelty_feed_time":1542208951,"intr_term":{"拆散":30,"导火索":51,"格林":129,"内讧":33,"勇士队":43,"球迷":107,"杜兰特":90,"王朝":53,"崩坏":56,"勇士":94},"vertical_level_bak":0,"m_image_urls":"{\"image_score_beta\": [{\"url\": \"http://t11.baidu.com/it/u=980303476,3546484602&fm=173&app=25&f=JPEG?w=218&h=146&s=4B02498A4D9007E95268259903008093\", \"image_score_beta\": -0.67532598972321, \"height\": 146, \"width\": 218}, {\"url\": \"http://t12.baidu.com/it/u=184648805,3595241792&fm=173&app=25&f=JPEG?w=218&h=146&s=832004A8449A17ED86E1808C03003003\", \"image_score_beta\": -0.41119229793549, \"height\": 146, \"width\": 218}, {\"url\": \"http://t11.baidu.com/it/u=1379924773,2240087527&fm=173&app=25&f=JPEG?w=218&h=146&s=2EA3208C6C53BEDC5CA416830300E08F\", \"image_score_beta\": 3.3924374580383, \"height\": 146, \"width\": 218}], \"author_img\": {\"original\": {\"url\": null, \"width\": null, \"height\": null}}, \"imgurls\": [{\"url\": \"http://t12.baidu.com/it/u=3111758387,809779261&fm=173&app=25&f=JPEG?w=218&h=146&s=29B0209CB68F0EEC3AA07586030080A0\", \"width\": 218, \"height\": 146}, {\"url\": \"http://t11.baidu.com/it/u=980303476,3546484602&fm=173&app=25&f=JPEG?w=218&h=146&s=4B02498A4D9007E95268259903008093\", \"width\": 218, \"height\": 146}, {\"url\": \"http://t12.baidu.com/it/u=184648805,3595241792&fm=173&app=25&f=JPEG?w=218&h=146&s=832004A8449A17ED86E1808C03003003\", \"width\": 218, \"height\": 146}, {\"url\": \"http://t11.baidu.com/it/u=1379924773,2240087527&fm=173&app=25&f=JPEG?w=218&h=146&s=2EA3208C6C53BEDC5CA416830300E08F\", \"width\": 218, \"height\": 146}], \"bimgurls\": null, \"gimgurls\": null}","dispatch_num":0,"vertical_type":0,"news_sub_category_v2":"NBA","soft_level":0,"news_sub_category_v1":"NBA","score_topic":46.76898263253025,"title_content_non_sim_level":0,"tj_news_timeliness_attention":[["格林-->>德雷蒙德·格林",595],["杜兰特",584],["nba",267],["汤普森-->>克莱·汤普森",217],["史蒂夫-->>勇士队教练",215]],"new_locname":[{}],"author_health_rank":-1,"penetration":0,"news_attraction_model":0,"click_estimate_score":2.979458706166075,"gd_brand_info":{"sentiment":2,"subject":"勇士,王朝,导火索,格林,杜兰特,美,球迷"},"gram_check_score":0,"news_location_level":"2","long_summary":"格林和杜兰特的口角逐渐发酵，最终在科尔的铁腕下，勇士队内禁赛格林参赛一场宣告终结；可美球迷如何评价勇士内讧？“你（杜兰特）马上就要进入自由市场了，你个小婊砸！”这句话成为了勇士内讧的根源之一！历来“场上鲁莽，场下人精”的格林竟说出这种小白文，令人难以置信！连一向在更衣室沉默寡言的汤普森都站出来，开口强调了团队的重要性，可见这件事在勇士队内影响有多大！美球迷调侃道：没想到西部弱旅快船，不显山不露水，竟然干出了如此惊天动地的大事——他们竟然成为一支王朝球队崩坏的导火索！不少球迷想出了多种拆散勇士王朝的点子，其中一个深得我心！但仍然有不少美球迷表示：拆散他们就能瓦解勇士，这个想法太乐观！","pctr_1":0.03617648444668072,"author_type":-1,"discomfort_level":0,"ecnet_level":0,"m_content_sign":"6185173119204958644","locname":[{}],"m_ext_type":"8","category":3,"news_category":"体育","news_category_mul_v2":{"体育":0.9999918},"porn_level":0}],"error":"success","status":{"16736811619630306176":0}}