{"errno":0,"data":[{"new_title_basic_seg_list":["格林","：","你","来","之","前","勇士","就","夺冠","了","！","杜兰特","：","这","就","是","我","要","离开","的","理由","？"],"quality_grade":2,"is_high_quality_res":0,"nid":"9420830529692060020","prior_antispam_tag":{"old_news":{"level":"Middle"}},"type_setting_basic_feature":{"valid_image_media_type_number":1,"is_good_clarity":true,"valid_bjh_type_number":0,"text_para_density":false,"valid_image_media_number":0,"heading_rich":true,"valid_customer_subtitle_number":0,"is_through_the_subtitle":false,"valid_bjh_number":0,"valid_customer_subtitle_type_number":0,"text_image_inter_good":0,"is_clarity":true,"rich_media_types":false},"novelty_sim_docs":[["7876865519557377016","7876865519557377016",0.984159574382961,1542206193]],"content_brief_rewrite":1,"nlpc_title_ner":["来之","离开的理由"],"news_clickbait_score":0.00348203,"news_category_prob":0.721982,"click_estimate_level":0,"novelty_rtg_time":1542206202,"rule_quality_reason":1000,"image_sign":"[{\"image_id\":\"0FBFB3C1_706A79A0\",\"sign\":\"AF387986D63315AFD67589370300D0C3\"},{\"image_id\":\"17CA2BCA_810EB56D\",\"sign\":\"60948D7354A26FBFBA9484CF0300E030\"},{\"image_id\":\"F108AD6F_8BA2D07A\",\"sign\":\"4A6DA1445D1205D0865C79940300C09A\"},{\"image_id\":\"D8066339_3B8980BE\",\"sign\":\"0C724A8748728FD65ED120890300C081\"}]\n","url_type":0,"news_title_attraction_level":1,"res_title_sign":"2804939461 4119578056","time_dis":[],"author_authority_score_v1_from":{"group_key_level":2},"title_pure":"格林：你来之前勇士就夺冠了！杜兰特：这就是我要离开的理由？","news_category_v2":"体育","news_category_v1":"体育","plsa3000":{"2965":769,"430":328,"1776":1009,"2799":459,"2169":426,"412":385,"1596":329,"2883":563,"2486":659,"616":328},"high_quality_repo":{"rewrite_times":1,"is_platform_high_quality":0,"is_push":"0","timeliness":52604,"is_topic_data":0,"push_source":"-1","quality_score":{"final_score":2,"after_score":2,"prev_score":2},"is_hqv2_data":1,"is_listen_data":0,"is_tup2_data":0,"is_group_data":0,"is_explore_data":0},"low_matching_score":0.3774942154082818,"display_url":"http://baijiahao.baidu.com/s?id=1617161057838710995","feature_mapping":{"http://t12.baidu.com/it/u=2025074930,2273287304&fm=173&app=25&f=JPEG?w=218&h=146&s=4A21B1445C4206D8165C79940300C09A":{"original_src":"http://timg01.bdimg.com/timg?pacompress&imgtype=1&sec=1439619614&autorotate=1&di=8380aa912dfea69ac0a09deafa1a4f80&quality=100&size=b640_10053&cut_x=0&cut_y=0&cut_w=640&cut_h=427&src=http%3A%2F%2Fpic.rmb.bdstatic.com%2F9fd62844c2777a7d0683bf7c7f94f7a06850.jpeg","feature_970_topn":[{"val":0.80426877737045,"cid":201},{"val":0.068790748715401,"cid":196},{"val":0.048388984054327,"cid":213},{"val":0.019802460446954,"cid":216},{"val":0.011300397105515,"cid":212}]},"http://t10.baidu.com/it/u=3792295749,2026686372&fm=173&app=25&f=JPEG?w=218&h=146&s=0C604A860A328EDE5ED124890300C001":{"original_src":"http://timg01.bdimg.com/timg?pacompress&imgtype=0&sec=1439619614&autorotate=1&di=beea54138af5c653b8e6a809fcda36b0&quality=100&size=b626_10012&cut_x=0&cut_y=0&cut_w=626&cut_h=448&src=http%3A%2F%2Fpic.rmb.bdstatic.com%2F39b9d6089c28c9c57ef65abbd1d2e7ec2126.png","feature_970_topn":[{"val":0.51182115077972,"cid":201},{"val":0.38987016677856,"cid":196},{"val":0.064134918153286,"cid":212},{"val":0.016204392537475,"cid":213},{"val":0.0035316618159413,"cid":180}]},"http://t10.baidu.com/it/u=1824154230,145598036&fm=173&app=25&f=JPEG?w=218&h=146&s=E4948D739EB26FBF2A8884CE03007030":{"original_src":"http://timg01.bdimg.com/timg?pacompress&imgtype=0&sec=1439619614&autorotate=1&di=8c0d5b6cb5bd15c57dcae94d013bcaf8&quality=100&size=b435_10065&cut_x=0&cut_y=0&cut_w=435&cut_h=365&src=http%3A%2F%2Fpic.rmb.bdstatic.com%2F0e21fc47a7ba4cb82e597ac22610ab623590.png","feature_970_topn":[{"val":0.86624646186829,"cid":201},{"val":0.09207608550787,"cid":196},{"val":0.028564509004354,"cid":212},{"val":0.005481060128659,"cid":213},{"val":0.001208167639561,"cid":218}]},"http://t11.baidu.com/it/u=3785180524,3611444518&fm=173&app=25&f=JPEG?w=218&h=146&s=EF7A31C6D73305AFD67409170300D0C0":{"original_src":"http://timg01.bdimg.com/timg?pacompress&imgtype=0&sec=1439619614&autorotate=1&di=7ec369ae484e3cd685ddf39aeafe603e&quality=100&size=b566_10014&cut_x=0&cut_y=0&cut_w=566&cut_h=359&src=http%3A%2F%2Fpic.rmb.bdstatic.com%2Fe6cb02a7f5a2311ad715fdb1483d580a2329.png","feature_970_topn":[{"val":0.44424599409103,"cid":201},{"val":0.19307297468185,"cid":196},{"val":0.12138571590185,"cid":212},{"val":0.047825615853071,"cid":159},{"val":0.021666590124369,"cid":180}]}},"m_public_time":"1542244996","media_subCategory_id":0,"readable_level":2,"conserve_type":3,"mthid":"1579750318596649","recommend":0,"meta_keywords":"","novelty_feed_all_sim":0.984159574382961,"cont_xpath_type":"0","res_content_sign":"2804939461 4119578056","term":{"明年夏天":11,"尼克斯":8,"理由":15,"失误":11,"格林":172,"汤普森":10,"比赛":6,"杜兰特":177,"联盟":7,"勇士":49},"ad_recognition_reason":{"hot_flag":true,"ad_level":0,"pincou_flag":false,"matched_rule":"","white_rule":"","matched_dict_type":"","hot_msg":["杜兰特"],"white_dict_type":""},"url_level":0,"news_score":0.8480000000000001,"novelty_imgs_real_time":{"4B69B1445C4206D8165C79940300C09A":["7876865519557377016","4B69B1445C4206D8165C79940300C09A",0,1542206193],"E4948D739EF26FBF2A8884CE03007030":["7876865519557377016","E4948D739EF26FBF2A8884CE03007030",0,1542206193],"0C704A860A328ED65ED124890300C001":["7876865519557377016","0C704A860A328ED65ED124890300C001",0,1542206193],"AF7A7986D72305AFD67409170300D0C0":["7876865519557377016","AF7A7986D72305AFD67409170300D0C0",0,1542206193]},"plsa30":{"0":198,"1":4022,"12":152,"13":488,"2":1052,"26":594,"27":151,"28":171,"29":522,"10":157},"kg_resource_tag_index":{},"new_title_phrase_seg_list":["格林","：","你","来","之","前","勇士","就","夺冠","了","！","杜兰特","：","这就是我","要","离开","的","理由","？"],"innersource_id":"","news_style_ext_info":{},"sex_score":0.01551013721694907,"author_health_score":0.9487,"quality_score":{"final_score":2,"after_score":2,"prev_score":2},"news_style_gamma":[],"category_sign":1677721603,"tj_lda_square":194.221523009166,"porn_score":0.0179473,"plsa300":{"1":677,"47":379,"116":462,"138":379,"81":1498,"208":476,"130":763,"141":1367,"142":877,"43":376},"m_content_type":"1","tag_intr_term":{"曝光":0.0,"转载":0.0,"分量":1.0,"也谈":0.576185869915936,"打击":1.002878190409547,"格林和":0.1231352264968788,"前场":0.0,"汤普森":1.825567361557776,"延伸":0.0,"比赛":1.204955656754512,"合同到期":1.0,"洗刷":0.0,"勇士":6.964311215504833,"that":0.3185600024597038,"关键":0.0,"远远":0.0,"默默":0.0,"碧池":1.0,"带球":0.0,"致命":0.691816833627329,"联盟":1.298612312145082,"惊讶":0.0,"重回":0.0,"作者":0.1998584649011433,"二人":0.67041733196611,"该死":0.0,"湖人":1.0,"明年":0.0,"吵架":0.0,"罚款":0.0,"夺冠":0.5288117970470204,"功臣":1.0,"冤屈":0.7593776129541344,"marcus":0.08352227246667851,"有多重":1.0,"大腿":0.8284045985079178,"加盟":0.0,"体育":0.4394960348305206,"乐意":0.0,"罚金":1.0,"自言自语":0.0,"athletic":0.08883198399737621,"后果":0.4703550862266624,"记者":0.158507624855119,"卷入":0.0,"输掉":1.0,"离队":0.0,"离开的理由":2.995200628726042,"替补":0.0,"这件事":0.9935463769667912,"自语":0.0,"念头":0.7095452702757786,"失误":2.0,"格林":25.14522521803923,"诟病":1.0,"thompson":0.08516779492644165,"命中":0.0,"球迷":0.793828946546085,"队伍":0.907308667693392,"处罚":0.5738255099890118,"战火":1.0,"重建":0.0,"拿下":0.0,"尼克斯":1.44,"理由":1.427321387445655,"杜兰特":26.77529418922855,"the":0.03234128089497636,"指责":0.0,"冠军":0.7009080751276681,"明年夏天":2.0,"夏天":0.0,"球队":1.0,"禁赛":1.0,"百家":0.9842639954856952,"影响":0.3075712060452692,"说话":0.0,"证明":0.0,"致命失误":1.0,"雷霆":0.8856068908129885},"tag_title_term":{"理由":0.4588986517065289,"格林":1.753259315184744,"杜兰特":1.5,"离开的理由":1.0,"夺冠":0.0,"勇士":0.5933450835675922},"news_sub_category_mul_v2":{"篮球":0.418421,"NBA":0.912713},"news_sub_category_mul_v1":{"篮球":0.80194,"NBA":0.84663},"is_mjh":0,"img_ids":[5902450667618597518,7830417012879259159,10700997470374042559],"news_attentions_rewrite":{"格林-->>德雷蒙德·格林":"","勇士比赛":"","篮球":"","杜兰特":"","nba":"","杜兰特加盟勇士":""},"newsmans":[{"site":"","name":"光明热点","id":-1}],"author_health_ext_info":{"filter_ratio":0.0001,"article_num":62049,"ad_avg_score":0.016,"disgust_ratio":0.0467,"lowstyle_ratio":0.027,"sex_avg_score":0.05},"disgust_score":0.00901099351393978,"news_style_super_beta":[],"displaytype_exinfo":"{\"comment_thread_id\":\"1057000010018096\"}","quality_feature_level":2,"source_url":"http://baijiahao.baidu.com/u?id=1579750318596649","idset":[80001],"score_topic_short":0.04217440762857516,"novelty_rtg_sim":1.0,"is_modify":0,"score_quality":0.100011215887193,"smfw":{"quality_model_1003406":{"quality_score":{"final_score":2,"after_score":2,"prev_score":2}},"content_model_1008810":{"news_attentions_id":{"格林-->>德雷蒙德·格林":"1850q3","篮球":"1fgs_6","杜兰特":"10_stj","nba":"1td1cv","杜兰特加盟勇士":"129w7q"},"news_attention":{"格林-->>德雷蒙德·格林":558,"篮球":246,"杜兰特":548,"nba":257,"杜兰特加盟勇士":408},"news_hierarchy":[{"path":[["nba=>篮球=>球类运动=>体育项目=>体育",252]],"topic":"篮球"}],"news_short_hierarchy":[{"path":[["nba=>篮球",252]],"topic":"篮球"}],"news_attentions_rewrite":{"格林-->>德雷蒙德·格林":"","篮球":"","杜兰特":"","nba":"","杜兰特加盟勇士":""}},"1005989_1":{"vertical_level_bak":2,"author_authority_score_v1":2},"1009041_2":{"quality_emergent_flags":{"40030":"non_fr_brush_模板账号","51010":"common_weight","50010":"common_weight","70010":"common_weight","71010":"common_weight","60030":"fr_brush_模板账号","10006":"模板账号"}},"1009221_2":{"news_attention":{"格林-->>德雷蒙德·格林":527,"勇士比赛":113,"篮球":236,"杜兰特":880,"NBA":666,"nba":246,"勇士":749},"is_valid_attention":1},"content_model_1006454":{"news_attention":{"格林-->>德雷蒙德·格林":527,"勇士比赛":318,"篮球":236,"杜兰特":517,"nba":246,"杜兰特加盟勇士":388}},"1006739_0":{"news_style_super":[],"news_style_super_beta":[]},"1008133_1":{"timeliness":52604},"1006739_1":{"news_style_super":[],"news_style_super_beta":[]},"content_model_1000403":{"base_weight":55},"1008364_0":{"m_image_urls":"{\"image_score_beta\": [{\"url\": \"http://t10.baidu.com/it/u=1824154230,145598036&fm=173&app=25&f=JPEG?w=218&h=146&s=E4948D739EB26FBF2A8884CE03007030\", \"image_score_beta\": 2.9830319881439, \"height\": 146, \"width\": 218}, {\"url\": \"http://t12.baidu.com/it/u=2025074930,2273287304&fm=173&app=25&f=JPEG?w=218&h=146&s=4A21B1445C4206D8165C79940300C09A\", \"image_score_beta\": 3.1507835388184, \"height\": 146, \"width\": 218}, {\"url\": \"http://t10.baidu.com/it/u=3792295749,2026686372&fm=173&app=25&f=JPEG?w=218&h=146&s=0C604A860A328EDE5ED124890300C001\", \"image_score_beta\": 3.3567776679993, \"height\": 146, \"width\": 218}], \"author_img\": {\"original\": {\"url\": \"http://timg01.bdimg.com/timg?pa&Imgtype=0&sec=1439619614&di=0c44a0420ede1793c52d27b8f829cf19&quality=90&size=b870_10000&src=http%3A%2F%2Ftimg01.bdimg.com%2Ftimg%3Fpacompress%3D%26imgtype%3D0%26sec%3D1439619614%26autorotate%3D1%26di%3D6ba90d9414df1fafac5179bc6875b625%26quality%3D90%26size%3Db200_200%26src%3Dhttp%253A%252F%252Fpic.rmb.bdstatic.com%252Fba285fa96becc2d32b6467614c613096.png\", \"width\": 0, \"height\": 0}}, \"imgurls\": [{\"url\": \"http://t12.baidu.com/it/u=1374271388,330070670&fm=173&app=25&f=JPEG?w=218&h=146&s=AF3A6986DF3305AFD67409160300C0C0\", \"width\": 218, \"height\": 146}, {\"url\": \"http://t11.baidu.com/it/u=1823161033,802682391&fm=173&app=25&f=JPEG?w=218&h=146&s=C4B48D7396B26BBF228984CE03003030\", \"width\": 218, \"height\": 146}, {\"url\": \"http://t11.baidu.com/it/u=2491520128,3288308671&fm=173&app=25&f=JPEG?w=218&h=146&s=4A21B1445C0204D8165C79900300D09A\", \"width\": 218, \"height\": 146}], \"bimgurls\": null, \"gimgurls\": [{\"url\": \"http://t11.baidu.com/it/u=3892753285,3515264900&fm=173&app=25&f=JPEG?w=536&h=302&s=AF3A6986DF3305AFD67409160300C0C0\", \"width\": 536, \"height\": 302}, {\"url\": \"http://t12.baidu.com/it/u=3842881622,2420785904&fm=173&app=25&f=JPEG?w=435&h=245&s=C4B48D7396B26BBF228984CE03003030\", \"width\": 435, \"height\": 245}, {\"url\": \"http://t11.baidu.com/it/u=2520291361,2019214235&fm=173&app=25&f=JPEG?w=637&h=358&s=4A21B1445C0204D8165C79900300D09A\", \"width\": 637, \"height\": 358}]}"},"quality_model_1008133":{"timeliness":52604},"1004558_2":{"author_authority_score_v1":2},"1006454_1":{"news_attention":{"格林-->>德雷蒙德·格林":527,"勇士比赛":318,"篮球":236,"杜兰特":517,"nba":246,"杜兰特加盟勇士":388}},"1009249_2":{"news_location_level":"2"},"content_model_1006770":{"news_attentions_id":{"格林-->>德雷蒙德·格林":"1850q3","勇士比赛":"1lqxwk","篮球":"1fgs_6","杜兰特":"10_stj","nba":"1td1cv","杜兰特加盟勇士":"129w7q"},"news_attention":{"格林-->>德雷蒙德·格林":550,"勇士比赛":324,"篮球":198,"杜兰特":540,"nba":226,"杜兰特加盟勇士":381},"news_hierarchy":[{"path":[["nba=>篮球=>球类运动=>体育项目=>体育",229]],"topic":"篮球"}],"news_short_hierarchy":[{"path":[["nba=>篮球",229]],"topic":"篮球"}],"news_attentions_rewrite":{"格林-->>德雷蒙德·格林":"","勇士比赛":"","篮球":"","杜兰特":"","nba":"","杜兰特加盟勇士":""}},"1008810_2":{"news_attentions_id":{"格林-->>德雷蒙德·格林":"1850q3","篮球":"1fgs_6","杜兰特":"10_stj","nba":"1td1cv","杜兰特加盟勇士":"129w7q"},"news_attention":{"格林-->>德雷蒙德·格林":558,"篮球":246,"杜兰特":548,"nba":257,"杜兰特加盟勇士":408},"news_hierarchy":[{"path":[["nba=>篮球=>球类运动=>体育项目=>体育",252]],"topic":"篮球"}],"news_short_hierarchy":[{"path":[["nba=>篮球",252]],"topic":"篮球"}],"news_attentions_rewrite":{"格林-->>德雷蒙德·格林":"","篮球":"","杜兰特":"","nba":"","杜兰特加盟勇士":""}},"1003406_1":{"quality_score":{"final_score":2,"after_score":2,"prev_score":2}},"1006770_2":{"news_attentions_id":{"格林-->>德雷蒙德·格林":"1850q3","勇士比赛":"1lqxwk","篮球":"1fgs_6","杜兰特":"10_stj","nba":"1td1cv","杜兰特加盟勇士":"129w7q"},"news_attention":{"格林-->>德雷蒙德·格林":550,"勇士比赛":324,"篮球":198,"杜兰特":540,"nba":226,"杜兰特加盟勇士":381},"news_hierarchy":[{"path":[["nba=>篮球=>球类运动=>体育项目=>体育",229]],"topic":"篮球"}],"news_short_hierarchy":[{"path":[["nba=>篮球",229]],"topic":"篮球"}],"news_attentions_rewrite":{"格林-->>德雷蒙德·格林":"","勇士比赛":"","篮球":"","杜兰特":"","nba":"","杜兰特加盟勇士":""}},"quality_model_1004558":{"author_authority_score_v1":2},"1006770_1":{"news_attentions_id":{"格林-->>德雷蒙德·格林":"1850q3","勇士比赛":"1lqxwk","篮球":"1fgs_6","杜兰特":"10_stj","nba":"1td1cv","杜兰特加盟勇士":"129w7q"},"news_attention":{"格林-->>德雷蒙德·格林":550,"勇士比赛":324,"篮球":198,"杜兰特":540,"nba":226,"杜兰特加盟勇士":381},"news_hierarchy":[{"path":[["nba=>篮球=>球类运动=>体育项目=>体育",229]],"topic":"篮球"}],"news_short_hierarchy":[{"path":[["nba=>篮球",229]],"topic":"篮球"}],"news_attentions_rewrite":{"格林-->>德雷蒙德·格林":"","勇士比赛":"","篮球":"","杜兰特":"","nba":"","杜兰特加盟勇士":""}}},"novelty_paras_real_time":{"1":["7876865519557377016",0,1.0,1542206193],"2":["7876865519557377016",1,1.0,1542206193],"3":["7876865519557377016",2,0.986842105263158,1542206193],"5":["7876865519557377016",4,0.9850746268656716,1542206193],"7":["7876865519557377016",6,1.0,1542206193],"8":["7876865519557377016",7,1.0,1542206193]},"m_related_sign":"13205602821129020100","recommend_to_bs":1,"sndc_send_time":1542244999,"stype":2,"url_sign":9420830529692060020,"old_news_level":3,"m_site":"光明热点","weight":5,"entity_importance":11.89345688666651,"hit_conf_cont_xpath":"0","site_name":"光明热点","tags_author":[],"m_isvideo":"0","m_title":"格林：你来之前勇士就夺冠了！杜兰特：这就是我要离开的理由？","m_url":"http://baijiahao.baidu.com/s?id=1617161057838710995","operator_time":{"al2_nlpc_output_time":1542245000.761057,"content_vertical_input_time":1542245004.402398,"content_combian_input_time":1542245009.009249,"sndc_send_time":1542244999,"content_mining_input_time":1542245000.801862,"content_combian_output_time":1542245009.112409,"content_task_input_time":1542245002.626174,"data_analyzer_input_time":1542245005.00767,"content_cmnlpc_output_time":1542245009.157169,"content_class_input_time":1542245002.415431,"content_quality_output_time":1542245008.252585,"content_task_output_time":1542245004.344479,"content_cmnlpc_input_time":1542245009.149851,"content_mining_output_time":1542245001.398846,"part1_importer_output_time":1542245000.051712,"al2_nlpc_input_time":1542245000.679191,"content_quality_input_time":1542245005.136485,"content_rcmc_agent_input_time":1542245009.194103,"content_vertical_output_time":1542245004.938076,"part1_importer_input_time":1542245000.050228,"data_analyzer_output_time":1542245005.081702,"content_class_output_time":1542245002.57762},"sn_procesor_quality_reason":0,"low_quality_all_matched":{"filter":[{"rule_id":"rule_filter2","reason":"OLD_NEWS_RECOG","priority":13,"order":2}],"set_flag":[{"rule_id":"rule_setflag5","reason":"","priority":1,"order":1},{"rule_id":"rule_template_mthid","reason":"","priority":1,"order":1}],"white":[{"rule_id":"rule_white3","reason":"CMS_MTHID_WHITE","priority":15,"order":1}]},"news_title_attraction_score":2.58286,"news_sub_category_v1_prob":0.84663,"unique_class":{"second_class_weight":0.866,"second_class_name":"体育活动","first_class_weight":1.0,"first_class_name":"活动与事件"},"merge_locname":{"province":"","town":"","city":"","district":"","circle":""},"content_quality":{"disgust_level":0,"gj_quality":-1,"title_attentions":{"杜兰特":517},"news_attraction":0,"news_sub_category_prob":0.760945,"copy_time":1542206193,"news_category_prob":0.721982,"copy_level":3,"high_timeliness":0},"first_content":"","m_json_text":"{\"content\":[{\"data\":\"转载自百家号作者：子午体育\",\"data_rtf\":\"<span class=\\\"bjh-blockquote\\\"><span class=\\\"bjh-p\\\">转载自百家号作者：子午体育</span></span>\",\"type\":\"text\"},{\"data\":\"[子午11月14日讯]杜兰特因为格林在比赛最后时间出现致命失误而指责格林，他表示“你应该把那该死的球给我！”格林随后便在替补席跟杜兰特对喷了起来，而据说二人的战火一直延伸到更衣室，而且越吵越凶，这次吵架的程度已经远远超过了平时，甚至卷入了明年夏天两人离队的问题，也谈及了杜兰特加盟勇士的问题。\",\"data_rtf\":\"<span class=\\\"bjh-p\\\">[子午11月14日讯]杜兰特因为格林在比赛最后时间出现致命失误而指责格林，他表示“你应该把那该死的球给我！”格林随后便在替补席跟杜兰特对喷了起来，而据说二人的战火一直延伸到更衣室，而且越吵越凶，这次吵架的程度已经远远超过了平时，甚至卷入了明年夏天两人离队的问题，也谈及了杜兰特加盟勇士的问题。</span>\",\"type\":\"text\"},{\"data\":{\"big\":{\"height\":359,\"url\":\"http://t11.baidu.com/it/u=3730347925,3925162013&fm=173&app=49&f=JPEG?w=566&h=359&s=AF7A7986D72305AFD67409170300D0C0\",\"width\":566},\"caption\":\"\",\"cont_small\":{\"height\":203,\"src\":\"http://t12.baidu.com/it/u=3459066362,4205026556&fm=173&app=25&f=JPEG?w=320&h=203&s=EF7A31C6D73305AFD67409170300D0C0\",\"width\":320},\"original\":{\"feature_json_format\":\"{\\\"aesthetic\\\":1.0979804992676,\\\"antiporn_normal\\\":0.994943,\\\"antiporn_porn\\\":0.002138,\\\"antiporn_sexy\\\":0.002919,\\\"array\\\":[],\\\"clarity\\\":1.8325614929199,\\\"contsign\\\":\\\"1631796782,306821668\\\",\\\"disgust\\\":0.0033482315484434,\\\"feature_970_topn\\\":[{\\\"cid\\\":201,\\\"val\\\":0.44424599409103},{\\\"cid\\\":196,\\\"val\\\":0.19307297468185},{\\\"cid\\\":212,\\\"val\\\":0.12138571590185},{\\\"cid\\\":159,\\\"val\\\":0.047825615853071},{\\\"cid\\\":180,\\\"val\\\":0.021666590124369}],\\\"feature_sexy_lady\\\":0.0021154419519007,\\\"main_area\\\":{\\\"height\\\":363,\\\"left\\\":22,\\\"top\\\":4,\\\"width\\\":530},\\\"porn_prob\\\":0.002138,\\\"same_feature_with_hash\\\":\\\"{\\\\\\\"same_feature_hash_id\\\\\\\":178982,\\\\\\\"same_feature_hash_ids\\\\\\\":[178982,178727,46886,46631,178978,46882,138534,138279,138530]}\\\"}\",\"height\":359,\"image_format\":\"JPEG\",\"low_quality_type\":0,\"url\":\"http://timg01.bdimg.com/timg?pacompress&imgtype=0&sec=1439619614&autorotate=1&di=7ec369ae484e3cd685ddf39aeafe603e&quality=100&size=b566_10014&cut_x=0&cut_y=0&cut_w=566&cut_h=359&src=http%3A%2F%2Fpic.rmb.bdstatic.com%2Fe6cb02a7f5a2311ad715fdb1483d580a2329.png\",\"width\":566},\"original_third\":{\"feature_json_format\":\"{\\\"aesthetic\\\":1.0979804992676,\\\"antiporn_normal\\\":0.994943,\\\"antiporn_porn\\\":0.002138,\\\"antiporn_sexy\\\":0.002919,\\\"array\\\":[],\\\"clarity\\\":1.8325614929199,\\\"contsign\\\":\\\"1631796782,306821668\\\",\\\"disgust\\\":0.0033482315484434,\\\"feature_970_topn\\\":[{\\\"cid\\\":201,\\\"val\\\":0.44424599409103},{\\\"cid\\\":196,\\\"val\\\":0.19307297468185},{\\\"cid\\\":212,\\\"val\\\":0.12138571590185},{\\\"cid\\\":159,\\\"val\\\":0.047825615853071},{\\\"cid\\\":180,\\\"val\\\":0.021666590124369}],\\\"feature_sexy_lady\\\":0.0021154419519007,\\\"main_area\\\":{\\\"height\\\":363,\\\"left\\\":22,\\\"top\\\":4,\\\"width\\\":530},\\\"porn_prob\\\":0.002138,\\\"same_feature_with_hash\\\":\\\"{\\\\\\\"same_feature_hash_id\\\\\\\":178982,\\\\\\\"same_feature_hash_ids\\\\\\\":[178982,178727,46886,46631,178978,46882,138534,138279,138530]}\\\"}\",\"height\":359,\"image_format\":\"JPEG\",\"low_quality_type\":0,\"url\":\"http://timg01.bdimg.com/timg?pacompress&imgtype=0&sec=1439619614&autorotate=1&di=7ec369ae484e3cd685ddf39aeafe603e&quality=100&size=b566_10014&cut_x=0&cut_y=0&cut_w=566&cut_h=359&src=http%3A%2F%2Fpic.rmb.bdstatic.com%2Fe6cb02a7f5a2311ad715fdb1483d580a2329.png\",\"width\":566},\"small\":{\"height\":359,\"url\":\"http://t12.baidu.com/it/u=2621399549,1137609421&fm=173&app=25&f=JPEG?w=480&h=359&s=EF7A31C6D73305AFD67409170300D0C0\",\"width\":480}},\"type\":\"image\"},{\"data\":\"The Athletic的记者Marcus Thompson曝光了格林和杜兰特对喷的细节：\",\"data_rtf\":\"<span class=\\\"bjh-p\\\">The Athletic的记者Marcus Thompson曝光了格林和杜兰特对喷的细节：</span>\",\"type\":\"text\"},{\"data\":\"格林表示：勇士在杜兰特到来之前就是总冠军了对于格林在最后关头出现的失误，其实不仅仅杜兰特表示不爽，就连汤普森都觉得格林那样的失误太不应该了。一般勇士在最后时刻都会把球交给杜兰特，但是这次格林并没有把球给旁边的杜兰特，而是选择自己带球到前场，却出现了失误，最终导致输掉了比赛！杜兰特指责格林应该把球传给自己，但是格林却不乐意了，说：“你XX以为你在跟谁说话，别忘记了在你来之前勇士就拿到冠军了！”这一句话的分量想必每个人都知道有多重。杜兰特加盟勇士就是为了能够证明自己，拿到总冠军。而他更是勇士两连冠的夺冠功臣，但是即便如此还是被很多球迷这样诟病，觉得杜兰特是去抱大腿！别人这样说尚可原谅，但是作为勇士的一员，格林都如此说，那么对杜兰特打击相当大了。\",\"data_rtf\":\"<span class=\\\"bjh-ol\\\"><span class=\\\"bjh-li\\\"><span class=\\\"bjh-p\\\">格林表示：勇士在杜兰特到来之前就是总冠军了</span></span></span><span class=\\\"bjh-p\\\">对于格林在最后关头出现的失误，其实不仅仅杜兰特表示不爽，就连汤普森都觉得格林那样的失误太不应该了。一般勇士在最后时刻都会把球交给杜兰特，但是这次格林并没有把球给旁边的杜兰特，而是选择自己带球到前场，却出现了失误，最终导致输掉了比赛！杜兰特指责格林应该把球传给自己，但是格林却不乐意了，说：“你XX以为你在跟谁说话，别忘记了在你来之前勇士就拿到冠军了！”这一句话的分量想必每个人都知道有多重。杜兰特加盟勇士就是为了能够证明自己，拿到总冠军。而他更是勇士两连冠的夺冠功臣，但是即便如此还是被很多球迷这样诟病，觉得杜兰特是去抱大腿！别人这样说尚可原谅，但是作为勇士的一员，格林都如此说，那么对杜兰特打击相当大了。</span>\",\"type\":\"text\"},{\"data\":{\"big\":{\"height\":365,\"url\":\"http://t11.baidu.com/it/u=2336682787,1365582304&fm=173&app=49&f=JPEG?w=435&h=365&s=E4948D739EF26FBF2A8884CE03007030\",\"width\":435},\"caption\":\"\",\"cont_small\":{\"height\":269,\"src\":\"http://t10.baidu.com/it/u=4255944852,3566055385&fm=173&app=25&f=JPEG?w=320&h=269&s=E4948D739EB26FBF2A8884CE03007030\",\"width\":320},\"original\":{\"feature_json_format\":\"{\\\"aesthetic\\\":2.0405900478363,\\\"antiporn_normal\\\":0.994679,\\\"antiporn_porn\\\":0.001185,\\\"antiporn_sexy\\\":0.004136,\\\"array\\\":[{\\\"locheight\\\":26,\\\"locleft\\\":245,\\\"loctop\\\":179,\\\"locwidth\\\":43,\\\"ocrresult\\\":\\\"23\\\"},{\\\"locheight\\\":16,\\\"locleft\\\":224,\\\"loctop\\\":240,\\\"locwidth\\\":69,\\\"ocrresult\\\":\\\" APPIOT\\\"}],\\\"clarity\\\":3.1381440162659,\\\"contsign\\\":\\\"1791461325,1597834450\\\",\\\"disgust\\\":0.00037124933442101,\\\"feature_970_topn\\\":[{\\\"cid\\\":201,\\\"val\\\":0.86624646186829},{\\\"cid\\\":196,\\\"val\\\":0.09207608550787},{\\\"cid\\\":212,\\\"val\\\":0.028564509004354},{\\\"cid\\\":213,\\\"val\\\":0.005481060128659},{\\\"cid\\\":218,\\\"val\\\":0.001208167639561}],\\\"feature_sexy_lady\\\":0.00016277871327475,\\\"main_area\\\":{\\\"height\\\":373,\\\"left\\\":16,\\\"top\\\":1,\\\"width\\\":416},\\\"porn_prob\\\":0.001185,\\\"same_feature_with_hash\\\":\\\"{\\\\\\\"same_feature_hash_id\\\\\\\":46656,\\\\\\\"same_feature_hash_ids\\\\\\\":[46656,46688,178752,178784,46915,179011,164928,164960,165187]}\\\"}\",\"height\":365,\"image_format\":\"JPEG\",\"low_quality_type\":32,\"url\":\"http://timg01.bdimg.com/timg?pacompress&imgtype=0&sec=1439619614&autorotate=1&di=8c0d5b6cb5bd15c57dcae94d013bcaf8&quality=100&size=b435_10065&cut_x=0&cut_y=0&cut_w=435&cut_h=365&src=http%3A%2F%2Fpic.rmb.bdstatic.com%2F0e21fc47a7ba4cb82e597ac22610ab623590.png\",\"width\":435},\"original_third\":{\"feature_json_format\":\"{\\\"aesthetic\\\":2.0405900478363,\\\"antiporn_normal\\\":0.994679,\\\"antiporn_porn\\\":0.001185,\\\"antiporn_sexy\\\":0.004136,\\\"array\\\":[{\\\"locheight\\\":26,\\\"locleft\\\":245,\\\"loctop\\\":179,\\\"locwidth\\\":43,\\\"ocrresult\\\":\\\"23\\\"},{\\\"locheight\\\":16,\\\"locleft\\\":224,\\\"loctop\\\":240,\\\"locwidth\\\":69,\\\"ocrresult\\\":\\\" APPIOT\\\"}],\\\"clarity\\\":3.1381440162659,\\\"contsign\\\":\\\"1791461325,1597834450\\\",\\\"disgust\\\":0.00037124933442101,\\\"feature_970_topn\\\":[{\\\"cid\\\":201,\\\"val\\\":0.86624646186829},{\\\"cid\\\":196,\\\"val\\\":0.09207608550787},{\\\"cid\\\":212,\\\"val\\\":0.028564509004354},{\\\"cid\\\":213,\\\"val\\\":0.005481060128659},{\\\"cid\\\":218,\\\"val\\\":0.001208167639561}],\\\"feature_sexy_lady\\\":0.00016277871327475,\\\"main_area\\\":{\\\"height\\\":373,\\\"left\\\":16,\\\"top\\\":1,\\\"width\\\":416},\\\"porn_prob\\\":0.001185,\\\"same_feature_with_hash\\\":\\\"{\\\\\\\"same_feature_hash_id\\\\\\\":46656,\\\\\\\"same_feature_hash_ids\\\\\\\":[46656,46688,178752,178784,46915,179011,164928,164960,165187]}\\\"}\",\"height\":365,\"image_format\":\"JPEG\",\"low_quality_type\":32,\"url\":\"http://timg01.bdimg.com/timg?pacompress&imgtype=0&sec=1439619614&autorotate=1&di=8c0d5b6cb5bd15c57dcae94d013bcaf8&quality=100&size=b435_10065&cut_x=0&cut_y=0&cut_w=435&cut_h=365&src=http%3A%2F%2Fpic.rmb.bdstatic.com%2F0e21fc47a7ba4cb82e597ac22610ab623590.png\",\"width\":435},\"small\":{\"height\":360,\"url\":\"http://t11.baidu.com/it/u=2386893502,2885342073&fm=173&app=25&f=JPEG?w=435&h=360&s=E4948D739EB26FBF2A8884CE03007030\",\"width\":435}},\"type\":\"image\"},{\"data\":\"2.杜兰特自语：这就是我要离开的理由？\",\"data_rtf\":\"<span class=\\\"bjh-p\\\">2.杜兰特自语：这就是我要离开的理由？</span>\",\"type\":\"text\"},{\"data\":\"在格林说出如此重的话之后，杜兰特并没有回喷，而是默默的自言自语了一句：“That's why i'm out？”（这就是我要离开的理由？）格林还骂杜兰特是“碧池！”尤其在讲出那样的话之后，杜兰特似乎受到了很大的打击。并且从这句话之中听出了杜兰特想要离开勇士的念头。明年夏天杜兰特的合同到期，如果他真的想要用另一种方式证明自己的话，估计真的会离开勇士。至于去哪里？不管是去湖人还是重回雷霆，杜兰特将会重新洗刷冤屈。但是选择一个重建中的队伍也不失为一种很好的选择，比如尼克斯！\",\"data_rtf\":\"<span class=\\\"bjh-p\\\">在格林说出如此重的话之后，杜兰特并没有回喷，而是默默的自言自语了一句：“That's why i'm out？”（这就是我要离开的理由？）格林还骂杜兰特是“碧池！”尤其在讲出那样的话之后，杜兰特似乎受到了很大的打击。并且从这句话之中听出了杜兰特想要离开勇士的念头。明年夏天杜兰特的合同到期，如果他真的想要用另一种方式证明自己的话，估计真的会离开勇士。至于去哪里？不管是去湖人还是重回雷霆，杜兰特将会重新洗刷冤屈。但是选择一个重建中的队伍也不失为一种很好的选择，比如尼克斯！</span>\",\"type\":\"text\"},{\"data\":{\"big\":{\"height\":427,\"url\":\"http://t10.baidu.com/it/u=519875952,4225550768&fm=173&app=49&f=JPEG?w=640&h=427&s=4B69B1445C4206D8165C79940300C09A\",\"width\":640},\"caption\":\"\",\"cont_small\":{\"height\":214,\"src\":\"http://t12.baidu.com/it/u=746204942,3835062793&fm=173&app=25&f=JPEG?w=320&h=214&s=4A21B1445C4206D8165C79940300C09A\",\"width\":320},\"original\":{\"feature_json_format\":\"{\\\"aesthetic\\\":2.0789813995361,\\\"antiporn_normal\\\":0.998373,\\\"antiporn_porn\\\":0.000346,\\\"antiporn_sexy\\\":0.001281,\\\"array\\\":[],\\\"clarity\\\":2.4928302764893,\\\"contsign\\\":\\\"1070423808,3784296485\\\",\\\"disgust\\\":2.3277963919099e-5,\\\"feature_970_topn\\\":[{\\\"cid\\\":201,\\\"val\\\":0.80426877737045},{\\\"cid\\\":196,\\\"val\\\":0.068790748715401},{\\\"cid\\\":213,\\\"val\\\":0.048388984054327},{\\\"cid\\\":216,\\\"val\\\":0.019802460446954},{\\\"cid\\\":212,\\\"val\\\":0.011300397105515}],\\\"feature_sexy_lady\\\":0.0017468249425292,\\\"main_area\\\":{\\\"height\\\":431,\\\"left\\\":185,\\\"top\\\":8,\\\"width\\\":440},\\\"porn_prob\\\":0.000346,\\\"same_feature_with_hash\\\":\\\"{\\\\\\\"same_feature_hash_id\\\\\\\":178982,\\\\\\\"same_feature_hash_ids\\\\\\\":[178982,179139,46886,47043,179137,47041,138534,138691,138689]}\\\"}\",\"height\":427,\"image_format\":\"JPEG\",\"low_quality_type\":0,\"url\":\"http://timg01.bdimg.com/timg?pacompress&imgtype=1&sec=1439619614&autorotate=1&di=8380aa912dfea69ac0a09deafa1a4f80&quality=100&size=b640_10053&cut_x=0&cut_y=0&cut_w=640&cut_h=427&src=http%3A%2F%2Fpic.rmb.bdstatic.com%2F9fd62844c2777a7d0683bf7c7f94f7a06850.jpeg\",\"width\":640},\"original_third\":{\"feature_json_format\":\"{\\\"aesthetic\\\":2.0789813995361,\\\"antiporn_normal\\\":0.998373,\\\"antiporn_porn\\\":0.000346,\\\"antiporn_sexy\\\":0.001281,\\\"array\\\":[],\\\"clarity\\\":2.4928302764893,\\\"contsign\\\":\\\"1070423808,3784296485\\\",\\\"disgust\\\":2.3277963919099e-5,\\\"feature_970_topn\\\":[{\\\"cid\\\":201,\\\"val\\\":0.80426877737045},{\\\"cid\\\":196,\\\"val\\\":0.068790748715401},{\\\"cid\\\":213,\\\"val\\\":0.048388984054327},{\\\"cid\\\":216,\\\"val\\\":0.019802460446954},{\\\"cid\\\":212,\\\"val\\\":0.011300397105515}],\\\"feature_sexy_lady\\\":0.0017468249425292,\\\"main_area\\\":{\\\"height\\\":431,\\\"left\\\":185,\\\"top\\\":8,\\\"width\\\":440},\\\"porn_prob\\\":0.000346,\\\"same_feature_with_hash\\\":\\\"{\\\\\\\"same_feature_hash_id\\\\\\\":178982,\\\\\\\"same_feature_hash_ids\\\\\\\":[178982,179139,46886,47043,179137,47041,138534,138691,138689]}\\\"}\",\"height\":427,\"image_format\":\"JPEG\",\"low_quality_type\":0,\"url\":\"http://timg01.bdimg.com/timg?pacompress&imgtype=1&sec=1439619614&autorotate=1&di=8380aa912dfea69ac0a09deafa1a4f80&quality=100&size=b640_10053&cut_x=0&cut_y=0&cut_w=640&cut_h=427&src=http%3A%2F%2Fpic.rmb.bdstatic.com%2F9fd62844c2777a7d0683bf7c7f94f7a06850.jpeg\",\"width\":640},\"small\":{\"height\":360,\"url\":\"http://t11.baidu.com/it/u=3832600702,3996788134&fm=173&app=25&f=JPEG?w=480&h=360&s=4A21B1445C4206D8165C79940300C09A\",\"width\":480}},\"type\":\"image\"},{\"data\":\"3.格林被重罚\",\"data_rtf\":\"<span class=\\\"bjh-p\\\">3.格林被重罚</span>\",\"type\":\"text\"},{\"data\":\"格林对于联盟禁赛并且罚款的处罚表示非常的惊讶，他没有想到自己的言论居然会上升到让联盟禁赛的处理，并且罚金也相当高，或许这不是这些处罚的问题，而是球队在这件事情上面的选择吧。在格林禁赛之后杜兰特带队还是拿下了今天的比赛，并且命中了关键球，看起来KD的心态似乎没有受到太大的影响！\",\"data_rtf\":\"<span class=\\\"bjh-p\\\">格林对于联盟禁赛并且罚款的处罚表示非常的惊讶，他没有想到自己的言论居然会上升到让联盟禁赛的处理，并且罚金也相当高，或许这不是这些处罚的问题，而是球队在这件事情上面的选择吧。在格林禁赛之后杜兰特带队还是拿下了今天的比赛，并且命中了关键球，看起来KD的心态似乎没有受到太大的影响！</span>\",\"type\":\"text\"},{\"data\":{\"big\":{\"height\":448,\"url\":\"http://t10.baidu.com/it/u=335444118,89395724&fm=173&app=49&f=JPEG?w=626&h=448&s=0C704A860A328ED65ED124890300C001\",\"width\":626},\"caption\":\"\",\"cont_small\":{\"height\":229,\"src\":\"http://t11.baidu.com/it/u=39676351,3458292294&fm=173&app=25&f=JPEG?w=320&h=229&s=0C604A860A328EDE5ED124890300C001\",\"width\":320},\"original\":{\"feature_json_format\":\"{\\\"aesthetic\\\":2.8862612247467,\\\"antiporn_normal\\\":0.998425,\\\"antiporn_porn\\\":0.000345,\\\"antiporn_sexy\\\":0.001231,\\\"array\\\":[{\\\"locheight\\\":28,\\\"locleft\\\":567,\\\"loctop\\\":145,\\\"locwidth\\\":55,\\\"ocrresult\\\":\\\"E\\\"},{\\\"locheight\\\":77,\\\"locleft\\\":555,\\\"loctop\\\":179,\\\"locwidth\\\":68,\\\"ocrresult\\\":\\\"2\\\"}],\\\"clarity\\\":3.0663156509399,\\\"contsign\\\":\\\"4156732981,1969633851\\\",\\\"disgust\\\":2.523367811591e-6,\\\"feature_970_topn\\\":[{\\\"cid\\\":201,\\\"val\\\":0.51182115077972},{\\\"cid\\\":196,\\\"val\\\":0.38987016677856},{\\\"cid\\\":212,\\\"val\\\":0.064134918153286},{\\\"cid\\\":213,\\\"val\\\":0.016204392537475},{\\\"cid\\\":180,\\\"val\\\":0.0035316618159413}],\\\"feature_sexy_lady\\\":0.00018268177518621,\\\"main_area\\\":{\\\"height\\\":426,\\\"left\\\":2,\\\"top\\\":35,\\\"width\\\":614},\\\"porn_prob\\\":0.000345,\\\"same_feature_with_hash\\\":\\\"{\\\\\\\"same_feature_hash_id\\\\\\\":178860,\\\\\\\"same_feature_hash_ids\\\\\\\":[178860,178727,46764,46631,178845,46749,165036,164903,165021]}\\\"}\",\"height\":448,\"image_format\":\"JPEG\",\"low_quality_type\":0,\"url\":\"http://timg01.bdimg.com/timg?pacompress&imgtype=0&sec=1439619614&autorotate=1&di=beea54138af5c653b8e6a809fcda36b0&quality=100&size=b626_10012&cut_x=0&cut_y=0&cut_w=626&cut_h=448&src=http%3A%2F%2Fpic.rmb.bdstatic.com%2F39b9d6089c28c9c57ef65abbd1d2e7ec2126.png\",\"width\":626},\"original_third\":{\"feature_json_format\":\"{\\\"aesthetic\\\":2.8862612247467,\\\"antiporn_normal\\\":0.998425,\\\"antiporn_porn\\\":0.000345,\\\"antiporn_sexy\\\":0.001231,\\\"array\\\":[{\\\"locheight\\\":28,\\\"locleft\\\":567,\\\"loctop\\\":145,\\\"locwidth\\\":55,\\\"ocrresult\\\":\\\"E\\\"},{\\\"locheight\\\":77,\\\"locleft\\\":555,\\\"loctop\\\":179,\\\"locwidth\\\":68,\\\"ocrresult\\\":\\\"2\\\"}],\\\"clarity\\\":3.0663156509399,\\\"contsign\\\":\\\"4156732981,1969633851\\\",\\\"disgust\\\":2.523367811591e-6,\\\"feature_970_topn\\\":[{\\\"cid\\\":201,\\\"val\\\":0.51182115077972},{\\\"cid\\\":196,\\\"val\\\":0.38987016677856},{\\\"cid\\\":212,\\\"val\\\":0.064134918153286},{\\\"cid\\\":213,\\\"val\\\":0.016204392537475},{\\\"cid\\\":180,\\\"val\\\":0.0035316618159413}],\\\"feature_sexy_lady\\\":0.00018268177518621,\\\"main_area\\\":{\\\"height\\\":426,\\\"left\\\":2,\\\"top\\\":35,\\\"width\\\":614},\\\"porn_prob\\\":0.000345,\\\"same_feature_with_hash\\\":\\\"{\\\\\\\"same_feature_hash_id\\\\\\\":178860,\\\\\\\"same_feature_hash_ids\\\\\\\":[178860,178727,46764,46631,178845,46749,165036,164903,165021]}\\\"}\",\"height\":448,\"image_format\":\"JPEG\",\"low_quality_type\":0,\"url\":\"http://timg01.bdimg.com/timg?pacompress&imgtype=0&sec=1439619614&autorotate=1&di=beea54138af5c653b8e6a809fcda36b0&quality=100&size=b626_10012&cut_x=0&cut_y=0&cut_w=626&cut_h=448&src=http%3A%2F%2Fpic.rmb.bdstatic.com%2F39b9d6089c28c9c57ef65abbd1d2e7ec2126.png\",\"width\":626},\"small\":{\"height\":360,\"url\":\"http://t12.baidu.com/it/u=3154809401,1283017158&fm=173&app=25&f=JPEG?w=480&h=360&s=0C604A860A328EDE5ED124890300C001\",\"width\":480}},\"type\":\"image\"},{\"data\":\"你们觉得格林这样的话会对勇士造成什么样的后果呢？\",\"data_rtf\":\"<span class=\\\"bjh-p\\\">你们觉得格林这样的话会对勇士造成什么样的后果呢？</span>\",\"type\":\"text\"},{\"data\":\"\",\"data_rtf\":\"<span class=\\\"bjh-p\\\"></span>\",\"type\":\"text\"}],\"duplicate_sign\":\"2804939461 4119578056\",\"idset\":[80001],\"replace_sign\":\"2719444219 2265168372\"}","title":"格林：你来之前勇士就夺冠了！杜兰特：这就是我要离开的理由？","title_nlpc_lexer":[{"text":"格林：你来之前勇士就夺冠了！杜兰特：这就是我要离开的理由？","items":[{"formal":"","loc_details":[],"item":"格林","pos":"","basic_words":["格林"],"byte_length":4,"ne":"1007","byte_offset":0,"uri":""},{"formal":"","loc_details":[],"item":"：","pos":"w","basic_words":["："],"byte_length":2,"ne":"","byte_offset":4,"uri":""},{"formal":"","loc_details":[],"item":"你","pos":"r","basic_words":["你"],"byte_length":2,"ne":"","byte_offset":6,"uri":""},{"formal":"","loc_details":[],"item":"来","pos":"v","basic_words":["来"],"byte_length":2,"ne":"","byte_offset":8,"uri":""},{"formal":"","loc_details":[],"item":"之","pos":"u","basic_words":["之"],"byte_length":2,"ne":"","byte_offset":10,"uri":""},{"formal":"","loc_details":[],"item":"前","pos":"f","basic_words":["前"],"byte_length":2,"ne":"","byte_offset":12,"uri":""},{"formal":"","loc_details":[],"item":"勇士","pos":"n","basic_words":["勇士"],"byte_length":4,"ne":"","byte_offset":14,"uri":""},{"formal":"","loc_details":[],"item":"就","pos":"d","basic_words":["就"],"byte_length":2,"ne":"","byte_offset":18,"uri":""},{"formal":"","loc_details":[],"item":"夺冠","pos":"v","basic_words":["夺冠"],"byte_length":4,"ne":"","byte_offset":20,"uri":""},{"formal":"","loc_details":[],"item":"了","pos":"xc","basic_words":["了"],"byte_length":2,"ne":"","byte_offset":24,"uri":""},{"formal":"","loc_details":[],"item":"！","pos":"w","basic_words":["！"],"byte_length":2,"ne":"","byte_offset":26,"uri":""},{"formal":"","loc_details":[],"item":"杜兰特","pos":"","basic_words":["杜兰特"],"byte_length":6,"ne":"1007","byte_offset":28,"uri":""},{"formal":"","loc_details":[],"item":"：","pos":"w","basic_words":["："],"byte_length":2,"ne":"","byte_offset":34,"uri":""},{"formal":"","loc_details":[],"item":"这","pos":"r","basic_words":["这"],"byte_length":2,"ne":"","byte_offset":36,"uri":""},{"formal":"","loc_details":[],"item":"就是","pos":"v","basic_words":["就","是"],"byte_length":4,"ne":"","byte_offset":38,"uri":""},{"formal":"","loc_details":[],"item":"我","pos":"r","basic_words":["我"],"byte_length":2,"ne":"","byte_offset":42,"uri":""},{"formal":"","loc_details":[],"item":"要","pos":"v","basic_words":["要"],"byte_length":2,"ne":"","byte_offset":44,"uri":""},{"formal":"","loc_details":[],"item":"离开","pos":"v","basic_words":["离开"],"byte_length":4,"ne":"","byte_offset":46,"uri":""},{"formal":"","loc_details":[],"item":"的","pos":"u","basic_words":["的"],"byte_length":2,"ne":"","byte_offset":50,"uri":""},{"formal":"","loc_details":[],"item":"理由","pos":"n","basic_words":["理由"],"byte_length":4,"ne":"","byte_offset":52,"uri":""},{"formal":"","loc_details":[],"item":"？","pos":"w","basic_words":["？"],"byte_length":2,"ne":"","byte_offset":56,"uri":""}],"retcode":0}],"m_content":"转载自百家号作者：子午体育[子午11月14日讯]杜兰特因为格林在比赛最后时间出现致命失误而指责格林，他表示“你应该把那该死的球给我！”格林随后便在替补席跟杜兰特对喷了起来，而据说二人的战火一直延伸到更衣室，而且越吵越凶，这次吵架的程度已经远远超过了平时，甚至卷入了明年夏天两人离队的问题，也谈及了杜兰特加盟勇士的问题。The Athletic的记者Marcus Thompson曝光了格林和杜兰特对喷的细节：格林表示：勇士在杜兰特到来之前就是总冠军了对于格林在最后关头出现的失误，其实不仅仅杜兰特表示不爽，就连汤普森都觉得格林那样的失误太不应该了。一般勇士在最后时刻都会把球交给杜兰特，但是这次格林并没有把球给旁边的杜兰特，而是选择自己带球到前场，却出现了失误，最终导致输掉了比赛！杜兰特指责格林应该把球传给自己，但是格林却不乐意了，说：“你XX以为你在跟谁说话，别忘记了在你来之前勇士就拿到冠军了！”这一句话的分量想必每个人都知道有多重。杜兰特加盟勇士就是为了能够证明自己，拿到总冠军。而他更是勇士两连冠的夺冠功臣，但是即便如此还是被很多球迷这样诟病，觉得杜兰特是去抱大腿！别人这样说尚可原谅，但是作为勇士的一员，格林都如此说，那么对杜兰特打击相当大了。2.杜兰特自语：这就是我要离开的理由？在格林说出如此重的话之后，杜兰特并没有回喷，而是默默的自言自语了一句：“That's why i'm out？”（这就是我要离开的理由？）格林还骂杜兰特是“碧池！”尤其在讲出那样的话之后，杜兰特似乎受到了很大的打击。并且从这句话之中听出了杜兰特想要离开勇士的念头。明年夏天杜兰特的合同到期，如果他真的想要用另一种方式证明自己的话，估计真的会离开勇士。至于去哪里？不管是去湖人还是重回雷霆，杜兰特将会重新洗刷冤屈。但是选择一个重建中的队伍也不失为一种很好的选择，比如尼克斯！3.格林被重罚格林对于联盟禁赛并且罚款的处罚表示非常的惊讶，他没有想到自己的言论居然会上升到让联盟禁赛的处理，并且罚金也相当高，或许这不是这些处罚的问题，而是球队在这件事情上面的选择吧。在格林禁赛之后杜兰特带队还是拿下了今天的比赛，并且命中了关键球，看起来KD的心态似乎没有受到太大的影响！你们觉得格林这样的话会对勇士造成什么样的后果呢？","strategy_exinfo":"","content":"转载自百家号作者：子午体育[子午11月14日讯]杜兰特因为格林在比赛最后时间出现致命失误而指责格林，他表示“你应该把那该死的球给我！”格林随后便在替补席跟杜兰特对喷了起来，而据说二人的战火一直延伸到更衣室，而且越吵越凶，这次吵架的程度已经远远超过了平时，甚至卷入了明年夏天两人离队的问题，也谈及了杜兰特加盟勇士的问题。The Athletic的记者Marcus Thompson曝光了格林和杜兰特对喷的细节：格林表示：勇士在杜兰特到来之前就是总冠军了对于格林在最后关头出现的失误，其实不仅仅杜兰特表示不爽，就连汤普森都觉得格林那样的失误太不应该了。一般勇士在最后时刻都会把球交给杜兰特，但是这次格林并没有把球给旁边的杜兰特，而是选择自己带球到前场，却出现了失误，最终导致输掉了比赛！杜兰特指责格林应该把球传给自己，但是格林却不乐意了，说：“你XX以为你在跟谁说话，别忘记了在你来之前勇士就拿到冠军了！”这一句话的分量想必每个人都知道有多重。杜兰特加盟勇士就是为了能够证明自己，拿到总冠军。而他更是勇士两连冠的夺冠功臣，但是即便如此还是被很多球迷这样诟病，觉得杜兰特是去抱大腿！别人这样说尚可原谅，但是作为勇士的一员，格林都如此说，那么对杜兰特打击相当大了。2.杜兰特自语：这就是我要离开的理由？在格林说出如此重的话之后，杜兰特并没有回喷，而是默默的自言自语了一句：“That's why i'm out？”（这就是我要离开的理由？）格林还骂杜兰特是“碧池！”尤其在讲出那样的话之后，杜兰特似乎受到了很大的打击。并且从这句话之中听出了杜兰特想要离开勇士的念头。明年夏天杜兰特的合同到期，如果他真的想要用另一种方式证明自己的话，估计真的会离开勇士。至于去哪里？不管是去湖人还是重回雷霆，杜兰特将会重新洗刷冤屈。但是选择一个重建中的队伍也不失为一种很好的选择，比如尼克斯！3.格林被重罚格林对于联盟禁赛并且罚款的处罚表示非常的惊讶，他没有想到自己的言论居然会上升到让联盟禁赛的处理，并且罚金也相当高，或许这不是这些处罚的问题，而是球队在这件事情上面的选择吧。在格林禁赛之后杜兰特带队还是拿下了今天的比赛，并且命中了关键球，看起来KD的心态似乎没有受到太大的影响！你们觉得格林这样的话会对勇士造成什么样的后果呢？","m_text":"杜兰特因为格林在比赛最后时间出现致命失误而指责格林，他表示，你应该把那该死的球给我。","news_short_title":0,"display_type":3,"flip_page_num":0,"gram_bad_words":"","rela_sign":"2924126916 3074669004","content_type":1,"sex_level":0,"tj_category":3,"tj_news_attention":[["格林-->>德雷蒙德·格林",527],["杜兰特",517],["杜兰特加盟勇士",388],["勇士比赛",318],["nba",246]],"score_topic_short_weibo":0.01148112220523756,"new_long_summary":"{\"new_long_summary\":[{\"type\":\"text\", \"data\":\"[子午11月14日讯]杜兰特因为格林在比赛最后时间出现致命失误而指责格林，他表示“你应该把那该死的球给我！”格林随后便在替补席跟杜兰特对喷了起来，而据说二人的战火一直延伸到更衣室，而且越吵越凶，这次吵架的程度已经远远超过了平时，甚至卷入了明年夏天两人离队的问题，也谈及了杜兰特加盟勇士的问题。\", \"para_index\":1, \"view_index\":1, \"view_hint\":\"\", \"view_keywords\":\"\", \"logic_label\":\"0\"}, {\"type\":\"image\", \"data\":{\"original\":{\"url\":\"http:\\/\\/timg01.bdimg.com\\/timg?pacompress&imgtype=0&sec=1439619614&autorotate=1&di=7ec369ae484e3cd685ddf39aeafe603e&quality=100&size=b566_10014&cut_x=0&cut_y=0&cut_w=566&cut_h=359&src=http%3A%2F%2Fpic.rmb.bdstatic.com%2Fe6cb02a7f5a2311ad715fdb1483d580a2329.png\", \"width\":566, \"height\":359}, \"original_third\":{\"url\":\"http:\\/\\/timg01.bdimg.com\\/timg?pacompress&imgtype=0&sec=1439619614&autorotate=1&di=7ec369ae484e3cd685ddf39aeafe603e&quality=100&size=b566_10014&cut_x=0&cut_y=0&cut_w=566&cut_h=359&src=http%3A%2F%2Fpic.rmb.bdstatic.com%2Fe6cb02a7f5a2311ad715fdb1483d580a2329.png\", \"width\":566, \"height\":359}, \"big\":{\"url\":\"http:\\/\\/t11.baidu.com\\/it\\/u=3730347925,3925162013&fm=173&app=49&f=JPEG?w=566&h=359&s=AF7A7986D72305AFD67409170300D0C0\", \"width\":566, \"height\":359}, \"small\":{\"url\":\"http:\\/\\/t12.baidu.com\\/it\\/u=2621399549,1137609421&fm=173&app=25&f=JPEG?w=480&h=359&s=EF7A31C6D73305AFD67409170300D0C0\", \"width\":480, \"height\":359}}, \"para_index\":2, \"view_index\":1, \"view_hint\":\"\", \"view_keywords\":\"\", \"logic_label\":\"0\"}, {\"type\":\"text\", \"data\":\"格林表示：勇士在杜兰特到来之前就是总冠军了对于格林在最后关头出现的失误，其实不仅仅杜兰特表示不爽，就连汤普森都觉得格林那样的失误太不应该了。一般勇士在最后时刻都会把球交给杜兰特，但是这次格林并没有把球给旁边的杜兰特，而是选择自己带球到前场，却出现了失误，最终导致输掉了比赛！别人这样说尚可原谅，但是作为勇士的一员，格林都如此说，那么对杜兰特打击相当大了。\", \"para_index\":3, \"view_index\":2, \"view_hint\":\"\", \"view_keywords\":\"\", \"logic_label\":\"2\"}, {\"type\":\"image\", \"data\":{\"original\":{\"url\":\"http:\\/\\/timg01.bdimg.com\\/timg?pacompress&imgtype=0&sec=1439619614&autorotate=1&di=8c0d5b6cb5bd15c57dcae94d013bcaf8&quality=100&size=b435_10065&cut_x=0&cut_y=0&cut_w=435&cut_h=365&src=http%3A%2F%2Fpic.rmb.bdstatic.com%2F0e21fc47a7ba4cb82e597ac22610ab623590.png\", \"width\":435, \"height\":365}, \"original_third\":{\"url\":\"http:\\/\\/timg01.bdimg.com\\/timg?pacompress&imgtype=0&sec=1439619614&autorotate=1&di=8c0d5b6cb5bd15c57dcae94d013bcaf8&quality=100&size=b435_10065&cut_x=0&cut_y=0&cut_w=435&cut_h=365&src=http%3A%2F%2Fpic.rmb.bdstatic.com%2F0e21fc47a7ba4cb82e597ac22610ab623590.png\", \"width\":435, \"height\":365}, \"big\":{\"url\":\"http:\\/\\/t11.baidu.com\\/it\\/u=2336682787,1365582304&fm=173&app=49&f=JPEG?w=435&h=365&s=E4948D739EF26FBF2A8884CE03007030\", \"width\":435, \"height\":365}, \"small\":{\"url\":\"http:\\/\\/t11.baidu.com\\/it\\/u=2386893502,2885342073&fm=173&app=25&f=JPEG?w=435&h=360&s=E4948D739EB26FBF2A8884CE03007030\", \"width\":435, \"height\":360}}, \"para_index\":4, \"view_index\":2, \"view_hint\":\"\", \"view_keywords\":\"\", \"logic_label\":\"2\"}, {\"type\":\"text\", \"data\":\"在格林说出如此重的话之后，杜兰特并没有回喷，而是默默的自言自语了一句，That's why i'm out？格林还骂杜兰特是，碧池！尤其在讲出那样的话之后，杜兰特似乎受到了很大的打击。明年夏天杜兰特的合同到期，如果他真的想要用另一种方式证明自己的话，估计真的会离开勇士。不管是去湖人还是重回雷霆，杜兰特将会重新洗刷冤屈。但是选择一个重建中的队伍也不失为一种很好的选择，比如尼克斯！\", \"para_index\":5, \"view_index\":3, \"view_hint\":\"\", \"view_keywords\":\"\", \"logic_label\":\"0\"}, {\"type\":\"image\", \"data\":{\"original\":{\"url\":\"http:\\/\\/timg01.bdimg.com\\/timg?pacompress&imgtype=0&sec=1439619614&autorotate=1&di=beea54138af5c653b8e6a809fcda36b0&quality=100&size=b626_10012&cut_x=0&cut_y=0&cut_w=626&cut_h=448&src=http%3A%2F%2Fpic.rmb.bdstatic.com%2F39b9d6089c28c9c57ef65abbd1d2e7ec2126.png\", \"width\":626, \"height\":448}, \"original_third\":{\"url\":\"http:\\/\\/timg01.bdimg.com\\/timg?pacompress&imgtype=0&sec=1439619614&autorotate=1&di=beea54138af5c653b8e6a809fcda36b0&quality=100&size=b626_10012&cut_x=0&cut_y=0&cut_w=626&cut_h=448&src=http%3A%2F%2Fpic.rmb.bdstatic.com%2F39b9d6089c28c9c57ef65abbd1d2e7ec2126.png\", \"width\":626, \"height\":448}, \"big\":{\"url\":\"http:\\/\\/t10.baidu.com\\/it\\/u=335444118,89395724&fm=173&app=49&f=JPEG?w=626&h=448&s=0C704A860A328ED65ED124890300C001\", \"width\":626, \"height\":448}, \"small\":{\"url\":\"http:\\/\\/t12.baidu.com\\/it\\/u=3154809401,1283017158&fm=173&app=25&f=JPEG?w=480&h=360&s=0C604A860A328EDE5ED124890300C001\", \"width\":480, \"height\":360}}, \"para_index\":6, \"view_index\":3, \"view_hint\":\"\", \"view_keywords\":\"\", \"logic_label\":\"0\"}]}","queue_summary":{"QT_10005_data":{"queue_type":"10005","queue_attention":{"光明热点-baijiahao.baidu.com":100}},"QT_10007_data":{"queue_type":"10007","queue_attention":{"体育_NBA球员动态":841}}},"innersource_type":0,"news_style_super_alpha":[],"new_summary":"格林：你来之前勇士就夺冠了！杜兰特：这就是我要离开的理由？","m_tag":"","star_private_flag":0,"media_category_id":0,"multi_cate":[{"cate":3,"ratio":0},{"cate":0,"ratio":0}],"news_sub_category_prob":0.760945,"tj_tags":[["杜兰特",190],["格林",184],["离开的理由",180],["勇士",171],["理由",146],["夺冠",128],["失误",60],["禁赛",51],["明年夏天",40],["比赛",30],["联盟",25],["汤普森",25],["处罚",21],["证明",20],["打击",20],["战火",20],["功臣",20],["诟病",20],["尼克斯",20],["合同到期",20]],"copy_time":1542206193,"title_simhash64":9186766477222870795,"tj_cate_prob":0.9999715185415,"tj_timeliness":1,"score_topic_long_content":0.02181204795715819,"scrape_hot_attention_level":0,"feedid":"news_9420830529692060020","new_ds":"[{\"ds1\":2719444219,\"ds2\":2265168372}]\n","news_style_super":[],"old_news_recog_info":{"sim":1.0,"nid":"","type":"rtg","url":"http://baijiahao.baidu.com/s?id=1617120342100474101&wfr=spider&for=pc"},"low_matching_level":0,"data_type":0,"pages_type":"0","comment":"","time":1542244999,"is_confident_source":0,"red_news_type":0,"news_tag":{},"virtual_level":7,"news_style":[],"scene_type":0,"passport_id":"818639858","title_content_non_sim_score":0.0,"mypos":"","importance_model_level":"2","replace_sign":"2719444219 2265168372","value_general_tags":[],"is_push":"0","quality_emergent_flags":{"40030":"non_fr_brush_模板账号","50010":"common_weight","70010":"common_weight","60030":"fr_brush_模板账号","10006":"模板账号"},"readable_score":0.4025079607963562,"same_sign":"2924126916 3074669004","vertical_types":[0],"cluster_infos_for_rank":{"cluster_attention":{"格林-->>德雷蒙德·格林":527,"勇士比赛":319,"杜兰特":517,"杜兰特加盟勇士":388},"cluster_tags":{"理由":146,"格林":184,"杜兰特":190,"离开的理由":180,"夺冠":128,"勇士":171},"cluster_cnt":"2","cluster_nid":"7876865519557377016"},"importance_model_info":{"0":0.00195314,"1":0.224609,"2":0.771484},"news_category_v1_id":2,"ext_tag_term":"","query_attention":{"篮球":0.7989,"杜兰特":0.4975},"is_original":0,"novelty_level":1,"ext_info":"{\"ABTEST\":{\"mode\":\"1\",\"repo\":\"9\"},\"audit_type\":\"00000000\",\"author_level\":\"fresh\",\"can_edit_title\":1,\"cat_high_quality_score\":\"2\",\"group_key_info\":{\"level\":1,\"level_original_val\":\"2\",\"level_plan\":[],\"level_type\":2,\"level_val\":\"2\",\"original_status\":1,\"source_type\":\"platform\",\"sub_type\":\"individual\"},\"has_edited_times\":0,\"has_rtf\":1,\"has_spd\":0,\"is_pay\":0,\"machine_audit_white\":1,\"mthvideo\":0,\"original_recog_serv_ret\":{\"key_info\":{\"content\":\"格林随后便在替补席跟杜兰特对喷了起来而据说二人的战火一直延伸到更衣室而且越吵越凶这次吵架的程度已经远远超过了平时甚至卷入了明年夏天两人离队的问题也谈及了杜兰特加盟勇士的问题\",\"dedupid\":\"822978851446636755\",\"time\":1542244996,\"title\":\"格林：你来之前勇士就夺冠了！杜兰特：这就是我要离开的理由？\",\"url\":\"http://baijiahao.baidu.com/s?id=1617161057838710995\"},\"recog_ret\":\"REFER\",\"sim_cnt\":3,\"sim_list\":[{\"sim\":1.0,\"src\":0,\"url_info\":{\"content\":\"NULL\",\"time\":1542207649,\"title\":\"格林：你来之前勇士就夺冠了！杜兰特：这就是我要离开的理由？\",\"url\":\"http://www.toutiao.com/a6623725410486075918/\"}},{\"sim\":1.0,\"src\":0,\"url_info\":{\"content\":\"NULL\",\"time\":1542207258,\"title\":\"格林：你来之前勇士就夺冠了！杜兰特：这就是我要离开的理由？\",\"url\":\"http://www.toutiao.com/item/6623725410486075918/\"}},{\"sim\":1.0,\"src\":0,\"url_info\":{\"content\":\"NULL\",\"time\":1542206202,\"title\":\"格林：你来之前勇士就夺冠了！杜兰特：这就是我要离开的理由？\",\"url\":\"http://baijiahao.baidu.com/s?id=1617120342100474101&wfr=spider&for=pc\"}}]},\"original_status\":\"0\",\"pay_money\":0,\"picture_small_flow\":1,\"replicate_original\":\"7876865519557377016\",\"site_type\":0,\"which_title\":0}","importance_score_v1":0.06323922897647465,"high_timeliness":0,"type_setting_level":2,"timeliness":52604,"original_name":"","push_source":"-1","author_authority_score_v1":2,"m_category":"3","new_sex_level":0,"copy_score":0.984159574382961,"kg_resource_tag":[],"cont_xpath":"","loc_news":0,"from_id":"queue_dongxi","author_activity_score":-1,"check_locname":{},"m_display_url":"http://baijiahao.baidu.com/s?id=1617161057838710995","informative_level":1,"news_short_hierarchy":[{"path":[["nba=>篮球",252]],"topic":"篮球"}],"img_num":4,"title_simhash":"49205508650421067966001446705274027463","new_image_sign":"[{\"img_id\":15566238259515850942,\"sign\":[15566238259515850942]}, {\"img_id\":1714230756916508013,\"sign\":[1714230756916508013]}, {\"img_id\":17368322657549996154,\"sign\":[17368322657549996154]}, {\"img_id\":1134823274516740512,\"sign\":[1134823274516740512]}]","title_intr_wordseg":{"xx":0.8271919272795484,"曝光":0.0,"一":0.0,"谁":0.0,"知道":0.0,"最后":0.0,"球":0.3955730963820375,"打击":0.5014390986918839,"总冠军":0.6638567255391537,"更衣室":0.4033298539247915,"汤普森":1.217044906619698,"月":0.1247534510026061,"延伸":0.0,"比赛":0.482587347746874,"而":0.0,"不":0.0,"并没有":0.7057478251691082,"勇士":1.186690062064265,"我":0.0,"选择":0.0,"那么":0.0,"旁边":0.0,"就是":0.0,"已经":0.0,"甚至":0.0,"尚":0.0,"拿到":0.0,"两人":0.364603285018989,"11":0.0,"传":0.0,"14":0.0,"作者":0.2174365004498897,"两":0.0,"一般":0.0,"大":0.0,"该死":0.0,"在":0.0,"如此":0.0,"太":0.0,"之后":0.0,"别":0.0,"吵架":0.0,"席":0.0,".":0.0,"功臣":0.3848912166586446,"是":0.0,"到":0.0,"就":0.0,"2":0.0,"有多重":1.0,"大腿":0.3571668927133308,"吵":0.0,"加盟":0.0,"每个":0.0,"athletic":1.0,"不仅仅":0.0,"记者":0.5711671469071571,"还是":0.0,"输掉":0.3380519169617512,"据说":0.0,"替补":0.0,"之":0.0,"原谅":0.0,"前":0.0,"随后":0.0,"因为":0.0,"自语":0.0,"相当":0.0,"自己":0.0,"作为":0.0,"员":0.0,"thompson":0.2610333666156167,"球迷":0.2819488496153144,"就是为了":0.54639072988209,"战火":0.4110608828354628,"你":0.0,"来":0.0,"这样":0.0,"the":1.0,"明年夏天":1.0,"导致":0.0,"细节":0.1351861365163013,"却":0.0,"说话":0.0,"问题":0.1764866510907361,"这次":0.0,"证明":0.0,"转载":0.0,"要":0.0,"分量":0.9215391047696592,"也谈":0.5265166409650381,"的":0.0,"了":0.0,"而且":0.0,"前场":0.0,"最后时刻":0.402440559125584,"把":0.0,"越":0.0,"和":0.0,"远远":0.0,"连冠":0.3293654876205619,"带球":0.0,"说出":0.0,"很多":0.0,"但是":0.0,"那":0.0,"二人":0.2755823504847765,"离开":0.0,"被":0.0,"都会":0.2282923839407849,"而是":0.0,"夺冠":0.203535045094054,"不应该":1.0,"marcus":0.9402275893695508,"讯":0.0,"抱":0.0,"时间":0.1442833394112458,"体育":0.4781508158468028,"乐意":0.0,"喷":0.0,"一句话":0.0,"最后关头":0.353344690653229,"人":0.1672572949990557,"去":0.0,"到来之前":0.353344690653229,"对于":0.0,"便":0.0,"交给":0.0,"表示":0.0,"卷入":0.0,"最终":0.0,"必":0.0,"及":0.0,"离队":0.0,"能够":0.0,"重":0.0,"忘记":0.0,"失误":0.2966348056013356,"格林":2.337678988371444,"他":0.0,"诟病":0.3551758012047134,"不爽":0.2178935225867108,"给":0.0,"这":0.0,"应该":0.0,"话":0.2803541703093894,"回":0.0,"连":0.0,"跟":0.0,"起来":0.0,"其实":0.0,"别人":0.0,"理由":0.91779715913979,"那样":0.0,"日":0.0,"平时":0.0,"自":0.0,"杜兰特":2.0,"即便如此":0.4718230419449647,"可":0.0,"这就是我":1.71134344215122,"指责":0.0,"冠军":0.6522215906623133,"超过":0.0,"想":0.0,"子午":1.0,"程度":0.1825084954930669,"更":0.0,"说":0.0,"百家":1.171849756038485,"凶":0.0,"号":0.1379332154735141,"对":0.0,"出现":0.0,"以为":0.0,"致命失误":1.0,"都":0.0,"一直":0.0,"觉得":0.0},"quality_feature_score":0.4025079607963562,"original_gimgurls":[{"original":"http://timg01.bdimg.com/timg?pacompress&imgtype=0&sec=1439619614&autorotate=1&di=7c73beacf06b6fb27c64136a2e25af98&quality=100&size=b536_10048&cut_x=20&cut_y=12&cut_w=536&cut_h=359&src=http%3A%2F%2Ftimg01.bdimg.com%2Ftimg%3Fpacompress%26imgtype%3D0%26sec%3D1439619614%26autorotate%3D1%26di%3D7ec369ae484e3cd685ddf39aeafe603e%26quality%3D100%26size%3Db566_10014%26cut_x%3D0%26cut_y%3D0%26cut_w%3D566%26cut_h%3D359%26src%3Dhttp%253A%252F%252Fpic.rmb.bdstatic.com%252Fe6cb02a7f5a2311ad715fdb1483d580a2329.png","content_original":"http://timg01.bdimg.com/timg?pacompress&imgtype=0&sec=1439619614&autorotate=1&di=7ec369ae484e3cd685ddf39aeafe603e&quality=100&size=b566_10014&cut_x=0&cut_y=0&cut_w=566&cut_h=359&src=http%3A%2F%2Fpic.rmb.bdstatic.com%2Fe6cb02a7f5a2311ad715fdb1483d580a2329.png","width":536,"url":"http://t11.baidu.com/it/u=3892753285,3515264900&fm=173&app=25&f=JPEG?w=536&h=302&s=AF3A6986DF3305AFD67409160300C0C0","height":302},{"original":"http://timg01.bdimg.com/timg?pacompress&imgtype=0&sec=1439619614&autorotate=1&di=cd118d2ee9f75e56b30f3ff29705b196&quality=100&size=b435_10008&cut_x=0&cut_y=0&cut_w=435&cut_h=292&src=http%3A%2F%2Ftimg01.bdimg.com%2Ftimg%3Fpacompress%26imgtype%3D0%26sec%3D1439619614%26autorotate%3D1%26di%3D8c0d5b6cb5bd15c57dcae94d013bcaf8%26quality%3D100%26size%3Db435_10065%26cut_x%3D0%26cut_y%3D0%26cut_w%3D435%26cut_h%3D365%26src%3Dhttp%253A%252F%252Fpic.rmb.bdstatic.com%252F0e21fc47a7ba4cb82e597ac22610ab623590.png","content_original":"http://timg01.bdimg.com/timg?pacompress&imgtype=0&sec=1439619614&autorotate=1&di=8c0d5b6cb5bd15c57dcae94d013bcaf8&quality=100&size=b435_10065&cut_x=0&cut_y=0&cut_w=435&cut_h=365&src=http%3A%2F%2Fpic.rmb.bdstatic.com%2F0e21fc47a7ba4cb82e597ac22610ab623590.png","width":435,"url":"http://t12.baidu.com/it/u=3842881622,2420785904&fm=173&app=25&f=JPEG?w=435&h=245&s=C4B48D7396B26BBF228984CE03003030","height":245},{"original":"http://timg01.bdimg.com/timg?pacompress&imgtype=1&sec=1439619614&autorotate=1&di=c332bc4c5463aff5ac56aa7a97bccf85&quality=100&size=b637_10055&cut_x=47&cut_y=0&cut_w=637&cut_h=427&src=http%3A%2F%2Ftimg01.bdimg.com%2Ftimg%3Fpacompress%26imgtype%3D1%26sec%3D1439619614%26autorotate%3D1%26di%3D8380aa912dfea69ac0a09deafa1a4f80%26quality%3D100%26size%3Db640_10053%26cut_x%3D0%26cut_y%3D0%26cut_w%3D640%26cut_h%3D427%26src%3Dhttp%253A%252F%252Fpic.rmb.bdstatic.com%252F9fd62844c2777a7d0683bf7c7f94f7a06850.jpeg","content_original":"http://timg01.bdimg.com/timg?pacompress&imgtype=1&sec=1439619614&autorotate=1&di=8380aa912dfea69ac0a09deafa1a4f80&quality=100&size=b640_10053&cut_x=0&cut_y=0&cut_w=640&cut_h=427&src=http%3A%2F%2Fpic.rmb.bdstatic.com%2F9fd62844c2777a7d0683bf7c7f94f7a06850.jpeg","width":637,"url":"http://t11.baidu.com/it/u=2520291361,2019214235&fm=173&app=25&f=JPEG?w=637&h=358&s=4A21B1445C0204D8165C79900300D09A","height":358}],"priori_quality_score":0.6697742446819619,"quality_status":"","para_content":{"idset":[80001],"replace_sign":"2719444219 2265168372","duplicate_sign":"2804939461 4119578056","content":[{"data":"转载自百家号作者：子午体育","data_rtf":"<span class=\"bjh-blockquote\"><span class=\"bjh-p\">转载自百家号作者：子午体育</span></span>","type":"text"},{"data":"[子午11月14日讯]杜兰特因为格林在比赛最后时间出现致命失误而指责格林，他表示“你应该把那该死的球给我！”格林随后便在替补席跟杜兰特对喷了起来，而据说二人的战火一直延伸到更衣室，而且越吵越凶，这次吵架的程度已经远远超过了平时，甚至卷入了明年夏天两人离队的问题，也谈及了杜兰特加盟勇士的问题。","data_rtf":"<span class=\"bjh-p\">[子午11月14日讯]杜兰特因为格林在比赛最后时间出现致命失误而指责格林，他表示“你应该把那该死的球给我！”格林随后便在替补席跟杜兰特对喷了起来，而据说二人的战火一直延伸到更衣室，而且越吵越凶，这次吵架的程度已经远远超过了平时，甚至卷入了明年夏天两人离队的问题，也谈及了杜兰特加盟勇士的问题。</span>","type":"text"},{"data":{"cont_small":{"src":"http://t12.baidu.com/it/u=3459066362,4205026556&fm=173&app=25&f=JPEG?w=320&h=203&s=EF7A31C6D73305AFD67409170300D0C0","width":320,"height":203},"small":{"width":480,"url":"http://t12.baidu.com/it/u=2621399549,1137609421&fm=173&app=25&f=JPEG?w=480&h=359&s=EF7A31C6D73305AFD67409170300D0C0","height":359},"big":{"width":566,"url":"http://t11.baidu.com/it/u=3730347925,3925162013&fm=173&app=49&f=JPEG?w=566&h=359&s=AF7A7986D72305AFD67409170300D0C0","height":359},"original":{"low_quality_type":0,"feature_json_format":"{\"aesthetic\":1.0979804992676,\"antiporn_normal\":0.994943,\"antiporn_porn\":0.002138,\"antiporn_sexy\":0.002919,\"array\":[],\"clarity\":1.8325614929199,\"contsign\":\"1631796782,306821668\",\"disgust\":0.0033482315484434,\"feature_970_topn\":[{\"cid\":201,\"val\":0.44424599409103},{\"cid\":196,\"val\":0.19307297468185},{\"cid\":212,\"val\":0.12138571590185},{\"cid\":159,\"val\":0.047825615853071},{\"cid\":180,\"val\":0.021666590124369}],\"feature_sexy_lady\":0.0021154419519007,\"main_area\":{\"height\":363,\"left\":22,\"top\":4,\"width\":530},\"porn_prob\":0.002138,\"same_feature_with_hash\":\"{\\\"same_feature_hash_id\\\":178982,\\\"same_feature_hash_ids\\\":[178982,178727,46886,46631,178978,46882,138534,138279,138530]}\"}","width":566,"image_format":"JPEG","url":"http://timg01.bdimg.com/timg?pacompress&imgtype=0&sec=1439619614&autorotate=1&di=7ec369ae484e3cd685ddf39aeafe603e&quality=100&size=b566_10014&cut_x=0&cut_y=0&cut_w=566&cut_h=359&src=http%3A%2F%2Fpic.rmb.bdstatic.com%2Fe6cb02a7f5a2311ad715fdb1483d580a2329.png","height":359},"original_third":{"low_quality_type":0,"feature_json_format":"{\"aesthetic\":1.0979804992676,\"antiporn_normal\":0.994943,\"antiporn_porn\":0.002138,\"antiporn_sexy\":0.002919,\"array\":[],\"clarity\":1.8325614929199,\"contsign\":\"1631796782,306821668\",\"disgust\":0.0033482315484434,\"feature_970_topn\":[{\"cid\":201,\"val\":0.44424599409103},{\"cid\":196,\"val\":0.19307297468185},{\"cid\":212,\"val\":0.12138571590185},{\"cid\":159,\"val\":0.047825615853071},{\"cid\":180,\"val\":0.021666590124369}],\"feature_sexy_lady\":0.0021154419519007,\"main_area\":{\"height\":363,\"left\":22,\"top\":4,\"width\":530},\"porn_prob\":0.002138,\"same_feature_with_hash\":\"{\\\"same_feature_hash_id\\\":178982,\\\"same_feature_hash_ids\\\":[178982,178727,46886,46631,178978,46882,138534,138279,138530]}\"}","width":566,"image_format":"JPEG","url":"http://timg01.bdimg.com/timg?pacompress&imgtype=0&sec=1439619614&autorotate=1&di=7ec369ae484e3cd685ddf39aeafe603e&quality=100&size=b566_10014&cut_x=0&cut_y=0&cut_w=566&cut_h=359&src=http%3A%2F%2Fpic.rmb.bdstatic.com%2Fe6cb02a7f5a2311ad715fdb1483d580a2329.png","height":359},"caption":""},"type":"image"},{"data":"The Athletic的记者Marcus Thompson曝光了格林和杜兰特对喷的细节：","data_rtf":"<span class=\"bjh-p\">The Athletic的记者Marcus Thompson曝光了格林和杜兰特对喷的细节：</span>","type":"text"},{"data":"格林表示：勇士在杜兰特到来之前就是总冠军了对于格林在最后关头出现的失误，其实不仅仅杜兰特表示不爽，就连汤普森都觉得格林那样的失误太不应该了。一般勇士在最后时刻都会把球交给杜兰特，但是这次格林并没有把球给旁边的杜兰特，而是选择自己带球到前场，却出现了失误，最终导致输掉了比赛！杜兰特指责格林应该把球传给自己，但是格林却不乐意了，说：“你XX以为你在跟谁说话，别忘记了在你来之前勇士就拿到冠军了！”这一句话的分量想必每个人都知道有多重。杜兰特加盟勇士就是为了能够证明自己，拿到总冠军。而他更是勇士两连冠的夺冠功臣，但是即便如此还是被很多球迷这样诟病，觉得杜兰特是去抱大腿！别人这样说尚可原谅，但是作为勇士的一员，格林都如此说，那么对杜兰特打击相当大了。","data_rtf":"<span class=\"bjh-ol\"><span class=\"bjh-li\"><span class=\"bjh-p\">格林表示：勇士在杜兰特到来之前就是总冠军了</span></span></span><span class=\"bjh-p\">对于格林在最后关头出现的失误，其实不仅仅杜兰特表示不爽，就连汤普森都觉得格林那样的失误太不应该了。一般勇士在最后时刻都会把球交给杜兰特，但是这次格林并没有把球给旁边的杜兰特，而是选择自己带球到前场，却出现了失误，最终导致输掉了比赛！杜兰特指责格林应该把球传给自己，但是格林却不乐意了，说：“你XX以为你在跟谁说话，别忘记了在你来之前勇士就拿到冠军了！”这一句话的分量想必每个人都知道有多重。杜兰特加盟勇士就是为了能够证明自己，拿到总冠军。而他更是勇士两连冠的夺冠功臣，但是即便如此还是被很多球迷这样诟病，觉得杜兰特是去抱大腿！别人这样说尚可原谅，但是作为勇士的一员，格林都如此说，那么对杜兰特打击相当大了。</span>","type":"text"},{"data":{"cont_small":{"src":"http://t10.baidu.com/it/u=4255944852,3566055385&fm=173&app=25&f=JPEG?w=320&h=269&s=E4948D739EB26FBF2A8884CE03007030","width":320,"height":269},"small":{"width":435,"url":"http://t11.baidu.com/it/u=2386893502,2885342073&fm=173&app=25&f=JPEG?w=435&h=360&s=E4948D739EB26FBF2A8884CE03007030","height":360},"big":{"width":435,"url":"http://t11.baidu.com/it/u=2336682787,1365582304&fm=173&app=49&f=JPEG?w=435&h=365&s=E4948D739EF26FBF2A8884CE03007030","height":365},"original":{"low_quality_type":32,"feature_json_format":"{\"aesthetic\":2.0405900478363,\"antiporn_normal\":0.994679,\"antiporn_porn\":0.001185,\"antiporn_sexy\":0.004136,\"array\":[{\"locheight\":26,\"locleft\":245,\"loctop\":179,\"locwidth\":43,\"ocrresult\":\"23\"},{\"locheight\":16,\"locleft\":224,\"loctop\":240,\"locwidth\":69,\"ocrresult\":\" APPIOT\"}],\"clarity\":3.1381440162659,\"contsign\":\"1791461325,1597834450\",\"disgust\":0.00037124933442101,\"feature_970_topn\":[{\"cid\":201,\"val\":0.86624646186829},{\"cid\":196,\"val\":0.09207608550787},{\"cid\":212,\"val\":0.028564509004354},{\"cid\":213,\"val\":0.005481060128659},{\"cid\":218,\"val\":0.001208167639561}],\"feature_sexy_lady\":0.00016277871327475,\"main_area\":{\"height\":373,\"left\":16,\"top\":1,\"width\":416},\"porn_prob\":0.001185,\"same_feature_with_hash\":\"{\\\"same_feature_hash_id\\\":46656,\\\"same_feature_hash_ids\\\":[46656,46688,178752,178784,46915,179011,164928,164960,165187]}\"}","width":435,"image_format":"JPEG","url":"http://timg01.bdimg.com/timg?pacompress&imgtype=0&sec=1439619614&autorotate=1&di=8c0d5b6cb5bd15c57dcae94d013bcaf8&quality=100&size=b435_10065&cut_x=0&cut_y=0&cut_w=435&cut_h=365&src=http%3A%2F%2Fpic.rmb.bdstatic.com%2F0e21fc47a7ba4cb82e597ac22610ab623590.png","height":365},"original_third":{"low_quality_type":32,"feature_json_format":"{\"aesthetic\":2.0405900478363,\"antiporn_normal\":0.994679,\"antiporn_porn\":0.001185,\"antiporn_sexy\":0.004136,\"array\":[{\"locheight\":26,\"locleft\":245,\"loctop\":179,\"locwidth\":43,\"ocrresult\":\"23\"},{\"locheight\":16,\"locleft\":224,\"loctop\":240,\"locwidth\":69,\"ocrresult\":\" APPIOT\"}],\"clarity\":3.1381440162659,\"contsign\":\"1791461325,1597834450\",\"disgust\":0.00037124933442101,\"feature_970_topn\":[{\"cid\":201,\"val\":0.86624646186829},{\"cid\":196,\"val\":0.09207608550787},{\"cid\":212,\"val\":0.028564509004354},{\"cid\":213,\"val\":0.005481060128659},{\"cid\":218,\"val\":0.001208167639561}],\"feature_sexy_lady\":0.00016277871327475,\"main_area\":{\"height\":373,\"left\":16,\"top\":1,\"width\":416},\"porn_prob\":0.001185,\"same_feature_with_hash\":\"{\\\"same_feature_hash_id\\\":46656,\\\"same_feature_hash_ids\\\":[46656,46688,178752,178784,46915,179011,164928,164960,165187]}\"}","width":435,"image_format":"JPEG","url":"http://timg01.bdimg.com/timg?pacompress&imgtype=0&sec=1439619614&autorotate=1&di=8c0d5b6cb5bd15c57dcae94d013bcaf8&quality=100&size=b435_10065&cut_x=0&cut_y=0&cut_w=435&cut_h=365&src=http%3A%2F%2Fpic.rmb.bdstatic.com%2F0e21fc47a7ba4cb82e597ac22610ab623590.png","height":365},"caption":""},"type":"image"},{"data":"2.杜兰特自语：这就是我要离开的理由？","data_rtf":"<span class=\"bjh-p\">2.杜兰特自语：这就是我要离开的理由？</span>","type":"text"},{"data":"在格林说出如此重的话之后，杜兰特并没有回喷，而是默默的自言自语了一句：“That's why i'm out？”（这就是我要离开的理由？）格林还骂杜兰特是“碧池！”尤其在讲出那样的话之后，杜兰特似乎受到了很大的打击。并且从这句话之中听出了杜兰特想要离开勇士的念头。明年夏天杜兰特的合同到期，如果他真的想要用另一种方式证明自己的话，估计真的会离开勇士。至于去哪里？不管是去湖人还是重回雷霆，杜兰特将会重新洗刷冤屈。但是选择一个重建中的队伍也不失为一种很好的选择，比如尼克斯！","data_rtf":"<span class=\"bjh-p\">在格林说出如此重的话之后，杜兰特并没有回喷，而是默默的自言自语了一句：“That's why i'm out？”（这就是我要离开的理由？）格林还骂杜兰特是“碧池！”尤其在讲出那样的话之后，杜兰特似乎受到了很大的打击。并且从这句话之中听出了杜兰特想要离开勇士的念头。明年夏天杜兰特的合同到期，如果他真的想要用另一种方式证明自己的话，估计真的会离开勇士。至于去哪里？不管是去湖人还是重回雷霆，杜兰特将会重新洗刷冤屈。但是选择一个重建中的队伍也不失为一种很好的选择，比如尼克斯！</span>","type":"text"},{"data":{"cont_small":{"src":"http://t12.baidu.com/it/u=746204942,3835062793&fm=173&app=25&f=JPEG?w=320&h=214&s=4A21B1445C4206D8165C79940300C09A","width":320,"height":214},"small":{"width":480,"url":"http://t11.baidu.com/it/u=3832600702,3996788134&fm=173&app=25&f=JPEG?w=480&h=360&s=4A21B1445C4206D8165C79940300C09A","height":360},"big":{"width":640,"url":"http://t10.baidu.com/it/u=519875952,4225550768&fm=173&app=49&f=JPEG?w=640&h=427&s=4B69B1445C4206D8165C79940300C09A","height":427},"original":{"low_quality_type":0,"feature_json_format":"{\"aesthetic\":2.0789813995361,\"antiporn_normal\":0.998373,\"antiporn_porn\":0.000346,\"antiporn_sexy\":0.001281,\"array\":[],\"clarity\":2.4928302764893,\"contsign\":\"1070423808,3784296485\",\"disgust\":2.3277963919099e-5,\"feature_970_topn\":[{\"cid\":201,\"val\":0.80426877737045},{\"cid\":196,\"val\":0.068790748715401},{\"cid\":213,\"val\":0.048388984054327},{\"cid\":216,\"val\":0.019802460446954},{\"cid\":212,\"val\":0.011300397105515}],\"feature_sexy_lady\":0.0017468249425292,\"main_area\":{\"height\":431,\"left\":185,\"top\":8,\"width\":440},\"porn_prob\":0.000346,\"same_feature_with_hash\":\"{\\\"same_feature_hash_id\\\":178982,\\\"same_feature_hash_ids\\\":[178982,179139,46886,47043,179137,47041,138534,138691,138689]}\"}","width":640,"image_format":"JPEG","url":"http://timg01.bdimg.com/timg?pacompress&imgtype=1&sec=1439619614&autorotate=1&di=8380aa912dfea69ac0a09deafa1a4f80&quality=100&size=b640_10053&cut_x=0&cut_y=0&cut_w=640&cut_h=427&src=http%3A%2F%2Fpic.rmb.bdstatic.com%2F9fd62844c2777a7d0683bf7c7f94f7a06850.jpeg","height":427},"original_third":{"low_quality_type":0,"feature_json_format":"{\"aesthetic\":2.0789813995361,\"antiporn_normal\":0.998373,\"antiporn_porn\":0.000346,\"antiporn_sexy\":0.001281,\"array\":[],\"clarity\":2.4928302764893,\"contsign\":\"1070423808,3784296485\",\"disgust\":2.3277963919099e-5,\"feature_970_topn\":[{\"cid\":201,\"val\":0.80426877737045},{\"cid\":196,\"val\":0.068790748715401},{\"cid\":213,\"val\":0.048388984054327},{\"cid\":216,\"val\":0.019802460446954},{\"cid\":212,\"val\":0.011300397105515}],\"feature_sexy_lady\":0.0017468249425292,\"main_area\":{\"height\":431,\"left\":185,\"top\":8,\"width\":440},\"porn_prob\":0.000346,\"same_feature_with_hash\":\"{\\\"same_feature_hash_id\\\":178982,\\\"same_feature_hash_ids\\\":[178982,179139,46886,47043,179137,47041,138534,138691,138689]}\"}","width":640,"image_format":"JPEG","url":"http://timg01.bdimg.com/timg?pacompress&imgtype=1&sec=1439619614&autorotate=1&di=8380aa912dfea69ac0a09deafa1a4f80&quality=100&size=b640_10053&cut_x=0&cut_y=0&cut_w=640&cut_h=427&src=http%3A%2F%2Fpic.rmb.bdstatic.com%2F9fd62844c2777a7d0683bf7c7f94f7a06850.jpeg","height":427},"caption":""},"type":"image"},{"data":"3.格林被重罚","data_rtf":"<span class=\"bjh-p\">3.格林被重罚</span>","type":"text"},{"data":"格林对于联盟禁赛并且罚款的处罚表示非常的惊讶，他没有想到自己的言论居然会上升到让联盟禁赛的处理，并且罚金也相当高，或许这不是这些处罚的问题，而是球队在这件事情上面的选择吧。在格林禁赛之后杜兰特带队还是拿下了今天的比赛，并且命中了关键球，看起来KD的心态似乎没有受到太大的影响！","data_rtf":"<span class=\"bjh-p\">格林对于联盟禁赛并且罚款的处罚表示非常的惊讶，他没有想到自己的言论居然会上升到让联盟禁赛的处理，并且罚金也相当高，或许这不是这些处罚的问题，而是球队在这件事情上面的选择吧。在格林禁赛之后杜兰特带队还是拿下了今天的比赛，并且命中了关键球，看起来KD的心态似乎没有受到太大的影响！</span>","type":"text"},{"data":{"cont_small":{"src":"http://t11.baidu.com/it/u=39676351,3458292294&fm=173&app=25&f=JPEG?w=320&h=229&s=0C604A860A328EDE5ED124890300C001","width":320,"height":229},"small":{"width":480,"url":"http://t12.baidu.com/it/u=3154809401,1283017158&fm=173&app=25&f=JPEG?w=480&h=360&s=0C604A860A328EDE5ED124890300C001","height":360},"big":{"width":626,"url":"http://t10.baidu.com/it/u=335444118,89395724&fm=173&app=49&f=JPEG?w=626&h=448&s=0C704A860A328ED65ED124890300C001","height":448},"original":{"low_quality_type":0,"feature_json_format":"{\"aesthetic\":2.8862612247467,\"antiporn_normal\":0.998425,\"antiporn_porn\":0.000345,\"antiporn_sexy\":0.001231,\"array\":[{\"locheight\":28,\"locleft\":567,\"loctop\":145,\"locwidth\":55,\"ocrresult\":\"E\"},{\"locheight\":77,\"locleft\":555,\"loctop\":179,\"locwidth\":68,\"ocrresult\":\"2\"}],\"clarity\":3.0663156509399,\"contsign\":\"4156732981,1969633851\",\"disgust\":2.523367811591e-6,\"feature_970_topn\":[{\"cid\":201,\"val\":0.51182115077972},{\"cid\":196,\"val\":0.38987016677856},{\"cid\":212,\"val\":0.064134918153286},{\"cid\":213,\"val\":0.016204392537475},{\"cid\":180,\"val\":0.0035316618159413}],\"feature_sexy_lady\":0.00018268177518621,\"main_area\":{\"height\":426,\"left\":2,\"top\":35,\"width\":614},\"porn_prob\":0.000345,\"same_feature_with_hash\":\"{\\\"same_feature_hash_id\\\":178860,\\\"same_feature_hash_ids\\\":[178860,178727,46764,46631,178845,46749,165036,164903,165021]}\"}","width":626,"image_format":"JPEG","url":"http://timg01.bdimg.com/timg?pacompress&imgtype=0&sec=1439619614&autorotate=1&di=beea54138af5c653b8e6a809fcda36b0&quality=100&size=b626_10012&cut_x=0&cut_y=0&cut_w=626&cut_h=448&src=http%3A%2F%2Fpic.rmb.bdstatic.com%2F39b9d6089c28c9c57ef65abbd1d2e7ec2126.png","height":448},"original_third":{"low_quality_type":0,"feature_json_format":"{\"aesthetic\":2.8862612247467,\"antiporn_normal\":0.998425,\"antiporn_porn\":0.000345,\"antiporn_sexy\":0.001231,\"array\":[{\"locheight\":28,\"locleft\":567,\"loctop\":145,\"locwidth\":55,\"ocrresult\":\"E\"},{\"locheight\":77,\"locleft\":555,\"loctop\":179,\"locwidth\":68,\"ocrresult\":\"2\"}],\"clarity\":3.0663156509399,\"contsign\":\"4156732981,1969633851\",\"disgust\":2.523367811591e-6,\"feature_970_topn\":[{\"cid\":201,\"val\":0.51182115077972},{\"cid\":196,\"val\":0.38987016677856},{\"cid\":212,\"val\":0.064134918153286},{\"cid\":213,\"val\":0.016204392537475},{\"cid\":180,\"val\":0.0035316618159413}],\"feature_sexy_lady\":0.00018268177518621,\"main_area\":{\"height\":426,\"left\":2,\"top\":35,\"width\":614},\"porn_prob\":0.000345,\"same_feature_with_hash\":\"{\\\"same_feature_hash_id\\\":178860,\\\"same_feature_hash_ids\\\":[178860,178727,46764,46631,178845,46749,165036,164903,165021]}\"}","width":626,"image_format":"JPEG","url":"http://timg01.bdimg.com/timg?pacompress&imgtype=0&sec=1439619614&autorotate=1&di=beea54138af5c653b8e6a809fcda36b0&quality=100&size=b626_10012&cut_x=0&cut_y=0&cut_w=626&cut_h=448&src=http%3A%2F%2Fpic.rmb.bdstatic.com%2F39b9d6089c28c9c57ef65abbd1d2e7ec2126.png","height":448},"caption":""},"type":"image"},{"data":"你们觉得格林这样的话会对勇士造成什么样的后果呢？","data_rtf":"<span class=\"bjh-p\">你们觉得格林这样的话会对勇士造成什么样的后果呢？</span>","type":"text"},{"data":"","data_rtf":"<span class=\"bjh-p\"></span>","type":"text"}]},"news_lda":[[743,0.3598039215686274],[998,0.03865546218487395],[855,0.02521008403361345],[184,0.02282913165266106],[616,0.02100840336134454],[200,0.01862745098039216],[168,0.01512605042016807],[304,0.01456582633053221],[1235,0.01358543417366947],[1325,0.01344537815126051],[1483,0.01330532212885154],[1257,0.01316526610644258],[1243,0.01288515406162465],[277,0.01274509803921569],[1228,0.01274509803921569],[20,0.01260504201680672],[581,0.0123249299719888],[1208,0.01218487394957983],[1283,0.01204481792717087],[538,0.01148459383753501],[614,0.01120448179271709],[1400,0.01106442577030812],[565,0.009943977591036414],[1134,0.00938375350140056],[298,0.008823529411764706],[1387,0.008823529411764706],[989,0.008683473389355743],[1116,0.008543417366946778],[577,0.008543417366946778],[1355,0.008403361344537815],[589,0.008263305322128852],[1180,0.008123249299719889],[290,0.007983193277310924],[1464,0.007563025210084034],[47,0.006582633053221289],[334,0.006582633053221289],[1392,0.006582633053221289],[1412,0.006442577030812325],[1039,0.006442577030812325],[913,0.006442577030812325],[1121,0.006302521008403362],[404,0.006162464985994398],[1446,0.006022408963585434],[1375,0.005742296918767507],[339,0.00546218487394958],[849,0.005042016806722689],[211,0.004901960784313725],[526,0.004481792717086834],[740,0.004481792717086834],[1059,0.004341736694677871],[523,0.004341736694677871],[232,0.004341736694677871],[629,0.004341736694677871],[553,0.004341736694677871],[215,0.004341736694677871],[1055,0.004201680672268907],[235,0.004201680672268907],[934,0.004201680672268907],[161,0.004201680672268907],[540,0.004201680672268907],[533,0.004201680672268907],[1222,0.004201680672268907],[839,0.004201680672268907],[1471,0.004061624649859944],[1264,0.00392156862745098],[520,0.00392156862745098],[726,0.003781512605042017],[1035,0.003781512605042017],[735,0.003781512605042017],[1132,0.003781512605042017],[763,0.003641456582633053],[845,0.003361344537815126],[224,0.003221288515406162],[579,0.003221288515406162],[764,0.002661064425770308],[980,0.00196078431372549],[907,0.00196078431372549],[463,0.001820728291316527],[1249,0.001820728291316527],[766,0.001680672268907563],[82,0.0007002801120448179],[1131,0.0007002801120448179],[1082,0.0007002801120448179],[1177,0.0005602240896358543],[955,0.0005602240896358543],[923,0.0005602240896358543],[1388,0.0004201680672268908],[72,0.0004201680672268908],[1130,0.0002801120448179272],[945,0.0002801120448179272],[127,0.0002801120448179272],[894,0.0002801120448179272],[10,0.0002801120448179272],[430,0.0001400560224089636],[1024,0.0001400560224089636],[1022,0.0001400560224089636],[871,0.0001400560224089636]],"m_from":"3","news_category_id":3,"PIP_HEADER":{"Priority":"9","Product":"meitihao","Extra-data":{"spider_t":1542244998224,"dc_t":1542244999424},"Url":"http://baijiahao.baidu.com/s?id=1617161057838710995"},"content_simhash64":13032784495958597422,"score_attraction":3.2924832245410558E-17,"author_quality_score":-1,"gram_check_level":0,"product":"meitihao","local_authority_info":{"level":0,"from":""},"m_ext":"{\"8\":{\"long_summary\":\"杜兰特因为格林在比赛最后时间出现致命失误而指责格林，他表示“你应该把那该死的球给我！”格林随后便在替补席跟杜兰特对喷了起来，而据说二人的战火一直延伸到更衣室，而且越吵越凶，这次吵架的程度已经远远超过了平时，甚至卷入了明年夏天两人离队的问题，也谈及了杜兰特加盟勇士的问题。你们觉得格林这样的话会对勇士造成什么样的后果呢？\"},\"displaytype_exinfo\":\"{\\\"comment_thread_id\\\":\\\"1057000010018096\\\"}\",\"ext_info\":{\"ABTEST\":{\"mode\":\"1\",\"repo\":\"9\"},\"audit_type\":\"00000000\",\"author_level\":\"fresh\",\"can_edit_title\":1,\"cat_high_quality_score\":\"2\",\"group_key_info\":{\"level\":1,\"level_original_val\":\"2\",\"level_plan\":[],\"level_type\":2,\"level_val\":\"2\",\"original_status\":1,\"source_type\":\"platform\",\"sub_type\":\"individual\"},\"has_edited_times\":0,\"has_rtf\":1,\"has_spd\":0,\"is_pay\":0,\"machine_audit_white\":1,\"mthvideo\":0,\"original_recog_serv_ret\":{\"key_info\":{\"content\":\"格林随后便在替补席跟杜兰特对喷了起来而据说二人的战火一直延伸到更衣室而且越吵越凶这次吵架的程度已经远远超过了平时甚至卷入了明年夏天两人离队的问题也谈及了杜兰特加盟勇士的问题\",\"dedupid\":\"822978851446636755\",\"time\":1542244996,\"title\":\"格林：你来之前勇士就夺冠了！杜兰特：这就是我要离开的理由？\",\"url\":\"http://baijiahao.baidu.com/s?id=1617161057838710995\"},\"recog_ret\":\"REFER\",\"sim_cnt\":3,\"sim_list\":[{\"sim\":1.0,\"src\":0,\"url_info\":{\"content\":\"NULL\",\"time\":1542207649,\"title\":\"格林：你来之前勇士就夺冠了！杜兰特：这就是我要离开的理由？\",\"url\":\"http://www.toutiao.com/a6623725410486075918/\"}},{\"sim\":1.0,\"src\":0,\"url_info\":{\"content\":\"NULL\",\"time\":1542207258,\"title\":\"格林：你来之前勇士就夺冠了！杜兰特：这就是我要离开的理由？\",\"url\":\"http://www.toutiao.com/item/6623725410486075918/\"}},{\"sim\":1.0,\"src\":0,\"url_info\":{\"content\":\"NULL\",\"time\":1542206202,\"title\":\"格林：你来之前勇士就夺冠了！杜兰特：这就是我要离开的理由？\",\"url\":\"http://baijiahao.baidu.com/s?id=1617120342100474101&wfr=spider&for=pc\"}}]},\"original_status\":\"0\",\"pay_money\":0,\"picture_small_flow\":1,\"replicate_original\":\"7876865519557377016\",\"site_type\":0,\"which_title\":0},\"innersource_id\":\"\",\"mthid\":\"1579750318596649\",\"passport_id\":\"818639858\",\"sourceid\":80001}","is_scarce_sub_category_v1":1,"news_hierarchy":[{"path":[["nba=>篮球=>球类运动=>体育项目=>体育",252]],"topic":"篮球"}],"content_simhash":"60348128255928098438075500898709340487","title_defect_bad_str":"","para_num":10,"news_importance":0,"title_nerl_plus":[["格林","1007","0","4"],["：","","4","2"],["你","","6","2"],["来","","8","2"],["之","","10","2"],["前","","12","2"],["勇士","","14","4"],["就","","18","2"],["夺冠","","20","4"],["了","","24","2"],["！","","26","2"],["杜兰特","1007","28","6"],["：","","34","2"],["这","","36","2"],["就","","38","2"],["是","","40","2"],["我","","42","2"],["要","","44","2"],["离开","","46","4"],["的","","50","2"],["理由","","52","4"],["？","","56","2"]],"url":"http://baijiahao.baidu.com/s?id=1617161057838710995","visual_attention":{"体育-篮球":0.97864},"metaapi_versionkey":1542245060431,"disgust_level":0,"filter":0,"site":"baijiahao.baidu.com","tj_ldas":[[93,192],[81,20],[27,16],[97,11],[17,9]],"new_sex_level_rule":0,"novelty_feed_sim":0.984159574382961,"original_url":"","img_urls":"{\"image_score_beta\": [{\"url\": \"http://t12.baidu.com/it/u=1365764711,3647442306&fm=173&app=49&f=JPEG?w=218&h=146&s=C8B485531CA26E96228984CE03003030\", \"image_score_beta\": 139.17809242173894, \"width\": 218, \"height\": 146}, {\"url\": \"http://t10.baidu.com/it/u=2841713241,2378248271&fm=173&app=49&f=JPEG?w=218&h=146&s=2C724A874102055356E120890300C001\", \"image_score_beta\": 138.69510690989912, \"width\": 218, \"height\": 146}, {\"url\": \"http://t11.baidu.com/it/u=2071510171,4167771805&fm=173&app=49&f=JPEG?w=218&h=146&s=4A2DB944571A05D0165C79900300C09A\", \"image_score_beta\": 137.82072057038295, \"width\": 218, \"height\": 146}], \"author_img\": {\"original\": {\"url\": \"http://timg01.bdimg.com/timg?pa&Imgtype=0&sec=1439619614&di=0c44a0420ede1793c52d27b8f829cf19&quality=90&size=b870_10000&src=http%3A%2F%2Ftimg01.bdimg.com%2Ftimg%3Fpacompress%3D%26imgtype%3D0%26sec%3D1439619614%26autorotate%3D1%26di%3D6ba90d9414df1fafac5179bc6875b625%26quality%3D90%26size%3Db200_200%26src%3Dhttp%253A%252F%252Fpic.rmb.bdstatic.com%252Fba285fa96becc2d32b6467614c613096.png\", \"width\": 0, \"height\": 0}}, \"imgurls\": [{\"url\": \"http://t12.baidu.com/it/u=1374271388,330070670&fm=173&app=25&f=JPEG?w=218&h=146&s=AF3A6986DF3305AFD67409160300C0C0\", \"width\": 218, \"height\": 146}, {\"url\": \"http://t11.baidu.com/it/u=1823161033,802682391&fm=173&app=25&f=JPEG?w=218&h=146&s=C4B48D7396B26BBF228984CE03003030\", \"width\": 218, \"height\": 146}, {\"url\": \"http://t11.baidu.com/it/u=2491520128,3288308671&fm=173&app=25&f=JPEG?w=218&h=146&s=4A21B1445C0204D8165C79900300D09A\", \"width\": 218, \"height\": 146}], \"bimgurls\": null, \"gimgurls\": [{\"url\": \"http://t11.baidu.com/it/u=3892753285,3515264900&fm=173&app=25&f=JPEG?w=536&h=302&s=AF3A6986DF3305AFD67409160300C0C0\", \"width\": 536, \"height\": 302}, {\"url\": \"http://t12.baidu.com/it/u=3842881622,2420785904&fm=173&app=25&f=JPEG?w=435&h=245&s=C4B48D7396B26BBF228984CE03003030\", \"width\": 435, \"height\": 245}, {\"url\": \"http://t11.baidu.com/it/u=2520291361,2019214235&fm=173&app=25&f=JPEG?w=637&h=358&s=4A21B1445C0204D8165C79900300D09A\", \"width\": 637, \"height\": 358}]}","novelty_copy_score":0.0,"author_authority_score":-1,"logid":1617161058238645020,"source_id":80001,"url_3g":"","m_display_type":"3","public_time":1542244996,"plsa":{"138":379,"130":763,"141":1367,"142":877,"43":376},"feedcms_operation_oldnews":0,"real_time":1542206193,"command_no":1,"tag_square":427.1873125456794,"new_sex_score":0.01551013721694907,"title_ner":[["格林","PER","nr"],["：","NOR","w"],["你","NOR","r"],["来","NOR","v"],["之","NOR","u"],["前","NOR","f"],["勇士","NOR","n"],["就","NOR","d"],["夺冠","NOR","v"],["了","NOR","y"],["！","NOR","w"],["杜兰特","PER","nr"],["：","NOR","w"],["这就是我","NOR","r"],["要","NOR","v"],["离开","NOR","v"],["的","NOR","u"],["理由","NOR","n"],["？","NOR","w"]],"base_weight":50,"elevate_ratio":{"bs":1.2,"grc":1.0,"ucf":1.2,"matchnet":1.2,"gr":1.0,"icf":1.2,"cb":1.2},"thread_id":"1057000010018096","title_attentions":{"杜兰特":517},"rule_quality_level":3,"is_valid_attention":1,"anti_spam":{"source_id_status":"normal","url_status":"normal","tradition_char":0,"reprint_from":"子午体育","title_weirdochat_status":"normal","content_inferior_status":"normal","mthid_status":"white","nid_status":"normal","template_mthid":1.0,"title_inferior_status":"normal"},"content_len":1847,"copy_level":3,"mth_data":{"author_level":"fresh","cat_high_quality_score":2.0},"small_big_lists":"[{\"big_list\":{\"height\":318,\"src\":\"http://t10.baidu.com/it/u=607955469,1468542160&fm=173&app=49&f=JPEG?w=566&h=318&s=AF3A7986D72305AFC6751937030010C0\",\"width\":566},\"small_list\":{\"height\":146,\"image_score\":2.82550716400150,\"image_score_alpha\":1.0,\"image_score_alpha_desc\":\"image_score_alpha_20170407_beta1,cal four scores for test\",\"image_score_beta\":2.83724164962770,\"image_score_beta_desc\":\"image_score_beta_20170407_beta1,cal four scores for test\",\"image_score_delta\":2.82550716400150,\"image_score_delta_desc\":\"image_score_delta_20170407_beta1,cal four scores for test\",\"image_score_desc\":\"image_score_20170407_beta1,cal four scores for test\",\"src\":\"http://t11.baidu.com/it/u=3785180524,3611444518&fm=173&app=25&f=JPEG?w=218&h=146&s=EF7A31C6D73305AFD67409170300D0C0\",\"width\":218},\"small_list_smallflow\":{\"height\":146,\"src\":\"http://t12.baidu.com/it/u=770154650,3377546254&fm=173&app=49&f=JPEG?w=218&h=146&s=EF7A39C6D5231CAEF27401360300D0C0\",\"width\":218}},{\"big_list\":{\"height\":244,\"src\":\"http://t11.baidu.com/it/u=2709813412,2403141027&fm=173&app=49&f=JPEG?w=435&h=244&s=E4B4857380A266B75815ACCE0300F030\",\"width\":435},\"small_list\":{\"height\":146,\"image_score\":2.96887707710270,\"image_score_alpha\":1.0,\"image_score_alpha_desc\":\"image_score_alpha_20170407_beta1,cal four scores for test\",\"image_score_beta\":2.98303198814390,\"image_score_beta_desc\":\"image_score_beta_20170407_beta1,cal four scores for test\",\"image_score_delta\":2.96887707710270,\"image_score_delta_desc\":\"image_score_delta_20170407_beta1,cal four scores for test\",\"image_score_desc\":\"image_score_20170407_beta1,cal four scores for test\",\"src\":\"http://t10.baidu.com/it/u=1824154230,145598036&fm=173&app=25&f=JPEG?w=218&h=146&s=E4948D739EB26FBF2A8884CE03007030\",\"width\":218},\"small_list_smallflow\":{\"height\":146,\"src\":\"http://t12.baidu.com/it/u=1365764711,3647442306&fm=173&app=49&f=JPEG?w=218&h=146&s=C8B485531CA26E96228984CE03003030\",\"width\":218}},{\"big_list\":{\"height\":360,\"src\":\"http://t12.baidu.com/it/u=2283502448,558441111&fm=173&app=49&f=JPEG?w=640&h=360&s=0A21F1045C5207D616D8799403005098\",\"width\":640},\"small_list\":{\"height\":146,\"image_score\":3.14642763137820,\"image_score_alpha\":1.0,\"image_score_alpha_desc\":\"image_score_alpha_20170407_beta1,cal four scores for test\",\"image_score_beta\":3.15078353881840,\"image_score_beta_desc\":\"image_score_beta_20170407_beta1,cal four scores for test\",\"image_score_delta\":3.14642763137820,\"image_score_delta_desc\":\"image_score_delta_20170407_beta1,cal four scores for test\",\"image_score_desc\":\"image_score_20170407_beta1,cal four scores for test\",\"src\":\"http://t12.baidu.com/it/u=2025074930,2273287304&fm=173&app=25&f=JPEG?w=218&h=146&s=4A21B1445C4206D8165C79940300C09A\",\"width\":218},\"small_list_smallflow\":{\"height\":146,\"src\":\"http://t11.baidu.com/it/u=2071510171,4167771805&fm=173&app=49&f=JPEG?w=218&h=146&s=4A2DB944571A05D0165C79900300C09A\",\"width\":218}},{\"big_list\":{\"height\":352,\"src\":\"http://t12.baidu.com/it/u=2695463699,802312504&fm=173&app=49&f=JPEG?w=626&h=352&s=2C707A86CC3287D626E1B08803008001\",\"width\":626},\"small_list\":{\"height\":146,\"image_score\":3.35257506370540,\"image_score_alpha\":1.0,\"image_score_alpha_desc\":\"image_score_alpha_20170407_beta1,cal four scores for test\",\"image_score_beta\":3.35677766799930,\"image_score_beta_desc\":\"image_score_beta_20170407_beta1,cal four scores for test\",\"image_score_delta\":3.35257506370540,\"image_score_delta_desc\":\"image_score_delta_20170407_beta1,cal four scores for test\",\"image_score_desc\":\"image_score_20170407_beta1,cal four scores for test\",\"src\":\"http://t10.baidu.com/it/u=3792295749,2026686372&fm=173&app=25&f=JPEG?w=218&h=146&s=0C604A860A328EDE5ED124890300C001\",\"width\":218},\"small_list_smallflow\":{\"height\":146,\"src\":\"http://t10.baidu.com/it/u=2841713241,2378248271&fm=173&app=49&f=JPEG?w=218&h=146&s=2C724A874102055356E120890300C001\",\"width\":218}}]","resource_status":"white","importance_model_score":1.767577,"informative_score":0.43991619348526,"news_attraction":0,"author_brand_info":{"author_brand_authority_score":0.7532,"news_author_brand_spread_level":2,"group_code":["100000"],"news_author_brand_verticality_detail":{"cate":{"name_mismatch":0,"wishes_mishmatch":0,"detail":{"美食":0.06,"汽车":0.4,"体育":0.38,"nids":70138}},"sub_cate":{"name_mismatch":0,"wishes_mishmatch":0,"detail":{"日本汽车":0.03,"综合":0.45,"SUV":0.04,"nids":60710,"NBA":0.13,"国产车":0.03}}},"news_author_brand_interaction_score":0.373,"news_author_brand_spread_detail":{"nids":57482,"share_all":2015,"share_avg":0.0351,"click_all":613880,"click_avg":10.6795},"news_author_brand_health_detail":{"low_quality":1,"fresh":0,"pattern_filter":1,"negative_comment":0},"news_author_brand_level":2,"author_brand_authority_detail":{"vert_level_news":-1,"vert_level_video":-1,"bjh_fans":159948,"toutiao_fans":0,"toutiao_is_v":-1,"bjh_is_v":1},"news_author_brand_health_level":0,"news_author_brand_verticality_level":3,"author_brand_authority_level":3,"news_group":1,"news_author_brand_health_score":0.0,"news_author_brand_verticality_score":0.602,"news_author_brand_spread_score":0.4632,"news_author_brand_interaction_level":1,"news_author_brand_interaction_detail":{"avg_like_num":0.0009,"comment_num":8014,"avg_comment_num":0.1394,"like_num":50,"news_num":57482,"follower_num":491,"avg_follower_num":0.0085,"avg_collect_num":0.0342,"collect_num":1967,"click_num":613880,"avg_share_num":0.0351,"share_num":2015},"news_author_brand_score":0.3577},"general_tag":{"体育_NBA球员动态":841},"news_clickbait_level":0,"news_sub_category":"NBA","img_urls_new":"","page_weight":38.65598342895093,"title_defect_level":0,"news_title_attraction_ext_info":{"loc":0,"basiclen":22,"d":3.0,"nr":4.0,"phraselen":19,"exclam":2.0,"m":0,"n":4.0,"comma":0,"r":5.0,"v":9.0,"w":8.0,"pj":1,"gbklen":58},"cluster_optimized":508652,"news_attentions_id":{"格林-->>德雷蒙德·格林":"1850q3","勇士比赛":"1lqxwk","篮球":"1fgs_6","杜兰特":"10_stj","nba":"1td1cv","杜兰特加盟勇士":"129w7q"},"ctype":1,"similar_sign":"4090282972 3333108936","category_tag":"","quality_package":8482000,"event_cluster":{"event_info":{"gcid":10002310857691730727}},"speed_push":0,"title_term":{"这就是我":21,"理由":21,"格林":22,"离开":34,"杜兰特":22,"夺冠":34,"勇士":21},"pic_isdel":0,"cont_sign":"2924126916 3074669004","news_attention":{"格林-->>德雷蒙德·格林":527,"勇士比赛":318,"篮球":236,"杜兰特":517,"nba":246,"杜兰特加盟勇士":388},"news_category_v1_prob":0.6584,"ptype":0,"pages_url":[],"duplicate_sign":"2804939461 4119578056","img_urls_num":3,"m_calc_time":"1542244999","audite":{"is_audit":0,"audit_info":""},"path_exinfo":"","cms_editor_news_category":"体育明星","score_topic_long_weibo":0.01141313855351411,"cluster_id":0,"nlpc_title_seg":["格林","你","来","之前","勇士","就","夺冠","了","杜兰特","这就是我","要","离开","理由"],"novelty_feed_time":1542206193,"intr_term":{"这就是我":42,"明年夏天":30,"子午":26,"禁赛":34,"失误":26,"格林":128,"离开":37,"杜兰特":157,"夺冠":27,"勇士":112},"vertical_level_bak":2,"m_image_urls":"{\"image_score_beta\": [{\"url\": \"http://t12.baidu.com/it/u=1365764711,3647442306&fm=173&app=49&f=JPEG?w=218&h=146&s=C8B485531CA26E96228984CE03003030\", \"image_score_beta\": 139.17809242173894, \"width\": 218, \"height\": 146}, {\"url\": \"http://t10.baidu.com/it/u=2841713241,2378248271&fm=173&app=49&f=JPEG?w=218&h=146&s=2C724A874102055356E120890300C001\", \"image_score_beta\": 138.69510690989912, \"width\": 218, \"height\": 146}, {\"url\": \"http://t11.baidu.com/it/u=2071510171,4167771805&fm=173&app=49&f=JPEG?w=218&h=146&s=4A2DB944571A05D0165C79900300C09A\", \"image_score_beta\": 137.82072057038295, \"width\": 218, \"height\": 146}], \"author_img\": {\"original\": {\"url\": \"http://timg01.bdimg.com/timg?pa&Imgtype=0&sec=1439619614&di=0c44a0420ede1793c52d27b8f829cf19&quality=90&size=b870_10000&src=http%3A%2F%2Ftimg01.bdimg.com%2Ftimg%3Fpacompress%3D%26imgtype%3D0%26sec%3D1439619614%26autorotate%3D1%26di%3D6ba90d9414df1fafac5179bc6875b625%26quality%3D90%26size%3Db200_200%26src%3Dhttp%253A%252F%252Fpic.rmb.bdstatic.com%252Fba285fa96becc2d32b6467614c613096.png\", \"width\": 0, \"height\": 0}}, \"imgurls\": [{\"url\": \"http://t12.baidu.com/it/u=1374271388,330070670&fm=173&app=25&f=JPEG?w=218&h=146&s=AF3A6986DF3305AFD67409160300C0C0\", \"width\": 218, \"height\": 146}, {\"url\": \"http://t11.baidu.com/it/u=1823161033,802682391&fm=173&app=25&f=JPEG?w=218&h=146&s=C4B48D7396B26BBF228984CE03003030\", \"width\": 218, \"height\": 146}, {\"url\": \"http://t11.baidu.com/it/u=2491520128,3288308671&fm=173&app=25&f=JPEG?w=218&h=146&s=4A21B1445C0204D8165C79900300D09A\", \"width\": 218, \"height\": 146}], \"bimgurls\": null, \"gimgurls\": [{\"url\": \"http://t11.baidu.com/it/u=3892753285,3515264900&fm=173&app=25&f=JPEG?w=536&h=302&s=AF3A6986DF3305AFD67409160300C0C0\", \"width\": 536, \"height\": 302}, {\"url\": \"http://t12.baidu.com/it/u=3842881622,2420785904&fm=173&app=25&f=JPEG?w=435&h=245&s=C4B48D7396B26BBF228984CE03003030\", \"width\": 435, \"height\": 245}, {\"url\": \"http://t11.baidu.com/it/u=2520291361,2019214235&fm=173&app=25&f=JPEG?w=637&h=358&s=4A21B1445C0204D8165C79900300D09A\", \"width\": 637, \"height\": 358}]}","dispatch_num":0,"vertical_type":0,"news_sub_category_v2":"NBA","soft_level":0,"news_sub_category_v1":"NBA","score_topic":36.92766268013405,"title_content_non_sim_level":0,"tj_news_timeliness_attention":[["格林-->>德雷蒙德·格林",527],["杜兰特",517],["杜兰特加盟勇士",388],["勇士比赛",318],["nba",246]],"new_locname":[{}],"author_health_rank":0.94,"penetration":0,"news_attraction_model":1,"click_estimate_score":2.613344490587099,"gd_brand_info":{"sentiment":2,"subject":"格林,前,勇士,杜兰特,理由"},"gram_check_score":0.0,"news_location_level":"2","long_summary":"杜兰特因为格林在比赛最后时间出现致命失误而指责格林，他表示“你应该把那该死的球给我！”格林随后便在替补席跟杜兰特对喷了起来，而据说二人的战火一直延伸到更衣室，而且越吵越凶，这次吵架的程度已经远远超过了平时，甚至卷入了明年夏天两人离队的问题，也谈及了杜兰特加盟勇士的问题。你们觉得格林这样的话会对勇士造成什么样的后果呢？","pctr_1":0.04936909651036827,"author_type":-1,"discomfort_level":0,"ecnet_level":0,"m_content_sign":"13205602821129020100","locname":[{}],"m_ext_type":"8","category":3,"news_category":"体育","news_category_mul_v2":{"体育":0.9999901},"porn_level":0}],"error":"success","status":{"9420830529692060020":0}}